Workbook

Sheet 計画
A2: 設置店舗数 | B2: =M2+AE2+BE2+BO2+AN2+AH2+T2+AQ2 -> 32 | C2: 1 | D2: 1 | E2: 1 | F2: 1 | G2: 1 | H2: 1 | I2: 2 | M2: 3 | N2: 1 | O2: 1 | P2: 1 | Q2: 2 | S2: 3 | T2: 3 | U2: 1 | V2: 1 | W2: 1 | X2: 2 | Y2: 2 | Z2: 3 | AB2: 4 | AD2: 5 | AE2: 5 | AF2: 1 | AG2: 1 | AH2: 2 | AI2: 1 | AJ2: 1 | AK2: 2 | AL2: 2 | AN2: 2 | AO2: 1 | AP2: 2 | AQ2: 3 | AS2: 1 | AT2: 2 | AU2: 2 | AV2: 3 | AW2: 3 | AX2: 3 | AY2: 4 | AZ2: 4 | BA2: 4 | BB2: 5 | BC2: 5 | BD2: 6 | BE2: 7 | BF2: 1 | BG2: 1 | BH2: 2 | BI2: 3 | BJ2: 4 | BK2: 5 | BL2: 6 | BM2: 6 | BO2: 7 | BP2: =M2+AE2+AH2+AN2+AQ2+BE2+BO2+T2 -> 32 | BQ2: 店舗
A3: 45931 | B3: 合計 | C3: 福重 | D3: 福重② | E3: 福重③ | F3: 福重④ | G3: 福重⑤ | H3: 福重⑥ | I3: 那珂川 | K3: 西新 | M3: 唐津 | N3: 飯塚 | O3: 飯塚② | P3: 飯塚③ | Q3: 小倉 | S3: 黒崎 | T3: 黒崎② | U3: 宗像 | V3: 宗像② | W3: 宗像③ | X3: 魚町 | Y3: 魚町② | Z3: 鞍手 | AB3: 長府② | AC3: 宇部① | AD3: 宇部② | AE3: 宇部③ | AF3: 佐賀① | AG3: 佐賀② | AH3: 八女 | AI3: 都城① | AJ3: 都城② | AK3: 鹿屋① | AL3: 鹿屋② | AN3: 鹿屋500 | AO3: 浜町 | AP3: 時津 | AQ3: 大村 | AS3: 菊陽② | AT3: 宇宿① | AV3: 霧島① | AW3: 霧島② | AX3: 霧島500 | AY3: 川内① | AZ3: 川内② | BA3: 川内500 | BB3: 合志 | BC3: 合志 | BD3: 南熊本 | BE3: 下通 | BF3: 今宿 | BG3: 今宿➁ | BH3: 八代 | BI3: 佐世保 | BJ3: 別府 | BK3: 行橋 | BL3: 延岡① | BM3: 延岡② | BO3: 光吉
A4: 設置台数 | B4: 57 | C4: 500GACHA | D4: 1000GACHA | E4: ティアラ | F4: ティアラ | G4: ティアラ | H4: ティアラ | I4: 1000GACHA | M4: 1000GACHA | N4: 1000GACHA | O4: デカプセル | P4: ティアラ | Q4: ティアラ | S4: ティアラ | T4: 1000GACHA | U4: ガチャコロ1 | V4: 500GATCHA | W4: 500GATCHA | X4: ティアラ | Y4: 1000GACHA | Z4: ガチャコロ2 | AB4: 1000GACHA | AC4: ティアラ | AD4: 1000GACHA | AE4: 1000GACHA | AF4: 1000GACHA | AG4: ガチャコロ2 | AH4: ガチャコロ２ | AI4: ティアラ | AJ4: 1000GACHA | AK4: 1000GACHA | AL4: 1000GACHA | AN4: 500GATCHA | AO4: 1000GACHA | AP4: ガチャコロ２ | AQ4: ガチャコロ２ | AS4: ガチャコロ２ | AT4: 1000GACHA | AV4: 1000GACHA | AW4: ティアラ | AX4: 500GATCHA | AY4: 1000GACHA | AZ4: ティアラ | BA4: 500GATCHA | BB4: ガチャコロ２ | BC4: 500GACHA | BD4: ティアラ | BE4: ガチャコロ２ | BF4: 1000GACHA | BG4: ガチャコロ2 | BH4: ガチャコロ２ | BI4: ティアラ | BJ4: ティアラ | BK4: ガチャコロ2 | BL4: 1000GACHA | BM4: 1000GACHA | BO4: ティアラ
A5: ロッカー台数 | B5: =SUM(C5:BO5) -> 146 | C5: 2 | D5: 2 | E5: 3 | F5: 3 | G5: 3 | H5: 3 | I5: 2 | M5: 2 | N5: 2 | O5: 4 | P5: 3 | Q5: 2 | S5: 2 | T5: 2 | U5: 3 | V5: 2 | W5: 0 | X5: 6 | Y5: 2 | Z5: 4 | AB5: 2 | AC5: 2 | AD5: 2 | AE5: 2 | AF5: 3 | AG5: 2 | AH5: 4 | AI5: 2 | AJ5: 2 | AK5: 3 | AL5: 3 | AN5: 2 | AO5: 2 | AP5: 4 | AQ5: 2 | AS5: 4 | AT5: 1 | AV5: 3 | AW5: 3 | AX5: 2 | AY5: 3 | AZ5: 3 | BA5: 2 | BB5: 4 | BC5: 3 | BD5: 2 | BE5: 3 | BF5: 2 | BG5: 4 | BH5: 4 | BI5: 2 | BJ5: 2 | BK5: 4 | BL5: 2 | BM5: 2 | BO5: 2 | BP5: =SUM(C5:BO5) -> 146 | BQ5: ロッカー
A6: カプセル容量 | C6: 300 | D6: 300 | E6: 300 | F6: 300 | G6: 300 | H6: 300 | I6: 300 | M6: 300 | N6: 300 | O6: 300 | P6: 300 | Q6: 300 | S6: 300 | T6: 300 | U6: 400 | V6: 150 | W6: 150 | X6: 150 | Y6: 300 | Z6: 400 | AB6: 300 | AC6: 300 | AD6: 300 | AE6: 300 | AF6: 300 | AG6: 400 | AH6: 400 | AI6: 300 | AJ6: 300 | AK6: 300 | AL6: 300 | AN6: 300 | AO6: 300 | AP6: 400 | AQ6: 400 | AS6: 400 | AT6: 300 | AV6: 300 | AW6: 300 | AX6: 300 | AY6: 300 | AZ6: 300 | BA6: 300 | BB6: 400 | BC6: 300 | BD6: 300 | BE6: 400 | BF6: 300 | BG6: 400 | BH6: 400 | BI6: 300 | BJ6: 300 | BK6: 400 | BL6: 300 | BM6: 300 | BO6: 300
A7: ガチャの種類 | C7: バラエティー | D7: バラエティー | E7: スニーカー | F7: ゲームソフト | G7: ブランド | H7: ゲーム機 | I7: バラエティー | M7: バラエティー | N7: バラエティー | O7: バラエティー | P7: スニーカー | Q7: バラエティー | S7: バラエティー | T7: バラエティー | U7: バラエティー | V7: バラエティー | W7: バラエティー | X7: バラエティー | Y7: ポケモン | Z7: バラエティー | AB7: バラエティー | AC7: バラエティー | AD7: バラエティー | AE7: バラエティー(ポケモン） | AF7: バラエティー | AG7: バラエティー | AH7: バラエティー | AI7: バラエティー | AJ7: バラエティー | AK7: バラエティー | AL7: バラエティー | AN7: バラエティー | AO7: バラエティー | AP7: バラエティー | AQ7: バラエティー | AS7: バラエティー | AT7: バラエティー | AV7: バラエティー | AW7: バラエティー | AX7: ポケモン | AY7: バラエティー | AZ7: バラエティー | BA7: ポケモン | BB7: バラエティー | BC7: バラエティー | BD7: バラエティー | BE7: バラエティー | BF7: バラエティー | BG7: バラエティー | BH7: バラエティー | BI7: バラエティー | BJ7: バラエティー | BK7: バラエティー | BL7: バラエティー | BM7: バラエティー | BO7: バラエティー | BP7: ティアラ | BQ7: 26
A8: プレイ料金 | C8: 500 | D8: 2000 | E8: 2000 | F8: 1000 | G8: 2000 | H8: 2000 | I8: 2000 | M8: 1000 | N8: 1000 | O8: 2000 | P8: 2000 | Q8: 1000 | S8: 2000 | T8: 1000 | U8: 2000 | V8: 500 | W8: 500 | X8: 2000 | Y8: 1000 | Z8: 2000 | AB8: 1000 | AC8: 1000 | AD8: 2000 | AE8: 2000 | AF8: 1000 | AG8: 2000 | AH8: 1000＆2000 | AI8: 1000 | AJ8: 2000 | AK8: 1000 | AL8: 2000 | AN8: 500 | AO8: 1000 | AP8: 1000＆2000 | AQ8: 1000＆2000 | AS8: 2000 | AT8: 2000 | AV8: 1000 | AW8: 2000 | AX8: 500 | AY8: 1000 | AZ8: 2000 | BA8: 500 | BB8: 2000 | BC8: 500 | BD8: 1000 | BE8: 1000＆2000 | BF8: 1000 | BG8: 2000 | BH8: 1000＆2000 | BI8: 1000 | BJ8: 2000 | BK8: 1000＆2000 | BL8: 1000 | BM8: 2000 | BO8: 2000 | BP8: ガチャコロ1 | BQ8: 2
A9: 前年度 | B9: =SUM(C9:BO9) -> 7025100 | C9: 74500 | D9: 306000 | I9: 109000 | J9: 240000 | K9: 223000 | L9: 222000 | M9: 123000 | N9: 94000 | O9: 244000 | Q9: 119000 | S9: 158000 | T9: 110000 | U9: 224000 | V9: 23000 | W9: 22000 | X9: 86000 | Y9: 84000 | Z9: 124000 | AB9: 156000 | AF9: 61000 | AG9: 272000 | AH9: 151000 | AI9: 111000 | AJ9: 148000 | AO9: 118000 | AP9: 118000 | AQ9: 139000 | AS9: 470000 | AT9: 56000 | AU9: 103000 | AV9: 166000 | AW9: 154000 | AX9: 65300 | AY9: 206000 | AZ9: 188000 | BA9: 112800 | BB9: 125000 | BC9: 61500 | BE9: 631000 | BF9: 55000 | BG9: 106000 | BH9: 61000 | BI9: 75000 | BJ9: 108000 | BK9: 195000 | BL9: 87000 | BM9: 80000 | BO9: 60000 | BP9: ガチャコロ2 | BQ9: 10
A10: 目標 | B10: =SUM(C10:BO10) -> 9310000 | C10: 90000 | D10: 300000 | E10: 110000 | F10: 150000 | G10: 100000 | H10: 150000 | I10: 300000 | M10: 200000 | N10: 140000 | O10: 250000 | P10: 200000 | Q10: 140000 | S10: 250000 | T10: 250000 | U10: 350000 | V10: 40000 | W10: 40000 | X10: 120000 | Y10: 150000 | Z10: 300000 | AB10: 200000 | AC10: 100000 | AD10: 180000 | AE10: 110000 | AF10: 320000 | AG10: 400000 | AH10: 240000 | AI10: 130000 | AJ10: 150000 | AK10: 110000 | AL10: 170000 | AN10: 80000 | AO10: 100000 | AP10: 160000 | AQ10: 180000 | AS10: 400000 | AT10: 160000 | AV10: 120000 | AW10: 160000 | AX10: 60000 | AY10: 160000 | AZ10: 200000 | BA10: 80000 | BB10: 180000 | BC10: 50000 | BD10: 150000 | BE10: 400000 | BF10: 100000 | BG10: 100000 | BH10: 120000 | BI10: 100000 | BJ10: 100000 | BK10: 150000 | BL10: 100000 | BM10: 100000 | BO10: 60000 | BP10: 1000GACHA | BQ10: 15
BP11: デカプセル | BQ11: 1
A12: 売上実績 | B12: =SUM(C12:BO12) -> 11380100 | C12: =福重!F41-100 -> 154000 | D12: =福重!Q41 -> 120000 | E12: =福重!AT41 -> 56000 | F12: =福重!AA41 -> 108000 | G12: =福重!AG41 -> 94000 | H12: =福重!AM41 -> 106000 | I12: =那珂川!F16 -> 306000 | M12: =唐津!E14-22000 -> 228000 | N12: =飯塚!S16 -> 384000 | O12: =飯塚!H16 -> 475000 | P12: =飯塚!AB16 -> 152000 | Q12: =小倉!F14 -> 254000 | S12: =+黒崎!F13 -> 466000 | T12: =+黒崎!Q13 -> 343000 | U12: 335000 | V12: 16000 | W12: 37000 | X12: 196000 | Y12: 172000 | Z12: 321000 | AB12: 214000 | AC12: 120000 | AD12: 336000 | AE12: 104000 | AF12: 94000 | AG12: 462000 | AH12: 317000 | AI12: 70000 | AJ12: 138000 | AK12: 173000 | AL12: 188000 | AN12: 114200 | AO12: 334000 | AP12: 360000 | AQ12: 294000 | AS12: 561000 | AT12: 250000 | AV12: 129000 | AW12: 200000 | AX12: 219300 | AY12: 176000 | AZ12: 139000 | BA12: 208300 | BB12: 150000 | BC12: 89300 | BD12: 144000 | BE12: 452000 | BF12: 59000 | BG12: 40000 | BH12: 308000 | BI12: 56000 | BJ12: 182000 | BK12: 137000 | BL12: 121000 | BM12: 78000 | BO12: 40000 | BP12: 500GACHA | BQ12: 4
A13: 目標対比 | B13: =B12/B10 -> 1.2223523 | C13: =C12/C10 -> 1.7111111 | D13: =D12/D10 -> 0.4 | E13: =E12/E10 -> 0.50909091 | F13: =F12/F10 -> 0.72 | G13: =G12/G10 -> 0.94 | H13: =H12/H10 -> 0.70666667 | I13: =I12/I10 -> 1.02 | M13: =M12/M10 -> 1.14 | N13: =N12/N10 -> 2.7428571 | O13: =O12/O10 -> 1.9 | P13: =P12/P10 -> 0.76 | Q13: =Q12/Q10 -> 1.8142857 | S13: =S12/S10 -> 1.864 | T13: =T12/T10 -> 1.372 | U13: =U12/U10 -> 0.95714286 | V13: =V12/V10 -> 0.4 | W13: =W12/W10 -> 0.925 | X13: =X12/X10 -> 1.6333333 | Y13: =Y12/Y10 -> 1.1466667 | Z13: =Z12/Z10 -> 1.07 | AB13: =AB12/AB10 -> 1.07 | AC13: =AC12/AC10 -> 1.2 | AD13: =AD12/AD10 -> 1.8666667 | AE13: =AE12/AE10 -> 0.94545455 | AF13: =IFERROR(AF12/AF10,"-") -> 0.29375 | AG13: =IFERROR(AG12/AG10,"-") -> 1.155 | AH13: =IFERROR(AH12/AH10,"-") -> 1.3208333 | AI13: =IFERROR(AI12/AI10,"-") -> 0.53846154 | AJ13: =IFERROR(AJ12/AJ10,"-") -> 0.92 | AK13: =IFERROR(AK12/AK10,"-") -> 1.5727273 | AL13: =IFERROR(AL12/AL10,"-") -> 1.1058824 | AN13: =IFERROR(AN12/AN10,"-") -> 1.4275 | AO13: =IFERROR(AO12/AO10,"-") -> 3.34 | AP13: =IFERROR(AP12/AP10,"-") -> 2.25 | AQ13: =IFERROR(AQ12/AQ10,"-") -> 1.6333333 | AS13: =IFERROR(AS12/AS10,"-") -> 1.4025 | AT13: =IFERROR(AT12/AT10,"-") -> 1.5625 | AV13: =IFERROR(AV12/AV10,"-") -> 1.075 | AW13: =IFERROR(AW12/AW10,"-") -> 1.25 | AX13: =IFERROR(AX12/AX10,"-") -> 3.655 | AY13: =IFERROR(AY12/AY10,"-") -> 1.1 | AZ13: =IFERROR(AZ12/AZ10,"-") -> 0.695 | BA13: =IFERROR(BA12/BA10,"-") -> 2.60375 | BB13: =IFERROR(BB12/BB10,"-") -> 0.83333333 | BC13: =IFERROR(BC12/BC10,"-") -> 1.786 | ... BM13: =IFERROR(BM12/BM10,"-") -> 0.78 | BO13: =IFERROR(BO12/BO10,"-") -> 0.66666667 | BQ13: =SUM(BQ4:BQ12) -> 58
A14: =B13 -> 1.2223523
A15: 予測達成率 | C15: 開始日 | D15: 全台AVE | E15: =B12/B4 -> 199650.88 | F15: ガチャ | G15: プライズ | K15: 売上目標 | L15: =SUM(C10:M10) -> 1400000 | Q15: 売上目標 | S15: =SUM(N10:T10) -> 1230000 | AC15: 売上目標 | AD15: =SUM(U10:AE10) -> 1590000 | AF15: 売上目標 | AG15: =SUM(AF10:AH10) -> 960000 | AJ15: 新 | AK15: 売上目標 | AL15: =SUM(AI10:AN10) -> 640000 | AP15: 売上目標 | AQ15: =SUM(AO10:AR10) -> 440000 | AW15: 新 | BC15: 売上目標 | BD15: =SUM(AS10:BE10) -> 2120000 | BM15: 売上目標 | BN15: =SUM(BF10:BO10) -> 930000
A16: 進捗率 | B16: 経過日数 | C16: 45917 | D16: 総売上 | E16: 37083200 | F16: =B12 -> 11380100 | G16: =E16-B12 -> 25703100 | K16: 進捗 | L16: =SUM(C12:M12) -> 1172000 | M16: =L16/L15 -> 0.83714286 | Q16: 進捗 | S16: =SUM(N12:T12) -> 2074000 | T16: =S16/S15 -> 1.6861789 | AC16: 進捗 | AD16: =SUM(U12:AE12) -> 1851000 | AE16: =AD16/AD15 -> 1.1641509 | AF16: 進捗 | AG16: =SUM(AF12:AH12) -> 873000 | AH16: =AG16/AG15 -> 0.909375 | AK16: 進捗 | AL16: =SUM(AI12:AN12) -> 683200 | AN16: =AL16/AL15 -> 1.0675 | AP16: 進捗 | AQ16: =SUM(AO12:AR12) -> 988000 | AR16: =AQ16/AQ15 -> 2.2454545 | BC16: 進捗 | BD16: =SUM(AS12:BE12) -> 2717900 | BE16: =BD16/BD15 -> 1.2820283 | BM16: 進捗 | BN16: =SUM(BF12:BO12) -> 1021000 | BO16: =BN16/BN15 -> 1.0978495
A18: 設置店舗数 | B18: =M18+AE18+BE18+BO18+AN18+AH18+T18+AQ18 -> 32 | C18: 1 | D18: 1 | E18: 1 | F18: 1 | G18: 1 | H18: 1 | I18: 2 | M18: 3 | N18: 1 | O18: 1 | P18: 1 | Q18: 2 | S18: 3 | T18: 3 | U18: 1 | V18: 1 | W18: 1 | X18: 2 | Y18: 2 | Z18: 3 | AB18: 4 | AD18: 5 | AE18: 5 | AF18: 1 | AG18: 1 | AH18: 2 | AI18: 1 | AJ18: 1 | AK18: 2 | AL18: 2 | AN18: 2 | AO18: 1 | AP18: 2 | AQ18: 3 | AR18: 4 | AS18: 1 | AT18: 2 | AV18: 3 | AW18: 3 | AX18: 3 | AY18: 4 | AZ18: 4 | BA18: 4 | BB18: 5 | BC18: 5 | BD18: 6 | BE18: 7 | BF18: 1 | BG18: 1 | BH18: 2 | BI18: 3 | BJ18: 4 | BK18: 5 | BL18: 6 | BM18: 6 | BO18: 7 | BP18: =M18+AE18+AH18+AN18+AQ18+BE18+BO18+T18 -> 32 | BQ18: 店舗
A19: 45962 | B19: 合計 | C19: 福重 | D19: 福重② | E19: 福重③ | F19: 福重④ | G19: 福重⑤ | H19: 福重⑥ | I19: 那珂川 | J19: 那珂川 | K19: 西新 | L19: 博多駅南 | M19: 唐津 | N19: 飯塚 | O19: 飯塚② | P19: 飯塚③ | Q19: 小倉 | S19: 黒崎 | T19: 黒崎② | U19: 宗像 | V19: 宗像② | W19: 宗像③ | X19: 魚町 | Y19: 魚町② | Z19: 鞍手 | AB19: 長府② | AC19: 宇部① | AD19: 宇部② | AE19: 宇部③ | AF19: 佐賀① | AG19: 佐賀② | AH19: 八女 | AI19: 都城① | AJ19: 都城② | AK19: 鹿屋① | AL19: 鹿屋② | AN19: 鹿屋500 | AO19: 浜町 | AP19: 時津 | AQ19: 大村 | AR19: 中州 | AS19: 菊陽② | AT19: 宇宿① | AV19: 霧島① | AW19: 霧島② | AX19: 霧島500 | AY19: 川内① | AZ19: 川内② | BA19: 川内500 | BB19: 合志 | BC19: 合志 | BD19: 南熊本 | BE19: 下通 | BF19: 今宿 | BG19: 今宿➁ | BH19: 八代 | BI19: 佐世保 | BJ19: 別府 | BK19: 行橋 | BL19: 延岡① | BM19: 延岡② | BO19: 光吉
A20: 設置台数 | B20: 57 | C20: 500GACHA | D20: 1000GACHA | E20: ティアラ | F20: ティアラ | G20: ティアラ | H20: ティアラ | I20: 1000GACHA | M20: 1000GACHA | N20: 1000GACHA | O20: デカプセル | P20: ティアラ | Q20: ティアラ | S20: ティアラ | T20: 1000GACHA | U20: ガチャコロ1 | V20: 500GATCHA | W20: 500GATCHA | X20: ティアラ | Y20: 1000GACHA | Z20: ガチャコロ2 | AB20: 1000GACHA | AC20: ティアラ | AD20: 1000GACHA | AE20: 1000GACHA | AF20: 1000GACHA | AG20: ガチャコロ2 | AH20: ガチャコロ２ | AI20: ティアラ | AJ20: 1000GACHA | AK20: 1000GACHA | AL20: 1000GACHA | AN20: 500GATCHA | AO20: 1000GACHA | AP20: ガチャコロ２ | AQ20: ガチャコロ２ | AR20: 1000GACHA | AS20: ガチャコロ２ | AT20: 1000GACHA | AV20: 1000GACHA | AW20: ティアラ | AX20: 500GATCHA | AY20: 1000GACHA | AZ20: ティアラ | BA20: 500GATCHA | BB20: ガチャコロ２ | BC20: 500GACHA | BD20: ティアラ | BE20: ガチャコロ２ | BF20: 1000GACHA | BG20: ガチャコロ2 | BH20: ガチャコロ２ | BI20: ティアラ | BJ20: ティアラ | BK20: ガチャコロ2 | BL20: 1000GACHA | BM20: 1000GACHA | BO20: ティアラ
A21: ロッカー台数 | B21: =SUM(C21:BO21) -> 147 | C21: 2 | D21: 2 | E21: 3 | F21: 3 | G21: 3 | H21: 3 | I21: 2 | M21: 2 | N21: 2 | O21: 4 | P21: 3 | Q21: 2 | S21: 2 | T21: 2 | U21: 3 | V21: 2 | W21: 0 | X21: 6 | Y21: 2 | Z21: 4 | AB21: 2 | AC21: 2 | AD21: 2 | AE21: 2 | AF21: 3 | AG21: 2 | AH21: 4 | AI21: 2 | AJ21: 2 | AK21: 3 | AL21: 3 | AN21: 2 | AO21: 2 | AP21: 4 | AQ21: 2 | AR21: 1 | AS21: 4 | AT21: 1 | AV21: 3 | AW21: 3 | AX21: 2 | AY21: 3 | AZ21: 3 | BA21: 2 | BB21: 4 | BC21: 3 | BD21: 2 | BE21: 3 | BF21: 2 | BG21: 4 | BH21: 4 | BI21: 2 | BJ21: 2 | BK21: 4 | BL21: 2 | BM21: 2 | BO21: 2 | BP21: =SUM(C21:BO21) -> 147 | BQ21: ロッカー
A22: カプセル容量 | C22: 300 | D22: 300 | E22: 300 | F22: 300 | G22: 300 | H22: 300 | I22: 300 | M22: 300 | N22: 300 | O22: 300 | P22: 300 | Q22: 300 | S22: 300 | T22: 300 | U22: 400 | V22: 150 | W22: 150 | X22: 150 | Y22: 300 | Z22: 400 | AB22: 300 | AC22: 300 | AD22: 300 | AE22: 300 | AF22: 300 | AG22: 400 | AH22: 400 | AI22: 300 | AJ22: 300 | AK22: 300 | AL22: 300 | AN22: 300 | AO22: 300 | AP22: 400 | AQ22: 400 | AR22: 300 | AS22: 400 | AT22: 300 | AV22: 300 | AW22: 300 | AX22: 300 | AY22: 300 | AZ22: 300 | BA22: 300 | BB22: 400 | BC22: 300 | BD22: 300 | BE22: 400 | BF22: 300 | BG22: 400 | BH22: 400 | BI22: 300 | BJ22: 300 | BK22: 400 | BL22: 300 | BM22: 300 | BO22: 300
A23: ガチャの種類 | C23: バラエティー | D23: バラエティー | E23: スニーカー | F23: ゲームソフト | G23: ブランド | H23: ゲーム機 | I23: バラエティー | M23: バラエティー | N23: バラエティー | O23: バラエティー | P23: スニーカー | Q23: バラエティー | S23: バラエティー | T23: バラエティー | U23: バラエティー | V23: バラエティー | W23: バラエティー | X23: バラエティー | Y23: ポケモン | Z23: バラエティー | AB23: バラエティー | AC23: バラエティー | AD23: バラエティー | AE23: バラエティー(ポケモン） | AF23: バラエティー | AG23: バラエティー | AH23: バラエティー | AI23: バラエティー | AJ23: バラエティー | AK23: バラエティー | AL23: バラエティー | AN23: バラエティー | AO23: バラエティー | AP23: バラエティー | AQ23: バラエティー | AR23: バラエティー | AS23: バラエティー | AT23: バラエティー | AV23: バラエティー | AW23: バラエティー | AX23: ポケモン | AY23: バラエティー | AZ23: バラエティー | BA23: ポケモン | BB23: バラエティー | BC23: バラエティー | BD23: バラエティー | BE23: バラエティー | BF23: バラエティー | BG23: バラエティー | BH23: バラエティー | BI23: バラエティー | BJ23: バラエティー | BK23: バラエティー | BL23: バラエティー | BM23: バラエティー | BO23: バラエティー | BP23: ティアラ | BQ23: 26
A24: プレイ料金 | C24: 500 | D24: 2000 | E24: 2000 | F24: 1000 | G24: 2000 | H24: 2000 | I24: 2000 | M24: 1000 | N24: 1000 | O24: 2000 | P24: 2000 | Q24: 1000 | S24: 2000 | T24: 1000 | U24: 2000 | V24: 500 | W24: 500 | X24: 2000 | Y24: 1000 | Z24: 2000 | AB24: 1000 | AC24: 1000 | AD24: 2000 | AE24: 2000 | AF24: 1000 | AG24: 2000 | AH24: 1000＆2000 | AI24: 1000 | AJ24: 2000 | AK24: 1000 | AL24: 2000 | AN24: 500 | AO24: 1000 | AP24: 1000＆2000 | AQ24: 1000＆2000 | AR24: 3000 | AS24: 2000 | AT24: 2000 | AV24: 1000 | AW24: 2000 | AX24: 500 | AY24: 1000 | AZ24: 2000 | BA24: 500 | BB24: 2000 | BC24: 500 | BD24: 1000 | BE24: 1000＆2000 | BF24: 1000 | BG24: 2000 | BH24: 1000＆2000 | BI24: 1000 | BJ24: 2000 | BK24: 1000＆2000 | BL24: 1000 | BM24: 2000 | BO24: 2000 | BP24: ガチャコロ1 | BQ24: 2
A25: 前年度 | B25: =SUM(C25:BO25) -> 7672400 | C25: 93000 | D25: 232000 | I25: 216000 | J25: 120000 | K25: 343000 | L25: 195000 | M25: 176000 | N25: 96000 | O25: 264000 | Q25: 130000 | S25: 138000 | T25: 122000 | U25: 262000 | V25: 29000 | W25: 17000 | X25: 86000 | Y25: 98000 | Z25: 176000 | AB25: 70000 | AF25: 135000 | AG25: 275000 | AH25: 284000 | AI25: 94000 | AJ25: 68000 | AO25: 120000 | AP25: 159000 | AQ25: 81000 | AS25: 513000 | AT25: 138000 | AU25: 131000 | AV25: 140000 | AW25: 138000 | AX25: 85100 | AY25: 210000 | AZ25: 228000 | BA25: 70700 | BB25: 193000 | BC25: 46600 | BE25: 699000 | BF25: 103000 | BG25: 138000 | BH25: 94000 | BI25: 72000 | BJ25: 138000 | BK25: 147000 | BL25: 97000 | BM25: 132000 | BO25: 80000 | BP25: ガチャコロ2 | BQ25: 10
A26: 目標 | B26: =SUM(C26:BO26) -> 10280000 | C26: 120000 | D26: 200000 | E26: 120000 | F26: 120000 | G26: 120000 | H26: 120000 | I26: 250000 | M26: 200000 | N26: 250000 | O26: 400000 | P26: 120000 | Q26: 200000 | S26: 300000 | T26: 250000 | U26: 280000 | V26: 40000 | W26: 40000 | X26: 140000 | Y26: 130000 | Z26: 250000 | AA26: =(AA25+AA12)/2 -> 0 | AB26: 150000 | AC26: 100000 | AD26: 250000 | AE26: 100000 | AF26: 140000 | AG26: 350000 | AH26: 290000 | AI26: 120000 | AJ26: 150000 | AK26: 150000 | AL26: 200000 | AN26: 100000 | AO26: 230000 | AP26: 260000 | AQ26: 190000 | AR26: 300000 | AS26: 500000 | AT26: 200000 | AV26: 130000 | AW26: 150000 | AX26: 120000 | AY26: 190000 | AZ26: 200000 | BA26: 140000 | BB26: 170000 | BC26: 70000 | BD26: 120000 | BE26: 450000 | BF26: 100000 | BG26: 140000 | BH26: 200000 | BI26: 70000 | BJ26: =(BJ25+BJ12)/2 -> 160000 | BK26: 140000 | BL26: 110000 | BM26: 130000 | BN26: =(BN25+BN12)/2 -> 0 | BO26: =(BO25+BO12)/2 -> 60000 | BP26: 1000GACHA | BQ26: 15
BP27: デカプセル | BQ27: 1
A28: 売上実績 | B28: =SUM(C28:BO28) -> 9423800 | C28: =福重!F85-200 -> 175000 | D28: =福重!Q85 -> 151000 | E28: =福重!AT85 -> 126000 | F28: =福重!AA85 -> 98000 | G28: =福重!AG85 -> 190000 | H28: =福重!AM85 -> 108000 | I28: =那珂川!F33 -> 208000 | M28: =唐津!E29+36000 -> 184000 | N28: =飯塚!S33 -> 115000 | O28: =飯塚!H33 -> 218000 | P28: =飯塚!AB33 -> 70000 | Q28: =小倉!F29 -> 209000 | S28: =+黒崎!F27 -> 282000 | T28: =+黒崎!Q27 -> 274000 | U28: 268000 | V28: 30000 | W28: 38500 | X28: 192000 | Y28: 163000 | Z28: 215000 | AB28: 258000 | AC28: 115000 | AD28: 204000 | AE28: 94000 | AF28: 135000 | AG28: 351000 | AH28: 202000 | AI28: 76000 | AJ28: 112000 | AK28: 149000 | AL28: 166000 | AN28: 125900 | AO28: 219000 | AP28: 294000 | AQ28: 327000 | AR28: 402000 | AS28: 484000 | AT28: 210000 | AV28: 124000 | AW28: 190000 | AX28: 70400 | AY28: 257000 | AZ28: 142000 | BA28: 127800 | BB28: 158000 | BC28: 90200 | BD28: 131000 | BE28: 255000 | BF28: 41000 | BG28: 111000 | BH28: 92000 | BI28: 66000 | BJ28: 106000 | BK28: 103000 | BL28: 55000 | BM28: 46000 | BO28: 20000 | BP28: 500GACHA | BQ28: 4
A29: 目標対比 | B29: =B28/B26 -> 0.91671206 | C29: =C28/C26 -> 1.4583333 | D29: =D28/D26 -> 0.755 | E29: =E28/E26 -> 1.05 | F29: =F28/F26 -> 0.81666667 | G29: =G28/G26 -> 1.5833333 | H29: =H28/H26 -> 0.9 | I29: =I28/I26 -> 0.832 | M29: =M28/M26 -> 0.92 | N29: =N28/N26 -> 0.46 | O29: =O28/O26 -> 0.545 | P29: =P28/P26 -> 0.58333333 | Q29: =Q28/Q26 -> 1.045 | S29: =S28/S26 -> 0.94 | T29: =T28/T26 -> 1.096 | U29: =U28/U26 -> 0.95714286 | V29: =V28/V26 -> 0.75 | W29: =W28/W26 -> 0.9625 | X29: =X28/X26 -> 1.3714286 | Y29: =Y28/Y26 -> 1.2538462 | Z29: =Z28/Z26 -> 0.86 | AB29: =AB28/AB26 -> 1.72 | AC29: =AC28/AC26 -> 1.15 | AD29: =AD28/AD26 -> 0.816 | AE29: =AE28/AE26 -> 0.94 | AF29: =IFERROR(AF28/AF26,"-") -> 0.96428571 | AG29: =IFERROR(AG28/AG26,"-") -> 1.0028571 | AH29: =IFERROR(AH28/AH26,"-") -> 0.69655172 | AI29: =IFERROR(AI28/AI26,"-") -> 0.63333333 | AJ29: =IFERROR(AJ28/AJ26,"-") -> 0.74666667 | AK29: =IFERROR(AK28/AK26,"-") -> 0.99333333 | AL29: =IFERROR(AL28/AL26,"-") -> 0.83 | AN29: =IFERROR(AN28/AN26,"-") -> 1.259 | AO29: =IFERROR(AO28/AO26,"-") -> 0.95217391 | AP29: =IFERROR(AP28/AP26,"-") -> 1.1307692 | AQ29: =IFERROR(AQ28/AQ26,"-") -> 1.7210526 | AR29: =IFERROR(AR28/AR26,"-") -> 1.34 | AS29: =IFERROR(AS28/AS26,"-") -> 0.968 | AT29: =IFERROR(AT28/AT26,"-") -> 1.05 | AV29: =IFERROR(AV28/AV26,"-") -> 0.95384615 | AW29: =IFERROR(AW28/AW26,"-") -> 1.2666667 | AX29: =IFERROR(AX28/AX26,"-") -> 0.58666667 | AY29: =IFERROR(AY28/AY26,"-") -> 1.3526316 | AZ29: =IFERROR(AZ28/AZ26,"-") -> 0.71 | BA29: =IFERROR(BA28/BA26,"-") -> 0.91285714 | BB29: =IFERROR(BB28/BB26,"-") -> 0.92941176 | BC29: =IFERROR(BC28/BC26,"-") -> 1.2885714 | ... BM29: =IFERROR(BM28/BM26,"-") -> 0.35384615 | BO29: =IFERROR(BO28/BO26,"-") -> 0.33333333 | BQ29: =SUM(BQ20:BQ28) -> 58
A30: =B29 -> 0.91671206
A31: 予測達成率 | C31: 開始日 | D31: 全台AVE | E31: =B28/B20 -> 165329.82 | F31: ガチャ | G31: プライズ | K31: 売上目標 | L31: =SUM(C26:M26) -> 1250000 | Q31: 売上目標 | S31: =SUM(N26:T26) -> 1520000 | AC31: 売上目標 | AD31: =SUM(U26:AE26) -> 1480000 | AF31: 売上目標 | AG31: =SUM(AF26:AH26) -> 780000 | AJ31: 新 | AK31: 売上目標 | AL31: =SUM(AI26:AN26) -> 720000 | AP31: 売上目標 | AQ31: =SUM(AO26:AR26) -> 980000 | AW31: 新 | BC31: 売上目標 | BD31: =SUM(AS26:BE26) -> 2440000 | BM31: 売上目標 | BN31: =SUM(BF26:BO26) -> 1110000
A32: 進捗率 | B32: 経過日数 | C32: 45947 | D32: 総売上 | E32: 33818900 | F32: =B28 -> 9423800 | G32: =E32-B28 -> 24395100 | K32: 進捗 | L32: =SUM(C28:M28) -> 1240000 | M32: =L32/L31 -> 0.992 | Q32: 進捗 | S32: =SUM(N28:T28) -> 1168000 | T32: =S32/S31 -> 0.76842105 | AC32: 進捗 | AD32: =SUM(U28:AE28) -> 1577500 | AE32: =AD32/AD31 -> 1.0658784 | AF32: 進捗 | AG32: =SUM(AF28:AH28) -> 688000 | AH32: =AG32/AG31 -> 0.88205128 | AK32: 進捗 | AL32: =SUM(AI28:AN28) -> 628900 | AN32: =AL32/AL31 -> 0.87347222 | AP32: 進捗 | AQ32: =SUM(AO28:AR28) -> 1242000 | AR32: =AQ32/AQ31 -> 1.2673469 | BC32: 進捗 | BD32: =SUM(AS28:BE28) -> 2239400 | BE32: =BD32/BD31 -> 0.91778689 | BM32: 進捗 | BN32: =SUM(BF28:BO28) -> 640000 | BO32: =BN32/BN31 -> 0.57657658
A34: 設置店舗数 | B34: =M34+AE34+BE34+BO34+AH34+T34+AL34 -> 33 | C34: 1 | D34: 1 | E34: 1 | F34: 1 | G34: 1 | H34: 1 | I34: 2 | L34: 3 | M34: 3 | N34: 1 | O34: 1 | P34: 1 | Q34: 2 | S34: 3 | T34: 3 | U34: 1 | V34: 1 | W34: 1 | X34: 2 | Y34: 2 | Z34: 3 | AB34: 4 | AD34: 5 | AE34: 5 | AF34: 1 | AG34: 1 | AH34: 2 | AI34: 1 | AJ34: 2 | AK34: 3 | AL34: 4 | AN34: 1 | AO34: 1 | AP34: 2 | AQ34: 2 | AR34: 2 | AS34: 3 | AT34: 3 | AU34: 3 | AV34: 4 | AW34: 4 | AX34: 5 | AY34: 5 | AZ34: 5 | BA34: 6 | BB34: 7 | BC34: 7 | BD34: 8 | BE34: 9 | BF34: 1 | BG34: 1 | BH34: 2 | BI34: 3 | BJ34: 4 | BK34: 5 | BL34: 6 | BM34: 6 | BO34: 7 | BP34: =M34+AE34+AH34+AL34+BE34+BO34+T34 -> 33 | BQ34: 店舗
A35: 45992 | B35: 合計 | C35: 福重 | D35: 福重② | E35: 福重③ | F35: 福重④ | G35: 福重⑤ | H35: 福重⑥ | I35: 那珂川 | J35: 那珂川 | K35: 西新 | L35: 唐津 | M35: 唐津 | N35: 飯塚 | O35: 飯塚② | P35: 飯塚③ | Q35: 小倉 | S35: 黒崎 | T35: 黒崎② | U35: 宗像 | V35: 宗像② | W35: 宗像③ | X35: 魚町 | Y35: 魚町② | Z35: 鞍手 | AB35: 長府② | AC35: 宇部① | AD35: 宇部② | AE35: 宇部③ | AF35: 佐賀① | AG35: 佐賀② | AH35: 八女 | AI35: 浜町 | AJ35: 時津 | AK35: 大村 | AL35: 中州 | AN35: 宇宿① | AO35: 宇宿② | AP35: 霧島① | AQ35: 霧島② | AR35: 霧島500 | AS35: 川内① | AT35: 川内② | AU35: 川内500 | AV35: 都城① | AW35: 都城② | AX35: 鹿屋① | AY35: 鹿屋② | AZ35: 鹿屋500 | BA35: 菊陽② | BB35: 合志 | BC35: 合志 | BD35: 南熊本 | BE35: 下通 | BF35: 今宿 | BG35: 今宿➁ | BH35: 八代 | BI35: 佐世保 | BJ35: 別府 | BK35: 行橋 | BL35: 延岡① | BM35: 延岡② | BN35: Dプラ | BO35: 光吉
A36: 設置台数 | B36: 57 | C36: 500GACHA | D36: 1000GACHA | E36: ティアラ | F36: ティアラ | G36: ティアラ | H36: ティアラ | I36: 1000GACHA | L36: 1000GACHA | M36: ティアラ | N36: 1000GACHA | O36: デカプセル | P36: ティアラ | Q36: ティアラ | S36: ティアラ | T36: 1000GACHA | U36: ガチャコロ1 | V36: 500GATCHA | W36: 500GATCHA | X36: ティアラ | Y36: 1000GACHA | Z36: ガチャコロ2 | AB36: 1000GACHA | AC36: ティアラ | AD36: 1000GACHA | AE36: 1000GACHA | AF36: 1000GACHA | AG36: ガチャコロ2 | AH36: ガチャコロ２ | AI36: 1000GACHA | AJ36: ガチャコロ２ | AK36: ガチャコロ２ | AL36: 1000GACHA | AN36: 1000GACHA | AP36: 1000GACHA | AQ36: ティアラ | AR36: 500GATCHA | AS36: 1000GACHA | AT36: ティアラ | AU36: 500GATCHA | AV36: ティアラ | AW36: 1000GACHA | AX36: 1000GACHA | AY36: 1000GACHA | AZ36: 500GATCHA | BA36: ガチャコロ２ | BB36: ガチャコロ２ | BC36: 500GACHA | BD36: ティアラ | BE36: ガチャコロ２ | BF36: 1000GACHA | BG36: ガチャコロ2 | BH36: ガチャコロ２ | BI36: ティアラ | BJ36: ティアラ | BK36: ガチャコロ2 | BL36: 1000GACHA | BM36: 1000GACHA | BO36: ティアラ
A37: ロッカー台数 | B37: =SUM(C37:BO37) -> 148 | C37: 2 | D37: 2 | E37: 3 | F37: 3 | G37: 3 | H37: 3 | I37: 2 | L37: 2 | M37: 2 | N37: 2 | O37: 4 | P37: 3 | Q37: 2 | S37: 2 | T37: 2 | U37: 3 | V37: 2 | W37: 0 | X37: 6 | Y37: 2 | Z37: 4 | AB37: 2 | AC37: 2 | AD37: 2 | AE37: 2 | AF37: 3 | AG37: 2 | AH37: 4 | AI37: 2 | AJ37: 4 | AK37: 2 | AL37: 1 | AN37: 1 | AP37: 3 | AQ37: 3 | AR37: 2 | AS37: 3 | AT37: 3 | AU37: 2 | AV37: 2 | AW37: 2 | AX37: 3 | AY37: 3 | AZ37: 2 | BA37: 4 | BB37: 4 | BC37: 3 | BD37: 2 | BE37: 3 | BF37: 2 | BG37: 4 | BH37: 3 | BI37: 2 | BJ37: 2 | BK37: 4 | BL37: 2 | BM37: 2 | BO37: 2 | BP37: =SUM(C37:BO37) -> 148 | BQ37: ロッカー
A38: カプセル容量 | C38: 300 | D38: 300 | E38: 300 | F38: 300 | G38: 300 | H38: 300 | I38: 300 | L38: 300 | M38: 300 | N38: 300 | O38: 300 | P38: 300 | Q38: 300 | S38: 300 | T38: 300 | U38: 400 | V38: 150 | W38: 150 | X38: 150 | Y38: 300 | Z38: 400 | AB38: 300 | AC38: 300 | AD38: 300 | AE38: 300 | AF38: 300 | AG38: 400 | AH38: 400 | AI38: 300 | AJ38: 400 | AK38: 400 | AL38: 300 | AN38: 300 | AP38: 300 | AQ38: 300 | AR38: 300 | AS38: 300 | AT38: 300 | AU38: 300 | AV38: 300 | AW38: 300 | AX38: 300 | AY38: 300 | AZ38: 300 | BA38: 400 | BB38: 400 | BC38: 300 | BD38: 300 | BE38: 400 | BF38: 300 | BG38: 400 | BH38: 400 | BI38: 300 | BJ38: 300 | BK38: 400 | BL38: 300 | BM38: 300 | BO38: 300
A39: ガチャの種類 | C39: バラエティー | D39: バラエティー | E39: スニーカー | F39: ゲームソフト | G39: ブランド | H39: ゲーム機 | I39: バラエティー | L39: バラエティー | M39: バラエティー | N39: バラエティー | O39: バラエティー | P39: スニーカー | Q39: バラエティー | S39: バラエティー | T39: バラエティー | U39: バラエティー | V39: バラエティー | W39: バラエティー | X39: バラエティー | Y39: ポケモン | Z39: バラエティー | AB39: バラエティー | AC39: バラエティー | AD39: バラエティー | AE39: バラエティー(ポケモン） | AF39: バラエティー | AG39: バラエティー | AH39: バラエティー | AI39: バラエティー | AJ39: バラエティー | AK39: バラエティー | AL39: バラエティー | AN39: バラエティー | AP39: バラエティー | AQ39: バラエティー | AR39: ポケモン | AS39: バラエティー | AT39: バラエティー | AU39: ポケモン | AV39: バラエティー | AW39: バラエティー | AX39: バラエティー | AY39: バラエティー | AZ39: バラエティー | BA39: バラエティー | BB39: バラエティー | BC39: バラエティー | BD39: バラエティー | BE39: バラエティー | BF39: バラエティー | BG39: バラエティー | BH39: バラエティー | BI39: バラエティー | BJ39: バラエティー | BK39: バラエティー | BL39: バラエティー | BM39: バラエティー | BO39: バラエティー | BP39: ティアラ | BQ39: 26
A40: プレイ料金 | C40: 500 | D40: 2000 | E40: 2000 | F40: 1000 | G40: 2000 | H40: 2000 | I40: 2000 | L40: 1000 | M40: 2000 | N40: 1000 | O40: 2000 | P40: 2000 | Q40: 1000 | S40: 2000 | T40: 1000 | U40: 2000 | V40: 500 | W40: 500 | X40: 2000 | Y40: 1000 | Z40: 2000 | AB40: 1000 | AC40: 1000 | AD40: 2000 | AE40: 2000 | AF40: 1000 | AG40: 2000 | AH40: 1000＆2000 | AI40: 1000 | AJ40: 1000＆2000 | AK40: 1000＆2000 | AL40: 3000 | AN40: 2000 | AP40: 1000 | AQ40: 2000 | AR40: 500 | AS40: 1000 | AT40: 2000 | AU40: 500 | AV40: 1000 | AW40: 2000 | AX40: 1000 | AY40: 2000 | AZ40: 500 | BA40: 2000 | BB40: 2000 | BC40: 500 | BD40: 1000 | BE40: 1000＆2000 | BF40: 1000 | BG40: 2000 | BH40: 1000＆2000 | BI40: 1000 | BJ40: 2000 | BK40: 1000＆2000 | BL40: 1000 | BM40: 2000 | BO40: 2000 | BP40: ガチャコロ1 | BQ40: 2
A41: 前年度 | B41: =SUM(C41:BO41) -> 8951700 | C41: 72700 | D41: 140000 | E41: 213000 | F41: 141000 | G41: 105000 | H41: 158000 | I41: 228000 | J41: 173000 | K41: 114000 | L41: 154000 | N41: 71000 | O41: 244000 | Q41: 121000 | S41: 214000 | T41: 126000 | U41: 654000 | V41: 22000 | W41: 35100 | X41: 96000 | Y41: 137000 | Z41: 256000 | AB41: 94000 | AF41: 221000 | AG41: 380000 | AH41: 112000 | AI41: 136000 | AJ41: 263000 | AK41: 101000 | AL41: 500000 | AN41: 63000 | AO41: 66000 | AP41: 154000 | AQ41: 260000 | AR41: 77600 | AS41: 159000 | AT41: 282000 | AU41: 124100 | AV41: 156000 | AW41: 90000 | BA41: 493000 | BB41: 221000 | BC41: 54200 | BE41: 340000 | BF41: 74000 | BG41: 192000 | BH41: 85000 | BI41: 91000 | BJ41: 192000 | BK41: 234000 | BL41: 78000 | BM41: 58000 | BN41: 44000 | BO41: 82000 | BP41: ガチャコロ2 | BQ41: 10
A42: 目標 | B42: =SUM(C42:BO42) -> 9171800 | C42: 150000 | D42: 150000 | E42: 150000 | F42: 120000 | G42: 150000 | H42: 120000 | I42: 200000 | J42: =J28*0.9 -> 0 | K42: =K28*0.9 -> 0 | L42: 170000 | M42: 0 | N42: 100000 | O42: 200000 | P42: 100000 | Q42: 180000 | S42: 200000 | T42: 200000 | U42: 300000 | V42: 30000 | W42: 30000 | X42: 160000 | Y42: 140000 | Z42: 190000 | AA42: =AA28*0.9 -> 0 | AB42: 200000 | AC42: 120000 | AD42: 170000 | AE42: 120000 | AF42: 180000 | AG42: 350000 | AH42: 150000 | AI42: 170000 | AJ42: 250000 | AK42: 270000 | AL42: =AR28*0.9 -> 361800 | AN42: 150000 | AO42: =AU28*0.9 -> 0 | AP42: 130000 | AQ42: 210000 | AR42: 70000 | AS42: 200000 | AT42: 200000 | AU42: 110000 | AV42: 120000 | AW42: 120000 | AX42: 150000 | AY42: 160000 | AZ42: 100000 | BA42: 450000 | BB42: 150000 | BC42: 70000 | BD42: 120000 | BE42: 280000 | BF42: 100000 | BG42: 120000 | BH42: 100000 | BI42: 100000 | BJ42: 150000 | BK42: 150000 | BL42: 100000 | BM42: 100000 | BN42: =BN28*0.9 -> 0 | BO42: 80000 | BP42: 1000GACHA | BQ42: 15
BP43: デカプセル | BQ43: 1
A44: 売上実績 | B44: =SUM(C44:BO44) -> 8969010 | C44: =福重!F129 -> 136500 | D44: =福重!Q129 -> 184000 | E44: =福重!AT129 -> 140000 | F44: =福重!AA129 -> 138000 | G44: =福重!AG129 -> 132000 | H44: =福重!AM129 -> 158000 | I44: =那珂川!F50 -> 228000 | L44: =唐津!E44-1000 -> 205000 | M44: 46000 | N44: =飯塚!S50 -> 118000 | O44: =飯塚!H50 -> 232000 | P44: =飯塚!AB50 -> 106000 | Q44: =小倉!F44 -> 186000 | S44: =+黒崎!F41 -> 260000 | T44: =+黒崎!Q41 -> 334000 | U44: 248000 | V44: 18500 | W44: 25000 | X44: 116000 | Y44: 210000 | Z44: 209000 | AB44: 98000 | AC44: 59000 | AD44: 246000 | AE44: 100000 | AF44: 110000 | AG44: 253000 | AH44: 186000 | AI44: 127000 | AJ44: 185000 | AK44: 168000 | AL44: 730000 | AN44: 184000 | AP44: 129000 | AQ44: 142000 | AR44: 81100 | AS44: 211000 | AT44: 172000 | AU44: 139310 | AV44: 95000 | AW44: 80000 | AX44: 78000 | AY44: 96000 | AZ44: 140300 | BA44: 295000 | BB44: 157000 | BC44: 63300 | BD44: 94000 | BE44: 289000 | BF44: 86000 | BG44: 124000 | BH44: 100000 | BI44: 96000 | BJ44: 78000 | BK44: 126000 | BL44: 91000 | BM44: 100000 | BO44: 30000 | BP44: 500GACHA | BQ44: 4
A45: 目標対比 | B45: =B44/B42 -> 0.97788984 | C45: =C44/C42 -> 0.91 | D45: =D44/D42 -> 1.2266667 | E45: =E44/E42 -> 0.93333333 | F45: =F44/F42 -> 1.15 | G45: =G44/G42 -> 0.88 | H45: =H44/H42 -> 1.3166667 | I45: =I44/I42 -> 1.14 | L45: =L44/L42 -> 1.2058824 | M45: =M44/M42 -> #DIV/0! | N45: =N44/N42 -> 1.18 | O45: =O44/O42 -> 1.16 | P45: =P44/P42 -> 1.06 | Q45: =Q44/Q42 -> 1.0333333 | S45: =S44/S42 -> 1.3 | T45: =T44/T42 -> 1.67 | U45: =U44/U42 -> 0.82666667 | V45: =V44/V42 -> 0.61666667 | W45: =W44/W42 -> 0.83333333 | X45: =X44/X42 -> 0.725 | Y45: =Y44/Y42 -> 1.5 | Z45: =Z44/Z42 -> 1.1 | AB45: =AB44/AB42 -> 0.49 | AC45: =AC44/AC42 -> 0.49166667 | AD45: =AD44/AD42 -> 1.4470588 | AE45: =AE44/AE42 -> 0.83333333 | AF45: =IFERROR(AF44/AF42,"-") -> 0.61111111 | AG45: =IFERROR(AG44/AG42,"-") -> 0.72285714 | AH45: =IFERROR(AH44/AH42,"-") -> 1.24 | AI45: =IFERROR(AI44/AI42,"-") -> 0.74705882 | AJ45: =IFERROR(AJ44/AJ42,"-") -> 0.74 | AK45: =IFERROR(AK44/AK42,"-") -> 0.62222222 | AL45: =IFERROR(AL44/AL42,"-") -> 2.0176893 | AN45: =IFERROR(AN44/AN42,"-") -> 1.2266667 | AP45: =IFERROR(AP44/AP42,"-") -> 0.99230769 | AQ45: =IFERROR(AQ44/AQ42,"-") -> 0.67619048 | AR45: =IFERROR(AR44/AR42,"-") -> 1.1585714 | AS45: =IFERROR(AS44/AS42,"-") -> 1.055 | AT45: =IFERROR(AT44/AT42,"-") -> 0.86 | AU45: =IFERROR(AU44/AU42,"-") -> 1.2664545 | AV45: =IFERROR(AV44/AV42,"-") -> 0.79166667 | AW45: =IFERROR(AW44/AW42,"-") -> 0.66666667 | ... BM45: =IFERROR(BM44/BM42,"-") -> 1 | BO45: =IFERROR(BO44/BO42,"-") -> 0.375 | BQ45: =SUM(BQ36:BQ44) -> 58
A46: =B45 -> 0.97788984
A47: 予測達成率 | C47: 開始日 | D47: 全台AVE | E47: =B44/B36 -> 157351.05 | F47: ガチャ | G47: プライズ | K47: 売上目標 | L47: =SUM(C42:M42) -> 1210000 | Q47: 売上目標 | S47: =SUM(N42:T42) -> 980000 | AC47: 売上目標 | AD47: =SUM(U42:AE42) -> 1460000 | AF47: 売上目標 | AG47: =SUM(AF42:AH42) -> 680000 | AJ47: 売上目標 | AK47: =SUM(AI42:AL42) -> 1051800 | AQ47: 新 | AW47: 新 | BC47: 売上目標 | BD47: =SUM(AN42:BE42) -> 2790000 | BM47: 売上目標 | BN47: =SUM(BF42:BO42) -> 1000000
A48: 進捗率 | B48: 経過日数 | C48: 45978 | D48: 総売上 | E48: 30032010 | F48: =B44 -> 8969010 | G48: =E48-B44 -> 21063000 | K48: 進捗 | L48: =SUM(C44:M44) -> 1367500 | M48: =L48/L47 -> 1.1301653 | Q48: 進捗 | S48: =SUM(N44:T44) -> 1236000 | T48: =S48/S47 -> 1.2612245 | AC48: 進捗 | AD48: =SUM(U44:AE44) -> 1329500 | AE48: =AD48/AD47 -> 0.91061644 | AF48: 進捗 | AG48: =SUM(AF44:AH44) -> 549000 | AH48: =AG48/AG47 -> 0.80735294 | AJ48: 進捗 | AK48: =SUM(AI44:AL44) -> 1210000 | AL48: =AK48/AK47 -> 1.1504088 | BC48: 進捗 | BD48: =SUM(AN44:BE44) -> 2446010 | BE48: =BD48/BD47 -> 0.87670609 | BM48: 進捗 | BN48: =SUM(BF44:BO44) -> 831000 | BO48: =BN48/BN47 -> 0.831
A50: 設置店舗数 | B50: =M50+AE50+BG50+BQ50+AH50+T50+AO50 -> 33 | C50: 1 | D50: 1 | E50: 1 | F50: 1 | G50: 1 | H50: 1 | I50: 2 | L50: 3 | M50: 3 | N50: 1 | O50: 1 | P50: 1 | Q50: 2 | S50: 3 | T50: 3 | U50: 1 | V50: 1 | W50: 1 | X50: 2 | Y50: 2 | Z50: 3 | AB50: 4 | AD50: 5 | AE50: 5 | AH50: 1 | AI50: 1 | AJ50: 2 | AK50: 3 | AL50: 4 | AN50: 4 | AO50: 5 | AP50: 1 | AQ50: 1 | AR50: 2 | AS50: 2 | AT50: 2 | AU50: 3 | AV50: 3 | AW50: 3 | AX50: 4 | AY50: 4 | AZ50: 5 | BA50: 5 | BB50: 5 | BC50: 6 | BD50: 7 | BE50: 7 | BF50: 8 | BG50: 9 | BH50: 1 | BI50: 1 | BJ50: 2 | BK50: 3 | BL50: 4 | BM50: 5 | BN50: 6 | BO50: 6 | BQ50: 7 | BR50: =M50+AE50+AH50+AO50+BG50+BQ50+T50 -> 33 | BS50: 店舗
A51: 46023 | B51: 合計 | C51: 福重 | D51: 福重② | E51: 福重③ | F51: 福重④ | G51: 福重⑤ | H51: 福重⑥ | I51: 那珂川 | J51: 那珂川 | K51: 西新 | L51: 唐津 | M51: 唐津 | N51: 飯塚 | O51: 飯塚② | P51: 飯塚③ | Q51: 小倉 | S51: 黒崎 | T51: 黒崎② | U51: 宗像 | V51: 宗像② | W51: 宗像③ | X51: 魚町 | Y51: 魚町② | Z51: 鞍手 | AB51: 長府② | AC51: 宇部① | AD51: 宇部② | AE51: 宇部③ | AH51: 八女 | AI51: 浜町 | AJ51: 時津 | AK51: 大村 | AL51: 佐賀① | AN51: 佐賀② | AO51: 中州 | AP51: 宇宿① | AQ51: 宇宿② | AR51: 霧島① | AS51: 霧島② | AT51: 霧島500 | AU51: 川内① | AV51: 川内② | AW51: 川内500 | AX51: 都城① | AY51: 都城② | AZ51: 鹿屋① | BA51: 鹿屋② | BB51: 鹿屋500 | BC51: 菊陽② | BD51: 合志 | BE51: 合志 | BF51: 南熊本 | BG51: 下通 | BH51: 今宿 | BI51: 今宿➁ | BJ51: 八代 | BK51: 佐世保 | BL51: 別府 | BM51: 行橋 | BN51: 延岡① | BO51: 延岡② | BP51: Dプラ | BQ51: 光吉
A52: 設置台数 | B52: 57 | C52: 500GACHA | D52: 1000GACHA | E52: ティアラ | F52: ティアラ | G52: ティアラ | H52: ティアラ | I52: 1000GACHA | L52: 1000GACHA | M52: ティアラ | N52: 1000GACHA | O52: デカプセル | P52: ティアラ | Q52: ティアラ | S52: ティアラ | T52: 1000GACHA | U52: ガチャコロ1 | V52: 500GATCHA | W52: 500GATCHA | X52: ティアラ | Y52: 1000GACHA | Z52: ガチャコロ2 | AB52: 1000GACHA | AC52: ティアラ | AD52: 1000GACHA | AE52: 1000GACHA | AH52: ガチャコロ２ | AI52: 1000GACHA | AJ52: ガチャコロ２ | AK52: ガチャコロ２ | AL52: 1000GACHA | AN52: ガチャコロ2 | AO52: 1000GACHA | AP52: 1000GACHA | AR52: 1000GACHA | AS52: ティアラ | AT52: 500GATCHA | AU52: 1000GACHA | AV52: ティアラ | AW52: 500GATCHA | AX52: ティアラ | AY52: 1000GACHA | AZ52: 1000GACHA | BA52: 1000GACHA | BB52: 500GATCHA | BC52: ガチャコロ２ | BD52: ガチャコロ２ | BE52: 500GACHA | BF52: ティアラ | BG52: ガチャコロ２ | BH52: 1000GACHA | BI52: ガチャコロ2 | BJ52: 1000GACHA | BK52: ティアラ | BL52: ティアラ | BM52: ガチャコロ2 | BN52: 1000GACHA | BO52: 1000GACHA | BQ52: ティアラ
A53: ロッカー台数 | B53: =SUM(C53:BQ53) -> 148 | C53: 2 | D53: 2 | E53: 3 | F53: 3 | G53: 3 | H53: 3 | I53: 2 | L53: 2 | M53: 2 | N53: 2 | O53: 4 | P53: 3 | Q53: 2 | S53: 2 | T53: 2 | U53: 3 | V53: 2 | W53: 0 | X53: 6 | Y53: 2 | Z53: 4 | AB53: 2 | AC53: 2 | AD53: 2 | AE53: 2 | AH53: 4 | AI53: 2 | AJ53: 4 | AK53: 2 | AL53: 3 | AN53: 2 | AO53: 1 | AP53: 1 | AR53: 3 | AS53: 3 | AT53: 2 | AU53: 3 | AV53: 3 | AW53: 2 | AX53: 2 | AY53: 2 | AZ53: 3 | BA53: 3 | BB53: 2 | BC53: 4 | BD53: 4 | BE53: 3 | BF53: 2 | BG53: 3 | BH53: 2 | BI53: 4 | BJ53: 3 | BK53: 2 | BL53: 2 | BM53: 4 | BN53: 2 | BO53: 2 | BQ53: 2 | BR53: =SUM(C53:BQ53) -> 148 | BS53: ロッカー
A54: カプセル容量 | C54: 300 | D54: 300 | E54: 300 | F54: 300 | G54: 300 | H54: 300 | I54: 300 | L54: 300 | M54: 300 | N54: 300 | O54: 300 | P54: 300 | Q54: 300 | S54: 300 | T54: 300 | U54: 400 | V54: 150 | W54: 150 | X54: 150 | Y54: 300 | Z54: 400 | AB54: 300 | AC54: 300 | AD54: 300 | AE54: 300 | AH54: 400 | AI54: 300 | AJ54: 400 | AK54: 400 | AL54: 300 | AN54: 400 | AO54: 300 | AP54: 300 | AR54: 300 | AS54: 300 | AT54: 300 | AU54: 300 | AV54: 300 | AW54: 300 | AX54: 300 | AY54: 300 | AZ54: 300 | BA54: 300 | BB54: 300 | BC54: 400 | BD54: 400 | BE54: 300 | BF54: 300 | BG54: 400 | BH54: 300 | BI54: 400 | BJ54: 300 | BK54: 300 | BL54: 300 | BM54: 400 | BN54: 300 | BO54: 300 | BQ54: 300
A55: ガチャの種類 | C55: バラエティー | D55: バラエティー | E55: スニーカー | F55: ゲームソフト | G55: ブランド | H55: ゲーム機 | I55: バラエティー | L55: バラエティー | M55: バラエティー | N55: バラエティー | O55: バラエティー | P55: スニーカー | Q55: バラエティー | S55: バラエティー | T55: バラエティー | U55: バラエティー | V55: バラエティー | W55: バラエティー | X55: バラエティー | Y55: ポケモン | Z55: バラエティー | AB55: バラエティー | AC55: バラエティー | AD55: バラエティー | AE55: バラエティー(ポケモン） | AH55: バラエティー | AI55: バラエティー | AJ55: バラエティー | AK55: バラエティー | AL55: バラエティー | AN55: バラエティー | AO55: バラエティー | AP55: バラエティー | AR55: バラエティー | AS55: バラエティー | AT55: ポケモン | AU55: バラエティー | AV55: バラエティー | AW55: ポケモン | AX55: バラエティー | AY55: バラエティー | AZ55: バラエティー | BA55: バラエティー | BB55: バラエティー | BC55: バラエティー | BD55: バラエティー | BE55: バラエティー | BF55: バラエティー | BG55: バラエティー | BH55: バラエティー | BI55: バラエティー | BJ55: バラエティー | BK55: バラエティー | BL55: バラエティー | BM55: バラエティー | BN55: バラエティー | BO55: バラエティー | BQ55: バラエティー | BR55: ティアラ | BS55: 26
A56: プレイ料金 | C56: 500 | D56: 2000 | E56: 2000 | F56: 1000 | G56: 2000 | H56: 2000 | I56: 2000 | L56: 1000 | M56: 2000 | N56: 1000 | O56: 2000 | P56: 2000 | Q56: 1000 | S56: 2000 | T56: 1000 | U56: 2000 | V56: 500 | W56: 500 | X56: 2000 | Y56: 1000 | Z56: 2000 | AB56: 1000 | AC56: 1000 | AD56: 2000 | AE56: 2000 | AH56: 1000＆2000 | AI56: 1000 | AJ56: 1000＆2000 | AK56: 1000＆2000 | AL56: 1000 | AN56: 2000 | AO56: 2000 | AP56: 2000 | AR56: 1000 | AS56: 2000 | AT56: 500 | AU56: 1000 | AV56: 2000 | AW56: 500 | AX56: 1000 | AY56: 2000 | AZ56: 1000 | BA56: 2000 | BB56: 500 | BC56: 2000 | BD56: 2000 | BE56: 500 | BF56: 1000 | BG56: 1000＆2000 | BH56: 1000 | BI56: 2000 | BJ56: 2000 | BK56: 1000 | BL56: 2000 | BM56: 1000＆2000 | BN56: 1000 | BO56: 2000 | BQ56: 2000 | BR56: ガチャコロ1 | BS56: 2
A57: 前年度 | B57: =SUM(C57:BQ57) -> 14608200 | C57: 139000 | D57: 370000 | E57: 422000 | F57: 289000 | G57: 156000 | H57: 222000 | I57: 606000 | J57: 15000 | K57: 218000 | L57: 154000 | N57: 117000 | O57: 492000 | Q57: 337000 | S57: 358000 | T57: 332000 | U57: 496000 | V57: 31600 | W57: 36000 | X57: 94000 | Y57: 381000 | Z57: 376000 | AA57: 114000 | AB57: 182000 | AH57: 243000 | AI57: 221000 | AJ57: 407000 | AK57: 331000 | AL57: 250000 | AN57: 668000 | AP57: 283000 | AQ57: 50000 | AR57: 336000 | AS57: 246000 | AT57: 133200 | AU57: 418000 | AV57: 403000 | AW57: 156800 | AX57: 217000 | AY57: 164000 | BC57: 876000 | BD57: 315000 | BE57: 110600 | BG57: 550000 | BH57: 200000 | BI57: 314000 | BJ57: 370000 | BK57: 261000 | BL57: 254000 | BM57: 370000 | BN57: 199000 | BO57: 190000 | BP57: 4000 | BQ57: 130000 | BR57: ガチャコロ2 | BS57: 10
A58: 目標 | B58: =SUM(C58:BQ58) -> 14240000 | C58: 150000 | D58: 300000 | E58: 250000 | F58: 200000 | G58: 150000 | H58: 200000 | I58: 400000 | L58: 150000 | M58: 200000 | N58: 150000 | O58: 400000 | P58: 150000 | Q58: 300000 | S58: 300000 | T58: 350000 | U58: 400000 | V58: 60000 | W58: 60000 | X58: 100000 | Y58: 300000 | Z58: 300000 | AB58: 180000 | AC58: 150000 | AD58: 250000 | AE58: 200000 | AH58: 220000 | AI58: 220000 | AJ58: 400000 | AK58: 300000 | AL58: 200000 | AN58: 500000 | AO58: 1000000 | AP58: 250000 | AR58: 300000 | AS58: 220000 | AT58: 130000 | AU58: 350000 | AV58: 350000 | AW58: 150000 | AX58: 200000 | AY58: 150000 | AZ58: 150000 | BA58: 150000 | BB58: 150000 | BC58: 600000 | BD58: 250000 | BE58: 100000 | BF58: 200000 | BG58: 500000 | BH58: 150000 | BI58: 250000 | BJ58: 300000 | BK58: 200000 | BM58: 250000 | BN58: 150000 | BO58: 150000 | BQ58: 100000 | BR58: 1000GACHA | BS58: 15
BR59: デカプセル | BS59: 1
A60: 売上実績 | B60: =SUM(C60:BQ60) -> 16326300 | C60: =福重!F173 -> 235700 | D60: =福重!Q173 -> 224000 | E60: =福重!AT173 -> 188000 | F60: =福重!AA173 -> 181000 | G60: =福重!AG173 -> 152000 | H60: =福重!AM173 -> 342000 | I60: =那珂川!F67 -> 452000 | L60: =唐津!E61-47000 -> 303000 | M60: =唐津!K61-12000 -> 172000 | N60: =飯塚!S67 -> 352000 | O60: =飯塚!H67 -> 450000 | P60: =飯塚!AB67 -> 152000 | Q60: =小倉!F59 -> 277000 | S60: =+黒崎!F55 -> 426000 | T60: =+黒崎!Q55 -> 386000 | U60: 472000 | V60: 63000 | W60: 56500 | X60: 238000 | Y60: 486000 | Z60: 635000 | AB60: 252000 | AC60: 179000 | AD60: 292000 | AE60: 228000 | AH60: 289000 | AI60: 107000 | AJ60: 314000 | AK60: 581000 | AL60: 207000 | AN60: 558000 | AO60: 725000 | AP60: 230000 | AR60: 245000 | AS60: 282000 | AT60: 152800 | AU60: 345000 | AV60: 332000 | AW60: 272100 | AX60: 202000 | AY60: 202000 | AZ60: 127000 | BA60: 229000 | BB60: 181600 | BC60: 647000 | BD60: 258000 | BE60: 133600 | BF60: 143000 | BG60: 742000 | BH60: 144000 | BI60: 288000 | BJ60: 182000 | BK60: 228000 | BM60: 305000 | BN60: 158000 | BO60: 230000 | BQ60: 92000 | BR60: 500GACHA | BS60: 4
A61: 目標対比 | B61: =B60/B58 -> 1.1465098 | C61: =C60/C58 -> 1.5713333 | D61: =D60/D58 -> 0.74666667 | E61: =E60/E58 -> 0.752 | F61: =F60/F58 -> 0.905 | G61: =G60/G58 -> 1.0133333 | H61: =H60/H58 -> 1.71 | I61: =I60/I58 -> 1.13 | L61: =L60/L58 -> 2.02 | M61: =M60/M58 -> 0.86 | N61: =N60/N58 -> 2.3466667 | O61: =O60/O58 -> 1.125 | P61: =P60/P58 -> 1.0133333 | Q61: =Q60/Q58 -> 0.92333333 | S61: =S60/S58 -> 1.42 | T61: =T60/T58 -> 1.1028571 | U61: =U60/U58 -> 1.18 | V61: =V60/V58 -> 1.05 | W61: =W60/W58 -> 0.94166667 | X61: =X60/X58 -> 2.38 | Y61: =Y60/Y58 -> 1.62 | Z61: =Z60/Z58 -> 2.1166667 | AB61: =AB60/AB58 -> 1.4 | AC61: =AC60/AC58 -> 1.1933333 | AD61: =AD60/AD58 -> 1.168 | AE61: =AE60/AE58 -> 1.14 | AH61: =IFERROR(AH60/AH58,"-") -> 1.3136364 | AI61: =IFERROR(AI60/AI58,"-") -> 0.48636364 | AJ61: =IFERROR(AJ60/AJ58,"-") -> 0.785 | AK61: =IFERROR(AK60/AK58,"-") -> 1.9366667 | AL61: =IFERROR(AL60/AL58,"-") -> 1.035 | AN61: =IFERROR(AN60/AN58,"-") -> 1.116 | AO61: =IFERROR(AO60/AO58,"-") -> 0.725 | AP61: =IFERROR(AP60/AP58,"-") -> 0.92 | AR61: =IFERROR(AR60/AR58,"-") -> 0.81666667 | AS61: =IFERROR(AS60/AS58,"-") -> 1.2818182 | AT61: =IFERROR(AT60/AT58,"-") -> 1.1753846 | AU61: =IFERROR(AU60/AU58,"-") -> 0.98571429 | AV61: =IFERROR(AV60/AV58,"-") -> 0.94857143 | AW61: =IFERROR(AW60/AW58,"-") -> 1.814 | AX61: =IFERROR(AX60/AX58,"-") -> 1.01 | AY61: =IFERROR(AY60/AY58,"-") -> 1.3466667 | ... BO61: =IFERROR(BO60/BO58,"-") -> 1.5333333 | BQ61: =IFERROR(BQ60/BQ58,"-") -> 0.92 | BS61: =SUM(BS52:BS60) -> 58
A62: =B61 -> 1.1465098
A63: 予測達成率 | C63: 開始日 | D63: 全台AVE | E63: =B60/B52 -> 286426.32 | F63: ガチャ | G63: プライズ | K63: 売上目標 | L63: =SUM(C58:M58) -> 2000000 | Q63: 売上目標 | S63: =SUM(N58:T58) -> 1650000 | AC63: 売上目標 | AD63: =SUM(U58:AE58) -> 2000000 | AF63: 売上目標 | AG63: =SUM(AF58:AH58) -> 220000 | AL63: 売上目標 | AN63: =SUM(AI58:AO58) -> 2620000 | AS63: 新 | AY63: 新 | BE63: 売上目標 | BF63: =SUM(AP58:BG58) -> 4200000 | BO63: 売上目標 | BP63: =SUM(BH58:BQ58) -> 1550000
A64: 進捗率 | B64: 経過日数 | C64: 46008 | D64: 総売上 | E64: 46762400 | F64: =B60 -> 16326300 | G64: =E64-B60 -> 30436100 | K64: 進捗 | L64: =SUM(C60:M60) -> 2249700 | M64: =L64/L63 -> 1.12485 | Q64: 進捗 | S64: =SUM(N60:T60) -> 2043000 | T64: =S64/S63 -> 1.2381818 | AC64: 進捗 | AD64: =SUM(U60:AE60) -> 2901500 | AE64: =AD64/AD63 -> 1.45075 | AF64: 進捗 | AG64: =SUM(AF60:AH60) -> 289000 | AH64: =AG64/AG63 -> 1.3136364 | AL64: 進捗 | AN64: =SUM(AI60:AO60) -> 2492000 | AO64: =AN64/AN63 -> 0.95114504 | BE64: 進捗 | BF64: =SUM(AP60:BG60) -> 4724100 | BG64: =BF64/BF63 -> 1.1247857 | BO64: 進捗 | BP64: =SUM(BH60:BQ60) -> 1627000 | BQ64: =BP64/BP63 -> 1.0496774
A66: 設置店舗数 | B66: =M66+AE66+BG66+BQ66+AH66+T66+AO66 -> 32 | C66: 1 | D66: 1 | E66: 1 | F66: 1 | G66: 1 | H66: 1 | I66: 2 | L66: 3 | M66: 3 | N66: 1 | O66: 1 | P66: 1 | Q66: 2 | S66: 3 | T66: 3 | U66: 1 | V66: 1 | W66: 1 | X66: 2 | Y66: 2 | Z66: 3 | AB66: 4 | AD66: 5 | AE66: 5 | AH66: 1 | AI66: 1 | AJ66: 2 | AK66: 3 | AL66: 4 | AN66: 4 | AO66: 5 | AP66: 1 | AQ66: 1 | AR66: 2 | AS66: 2 | AT66: 2 | AU66: 3 | AV66: 3 | AW66: 3 | AX66: 4 | AY66: 4 | AZ66: 5 | BA66: 5 | BB66: 5 | BC66: 6 | BD66: 7 | BE66: 7 | BF66: 8 | BG66: 9 | BH66: 1 | BI66: 1 | BJ66: 2 | BK66: 3 | BM66: 4 | BN66: 5 | BO66: 5 | BQ66: 6 | BR66: =M66+AE66+AH66+AO66+BG66+BQ66+T66 -> 32 | BS66: 店舗
A67: 46054 | B67: 合計 | C67: 福重 | D67: 福重② | E67: 福重③ | F67: 福重④ | G67: 福重⑤ | H67: 福重⑥ | I67: 那珂川 | J67: 那珂川 | K67: 西新 | L67: 唐津 | M67: 唐津 | N67: 飯塚 | O67: 飯塚② | P67: 飯塚③ | Q67: 小倉 | S67: 黒崎 | T67: 黒崎② | U67: 宗像 | V67: 宗像② | W67: 宗像③ | X67: 魚町 | Y67: 魚町② | Z67: 鞍手 | AB67: 長府② | AC67: 宇部① | AD67: 宇部② | AE67: 宇部③ | AH67: 八女 | AI67: 浜町 | AJ67: 時津 | AK67: 大村 | AL67: 佐賀① | AN67: 佐賀② | AO67: 中州 | AP67: 宇宿① | AQ67: 宇宿② | AR67: 霧島① | AS67: 霧島② | AT67: 霧島500 | AU67: 川内① | AV67: 川内② | AW67: 川内500 | AX67: 都城① | AY67: 都城② | AZ67: 鹿屋① | BA67: 鹿屋② | BB67: 鹿屋500 | BC67: 菊陽② | BD67: 合志 | BE67: 合志 | BF67: 南熊本 | BG67: 下通 | BH67: 今宿 | BI67: 今宿➁ | BJ67: 八代 | BK67: 佐世保 | BM67: 行橋 | BN67: 延岡① | BO67: 延岡② | BP67: Dプラ | BQ67: 光吉
A68: 設置台数 | B68: 57 | C68: 500GACHA | D68: 1000GACHA | E68: ティアラ | F68: ティアラ | G68: ティアラ | H68: ティアラ | I68: 1000GACHA | L68: 1000GACHA | M68: ティアラ | N68: 1000GACHA | O68: デカプセル | P68: ティアラ | Q68: ティアラ | S68: ティアラ | T68: 1000GACHA | U68: ガチャコロ1 | V68: 500GATCHA | W68: 500GATCHA | X68: ティアラ | Y68: 1000GACHA | Z68: ガチャコロ2 | AB68: 1000GACHA | AC68: ティアラ | AD68: 1000GACHA | AE68: 1000GACHA | AH68: ガチャコロ２ | AI68: 1000GACHA | AJ68: ガチャコロ２ | AK68: ガチャコロ２ | AL68: 1000GACHA | AN68: ガチャコロ2 | AO68: 1000GACHA | AP68: 1000GACHA | AR68: 1000GACHA | AS68: ティアラ | AT68: 500GATCHA | AU68: 1000GACHA | AV68: ティアラ | AW68: 500GATCHA | AX68: ティアラ | AY68: 1000GACHA | AZ68: 1000GACHA | BA68: 1000GACHA | BB68: 500GATCHA | BC68: ガチャコロ２ | BD68: ガチャコロ２ | BE68: 500GACHA | BF68: ティアラ | BG68: ガチャコロ２ | BH68: 1000GACHA | BI68: ガチャコロ2 | BJ68: 1000GACHA | BK68: ティアラ | BM68: ガチャコロ2 | BN68: 1000GACHA | BO68: 1000GACHA | BQ68: ティアラ
A69: ロッカー台数 | B69: =SUM(C69:BQ69) -> 146 | C69: 2 | D69: 2 | E69: 3 | F69: 3 | G69: 3 | H69: 3 | I69: 2 | L69: 2 | M69: 2 | N69: 2 | O69: 4 | P69: 3 | Q69: 2 | S69: 2 | T69: 2 | U69: 3 | V69: 2 | W69: 0 | X69: 6 | Y69: 2 | Z69: 4 | AB69: 2 | AC69: 2 | AD69: 2 | AE69: 2 | AH69: 4 | AI69: 2 | AJ69: 4 | AK69: 2 | AL69: 3 | AN69: 2 | AO69: 1 | AP69: 1 | AR69: 3 | AS69: 3 | AT69: 2 | AU69: 3 | AV69: 3 | AW69: 2 | AX69: 2 | AY69: 2 | AZ69: 3 | BA69: 3 | BB69: 2 | BC69: 4 | BD69: 4 | BE69: 3 | BF69: 2 | BG69: 3 | BH69: 2 | BI69: 4 | BJ69: 3 | BK69: 2 | BM69: 4 | BN69: 2 | BO69: 2 | BQ69: 2 | BR69: =SUM(C69:BQ69) -> 146 | BS69: ロッカー
A70: カプセル容量 | C70: 300 | D70: 300 | E70: 300 | F70: 300 | G70: 300 | H70: 300 | I70: 300 | L70: 300 | M70: 300 | N70: 300 | O70: 300 | P70: 300 | Q70: 300 | S70: 300 | T70: 300 | U70: 400 | V70: 150 | W70: 150 | X70: 150 | Y70: 300 | Z70: 400 | AB70: 300 | AC70: 300 | AD70: 300 | AE70: 300 | AH70: 400 | AI70: 300 | AJ70: 400 | AK70: 400 | AL70: 300 | AN70: 400 | AO70: 300 | AP70: 300 | AR70: 300 | AS70: 300 | AT70: 300 | AU70: 300 | AV70: 300 | AW70: 300 | AX70: 300 | AY70: 300 | AZ70: 300 | BA70: 300 | BB70: 300 | BC70: 400 | BD70: 400 | BE70: 300 | BF70: 300 | BG70: 400 | BH70: 300 | BI70: 400 | BJ70: 300 | BK70: 300 | BM70: 400 | BN70: 300 | BO70: 300 | BQ70: 300
A71: ガチャの種類 | C71: バラエティー | D71: バラエティー | E71: スニーカー | F71: ゲームソフト | G71: ブランド | H71: ゲーム機 | I71: バラエティー | L71: バラエティー | M71: バラエティー | N71: バラエティー | O71: バラエティー | P71: スニーカー | Q71: バラエティー | S71: バラエティー | T71: バラエティー | U71: バラエティー | V71: バラエティー | W71: バラエティー | X71: バラエティー | Y71: ポケモン | Z71: バラエティー | AB71: バラエティー | AC71: バラエティー | AD71: バラエティー | AE71: バラエティー(ポケモン） | AH71: バラエティー | AI71: バラエティー | AJ71: バラエティー | AK71: バラエティー | AL71: バラエティー | AN71: バラエティー | AO71: バラエティー | AP71: バラエティー | AR71: バラエティー | AS71: バラエティー | AT71: ポケモン | AU71: バラエティー | AV71: バラエティー | AW71: ポケモン | AX71: バラエティー | AY71: バラエティー | AZ71: バラエティー | BA71: バラエティー | BB71: バラエティー | BC71: バラエティー | BD71: バラエティー | BE71: バラエティー | BF71: バラエティー | BG71: バラエティー | BH71: バラエティー | BI71: バラエティー | BJ71: バラエティー | BK71: バラエティー | BM71: バラエティー | BN71: バラエティー | BO71: バラエティー | BQ71: バラエティー | BR71: ティアラ | BS71: 26
A72: プレイ料金 | C72: 500 | D72: 2000 | E72: 2000 | F72: 1000 | G72: 2000 | H72: 2000 | I72: 2000 | L72: 1000 | M72: 2000 | N72: 1000 | O72: 2000 | P72: 2000 | Q72: 1000 | S72: 2000 | T72: 1000 | U72: 2000 | V72: 500 | W72: 500 | X72: 2000 | Y72: 1000 | Z72: 2000 | AB72: 1000 | AC72: 1000 | AD72: 2000 | AE72: 2000 | AH72: 1000＆2000 | AI72: 1000 | AJ72: 1000＆2000 | AK72: 1000＆2000 | AL72: 1000 | AN72: 2000 | AO72: 2000 | AP72: 2000 | AR72: 1000 | AS72: 2000 | AT72: 500 | AU72: 1000 | AV72: 2000 | AW72: 500 | AX72: 1000 | AY72: 2000 | AZ72: 1000 | BA72: 2000 | BB72: 500 | BC72: 2000 | BD72: 2000 | BE72: 500 | BF72: 1000 | BG72: 1000＆2000 | BH72: 1000 | BI72: 2000 | BJ72: 2000 | BK72: 1000 | BM72: 1000＆2000 | BN72: 1000 | BO72: 2000 | BQ72: 2000 | BR72: ガチャコロ1 | BS72: 2
A73: 前年度 | B73: =SUM(C73:BQ73) -> 10026400 | C73: 112500 | D73: 266000 | E73: 214000 | F73: 111000 | G73: 88000 | H73: 188000 | I73: 496000 | K73: 149000 | N73: 167000 | O73: 438000 | Q73: 247000 | S73: 230000 | T73: 309000 | U73: 440000 | V73: 45200 | W73: 40000 | X73: 128000 | Y73: 274000 | Z73: 291000 | AB73: 102000 | AC73: 132000 | AH73: 261000 | AI73: 168000 | AJ73: 266000 | AK73: 166000 | AL73: 221000 | AN73: 712000 | AP73: 143000 | AR73: 150000 | AS73: 190000 | AT73: 51500 | AU73: 160000 | AV73: 174000 | AW73: 78700 | AX73: 140000 | AY73: 78000 | BC73: 548000 | BD73: 438000 | BE73: 33500 | BG73: 397000 | BH73: 93000 | BI73: 169000 | BJ73: 145000 | BK73: 70000 | BL73: 182000 | BM73: 246000 | BN73: 134000 | BO73: 86000 | BQ73: 58000 | BR73: ガチャコロ2 | BS73: 10
A74: 目標 | B74: =SUM(C74:BQ74) -> 11930000 | C74: 150000 | D74: 200000 | E74: 180000 | F74: 150000 | G74: 120000 | H74: 180000 | I74: 450000 | L74: 200000 | M74: 200000 | N74: 200000 | O74: 400000 | P74: 130000 | Q74: 200000 | S74: 300000 | T74: 250000 | U74: 400000 | V74: 50000 | W74: 50000 | X74: 150000 | Y74: 400000 | Z74: 280000 | AB74: 150000 | AC74: 150000 | AD74: 200000 | AE74: 150000 | AH74: 250000 | AI74: 150000 | AJ74: 270000 | AK74: 200000 | AL74: 200000 | AN74: 500000 | AO74: 500000 | AP74: 160000 | AR74: 150000 | AS74: 200000 | AT74: 100000 | AU74: 250000 | AV74: 250000 | AW74: 150000 | AX74: 150000 | AY74: 150000 | AZ74: 120000 | BA74: 200000 | BB74: 100000 | BC74: 500000 | BD74: 400000 | BE74: 70000 | BF74: 120000 | BG74: 350000 | BH74: 100000 | BI74: 150000 | BJ74: 140000 | BK74: 120000 | BM74: 240000 | BN74: 120000 | BO74: 200000 | BQ74: 80000 | BR74: 1000GACHA | BS74: 15
BR75: デカプセル | BS75: 1
A76: 売上実績 | B76: =SUM(C76:BQ76) -> 8962800 | C76: =福重!F217-200 -> 138000 | D76: =福重!Q217 -> 134000 | E76: =福重!AT217 -> 126000 | F76: =福重!AA217 -> 128000 | G76: =福重!AG217 -> 64000 | H76: =福重!AM217 -> 76000 | I76: =那珂川!F84+2000 -> 272000 | L76: =唐津!E78-24000 -> 132000 | M76: =唐津!K78-2000 -> 48000 | N76: =飯塚!S84 -> 215000 | O76: =飯塚!H84 -> 212000 | P76: =飯塚!AB84 -> 44000 | Q76: =小倉!F74 -> 195000 | S76: =+黒崎!F69 -> 242000 | T76: =+黒崎!Q69 -> 359000 | U76: 248000 | V76: 24000 | W76: 27500 | X76: 264000 | Y76: 474000 | Z76: 237000 | AB76: 157000 | AC76: 119000 | AD76: 138000 | AE76: 238000 | AH76: 251000 | AI76: 37000 | AJ76: 152000 | AK76: 113000 | AL76: 102000 | AN76: 283000 | AO76: 418000 | AP76: 177000 | AR76: 86000 | AS76: 118000 | AT76: 74500 | AU76: 234000 | AV76: 226000 | AW76: 128700 | AX76: 83000 | AY76: 85000 | AZ76: 74000 | BA76: 66000 | BB76: 52600 | BC76: 333000 | BD76: 129000 | BE76: 185500 | BF76: 80000 | BG76: 288000 | BH76: 50000 | BI76: 136000 | BJ76: 104000 | BK76: 83000 | BM76: 186000 | BN76: 100000 | BO76: 120000 | BQ76: 96000 | BR76: 500GACHA | BS76: 4
A77: 目標対比 | B77: =B76/B74 -> 0.75128248 | C77: =C76/C74 -> 0.92 | D77: =D76/D74 -> 0.67 | E77: =E76/E74 -> 0.7 | F77: =F76/F74 -> 0.85333333 | G77: =G76/G74 -> 0.53333333 | H77: =H76/H74 -> 0.42222222 | I77: =I76/I74 -> 0.60444444 | L77: =L76/L74 -> 0.66 | M77: =M76/M74 -> 0.24 | N77: =N76/N74 -> 1.075 | O77: =O76/O74 -> 0.53 | P77: =P76/P74 -> 0.33846154 | Q77: =Q76/Q74 -> 0.975 | S77: =S76/S74 -> 0.80666667 | T77: =T76/T74 -> 1.436 | U77: =U76/U74 -> 0.62 | V77: =V76/V74 -> 0.48 | W77: =W76/W74 -> 0.55 | X77: =X76/X74 -> 1.76 | Y77: =Y76/Y74 -> 1.185 | Z77: =Z76/Z74 -> 0.84642857 | AB77: =AB76/AB74 -> 1.0466667 | AC77: =AC76/AC74 -> 0.79333333 | AD77: =AD76/AD74 -> 0.69 | AE77: =AE76/AE74 -> 1.5866667 | AH77: =IFERROR(AH76/AH74,"-") -> 1.004 | AI77: =IFERROR(AI76/AI74,"-") -> 0.24666667 | AJ77: =IFERROR(AJ76/AJ74,"-") -> 0.56296296 | AK77: =IFERROR(AK76/AK74,"-") -> 0.565 | AL77: =IFERROR(AL76/AL74,"-") -> 0.51 | AN77: =IFERROR(AN76/AN74,"-") -> 0.566 | AO77: =IFERROR(AO76/AO74,"-") -> 0.836 | AP77: =IFERROR(AP76/AP74,"-") -> 1.10625 | AR77: =IFERROR(AR76/AR74,"-") -> 0.57333333 | AS77: =IFERROR(AS76/AS74,"-") -> 0.59 | AT77: =IFERROR(AT76/AT74,"-") -> 0.745 | AU77: =IFERROR(AU76/AU74,"-") -> 0.936 | AV77: =IFERROR(AV76/AV74,"-") -> 0.904 | AW77: =IFERROR(AW76/AW74,"-") -> 0.858 | AX77: =IFERROR(AX76/AX74,"-") -> 0.55333333 | AY77: =IFERROR(AY76/AY74,"-") -> 0.56666667 | ... BO77: =IFERROR(BO76/BO74,"-") -> 0.6 | BQ77: =IFERROR(BQ76/BQ74,"-") -> 1.2 | BS77: =SUM(BS68:BS76) -> 58
A78: =B77 -> 0.75128248
A79: 予測達成率 | C79: 開始日 | D79: 全台AVE | E79: =B76/B68 -> 157242.11 | F79: ガチャ | G79: プライズ | K79: 売上目標 | L79: =SUM(C74:M74) -> 1830000 | Q79: 売上目標 | S79: =SUM(N74:T74) -> 1480000 | AC79: 売上目標 | AD79: =SUM(U74:AE74) -> 1980000 | AF79: 売上目標 | AG79: =SUM(AF74:AH74) -> 250000 | AL79: 売上目標 | AN79: =SUM(AI74:AO74) -> 1820000 | AS79: 新 | AY79: 新 | BE79: 売上目標 | BF79: =SUM(AP74:BG74) -> 3420000 | BO79: 売上目標 | BP79: =SUM(BH74:BQ74) -> 1150000
A80: 進捗率 | B80: 経過日数 | C80: 46039 | D80: 総売上 | E80: 36558400 | F80: =B76 -> 8962800 | G80: =E80-B76 -> 27595600 | K80: 進捗 | L80: =SUM(C76:M76) -> 1118000 | M80: =L80/L79 -> 0.61092896 | Q80: 進捗 | S80: =SUM(N76:T76) -> 1267000 | T80: =S80/S79 -> 0.85608108 | AC80: 進捗 | AD80: =SUM(U76:AE76) -> 1926500 | AE80: =AD80/AD79 -> 0.9729798 | AF80: 進捗 | AG80: =SUM(AF76:AH76) -> 251000 | AH80: =AG80/AG79 -> 1.004 | AL80: 進捗 | AN80: =SUM(AI76:AO76) -> 1105000 | AO80: =AN80/AN79 -> 0.60714286 | BE80: 進捗 | BF80: =SUM(AP76:BG76) -> 2420300 | BG80: =BF80/BF79 -> 0.70769006 | BO80: 進捗 | BP80: =SUM(BH76:BQ76) -> 875000 | BQ80: =BP80/BP79 -> 0.76086957
A82: 設置店舗数 | B82: =M82+AE82+BG82+BQ82+AH82+T82+AO82 -> 32 | C82: 1 | D82: 1 | E82: 1 | F82: 1 | G82: 1 | H82: 1 | I82: 2 | L82: 3 | M82: 3 | N82: 1 | O82: 1 | P82: 1 | Q82: 2 | S82: 3 | T82: 3 | U82: 1 | V82: 1 | W82: 1 | X82: 2 | Y82: 2 | Z82: 3 | AB82: 4 | AD82: 5 | AE82: 5 | AH82: 1 | AI82: 1 | AJ82: 2 | AL82: 3 | AN82: 3 | AO82: 4 | AP82: 1 | AQ82: 1 | AR82: 2 | AS82: 2 | AT82: 2 | AU82: 3 | AV82: 3 | AW82: 3 | AX82: 4 | AY82: 4 | AZ82: 5 | BA82: 5 | BB82: 5 | BC82: 6 | BD82: 7 | BE82: 7 | BF82: 8 | BG82: 9 | BH82: 1 | BI82: 1 | BJ82: 2 | BK82: 3 | BL82: 4 | BM82: 5 | BN82: 6 | BO82: 6 | BQ82: 7 | BR82: =M82+AE82+AH82+AO82+BG82+BQ82+T82 -> 32 | BS82: 店舗
A83: 46082 | B83: 合計 | C83: 福重 | D83: 福重② | E83: 福重③ | F83: 福重④ | G83: 福重⑤ | H83: 福重⑥ | I83: 那珂川 | J83: 那珂川 | K83: 西新 | L83: 唐津 | M83: 唐津 | N83: 飯塚 | O83: 飯塚② | P83: 飯塚③ | Q83: 小倉 | S83: 黒崎 | T83: 黒崎② | U83: 宗像 | V83: 宗像② | W83: 宗像③ | X83: 魚町 | Y83: 魚町② | Z83: 鞍手 | AB83: 長府② | AC83: 宇部① | AD83: 宇部② | AE83: 宇部③ | AH83: 八女 | AI83: 浜町 | AJ83: 時津 | AL83: 佐賀① | AN83: 佐賀② | AO83: 中州 | AP83: 宇宿① | AQ83: 宇宿② | AR83: 霧島① | AS83: 霧島② | AT83: 霧島500 | AU83: 川内① | AV83: 川内② | AW83: 川内500 | AX83: 都城① | AY83: 都城② | AZ83: 鹿屋① | BA83: 鹿屋② | BB83: 鹿屋500 | BC83: 菊陽② | BD83: 合志 | BE83: 合志 | BF83: 南熊本 | BG83: 下通 | BH83: 今宿 | BI83: 今宿➁ | BJ83: 八代 | BK83: 佐世保 | BL83: 大村 | BM83: 行橋 | BN83: 延岡① | BO83: 延岡② | BP83: Dプラ | BQ83: 光吉
A84: 設置台数 | B84: 57 | C84: 500GACHA | D84: 1000GACHA | E84: ティアラ | F84: ティアラ | G84: ティアラ | H84: ティアラ | I84: 1000GACHA | L84: 1000GACHA | M84: ティアラ | N84: 1000GACHA | O84: デカプセル | P84: ティアラ | Q84: ティアラ | S84: ティアラ | T84: 1000GACHA | U84: ガチャコロ1 | V84: 500GATCHA | W84: 500GATCHA | X84: ティアラ | Y84: 1000GACHA | Z84: ガチャコロ2 | AB84: 1000GACHA | AC84: ティアラ | AD84: 1000GACHA | AE84: 1000GACHA | AH84: ガチャコロ２ | AI84: 1000GACHA | AJ84: ガチャコロ２ | AL84: 1000GACHA | AN84: ガチャコロ2 | AO84: 1000GACHA | AP84: 1000GACHA | AR84: 1000GACHA | AS84: ティアラ | AT84: 500GATCHA | AU84: 1000GACHA | AV84: ティアラ | AW84: 500GATCHA | AX84: ティアラ | AY84: 1000GACHA | AZ84: 1000GACHA | BA84: 1000GACHA | BB84: 500GATCHA | BC84: ガチャコロ２ | BD84: ガチャコロ２ | BE84: 500GACHA | BF84: ティアラ | BG84: ガチャコロ２ | BH84: 1000GACHA | BI84: ガチャコロ2 | BJ84: 1000GACHA | BK84: ティアラ | BL84: ガチャコロ２ | BM84: ガチャコロ2 | BN84: 1000GACHA | BO84: 1000GACHA | BQ84: ティアラ
A85: ロッカー台数 | B85: =SUM(C85:BQ85) -> 146 | C85: 2 | D85: 2 | E85: 3 | F85: 3 | G85: 3 | H85: 3 | I85: 2 | L85: 2 | M85: 2 | N85: 2 | O85: 4 | P85: 3 | Q85: 2 | S85: 2 | T85: 2 | U85: 3 | V85: 2 | W85: 0 | X85: 6 | Y85: 2 | Z85: 4 | AB85: 2 | AC85: 2 | AD85: 2 | AE85: 2 | AH85: 4 | AI85: 2 | AJ85: 4 | AL85: 3 | AN85: 2 | AO85: 1 | AP85: 1 | AR85: 3 | AS85: 3 | AT85: 2 | AU85: 3 | AV85: 3 | AW85: 2 | AX85: 2 | AY85: 2 | AZ85: 3 | BA85: 3 | BB85: 2 | BC85: 4 | BD85: 4 | BE85: 3 | BF85: 2 | BG85: 3 | BH85: 2 | BI85: 4 | BJ85: 3 | BK85: 2 | BL85: 2 | BM85: 4 | BN85: 2 | BO85: 2 | BQ85: 2 | BR85: =SUM(C85:BQ85) -> 146 | BS85: ロッカー
A86: カプセル容量 | C86: 300 | D86: 300 | E86: 300 | F86: 300 | G86: 300 | H86: 300 | I86: 300 | L86: 300 | M86: 300 | N86: 300 | O86: 300 | P86: 300 | Q86: 300 | S86: 300 | T86: 300 | U86: 400 | V86: 150 | W86: 150 | X86: 150 | Y86: 300 | Z86: 400 | AB86: 300 | AC86: 300 | AD86: 300 | AE86: 300 | AH86: 400 | AI86: 300 | AJ86: 400 | AL86: 300 | AN86: 400 | AO86: 300 | AP86: 300 | AR86: 300 | AS86: 300 | AT86: 300 | AU86: 300 | AV86: 300 | AW86: 300 | AX86: 300 | AY86: 300 | AZ86: 300 | BA86: 300 | BB86: 300 | BC86: 400 | BD86: 400 | BE86: 300 | BF86: 300 | BG86: 400 | BH86: 300 | BI86: 400 | BJ86: 300 | BK86: 300 | BL86: 400 | BM86: 400 | BN86: 300 | BO86: 300 | BQ86: 300
A87: ガチャの種類 | C87: バラエティー | D87: バラエティー | E87: スニーカー | F87: ゲームソフト | G87: ブランド | H87: ゲーム機 | I87: バラエティー | L87: バラエティー | M87: バラエティー | N87: バラエティー | O87: バラエティー | P87: スニーカー | Q87: バラエティー | S87: バラエティー | T87: バラエティー | U87: バラエティー | V87: バラエティー | W87: バラエティー | X87: バラエティー | Y87: ポケモン | Z87: バラエティー | AB87: バラエティー | AC87: バラエティー | AD87: バラエティー | AE87: バラエティー(ポケモン） | AH87: バラエティー | AI87: バラエティー | AJ87: バラエティー | AL87: バラエティー | AN87: バラエティー | AO87: バラエティー | AP87: バラエティー | AR87: バラエティー | AS87: バラエティー | AT87: ポケモン | AU87: バラエティー | AV87: バラエティー | AW87: ポケモン | AX87: バラエティー | AY87: バラエティー | AZ87: バラエティー | BA87: バラエティー | BB87: バラエティー | BC87: バラエティー | BD87: バラエティー | BE87: バラエティー | BF87: バラエティー | BG87: バラエティー | BH87: バラエティー | BI87: バラエティー | BJ87: バラエティー | BK87: バラエティー | BL87: バラエティー | BM87: バラエティー | BN87: バラエティー | BO87: バラエティー | BQ87: バラエティー | BR87: ティアラ | BS87: 26
A88: プレイ料金 | C88: 500 | D88: 2000 | E88: 2000 | F88: 1000 | G88: 2000 | H88: 2000 | I88: 2000 | L88: 1000 | M88: 2000 | N88: 1000 | O88: 2000 | P88: 2000 | Q88: 1000 | S88: 2000 | T88: 1000 | U88: 2000 | V88: 500 | W88: 500 | X88: 2000 | Y88: 1000 | Z88: 2000 | AB88: 1000 | AC88: 1000 | AD88: 2000 | AE88: 2000 | AH88: 1000＆2000 | AI88: 1000 | AJ88: 1000＆2000 | AL88: 1000 | AN88: 2000 | AO88: 2000 | AP88: 2000 | AR88: 1000 | AS88: 2000 | AT88: 500 | AU88: 1000 | AV88: 2000 | AW88: 500 | AX88: 1000 | AY88: 2000 | AZ88: 1000 | BA88: 2000 | BB88: 500 | BC88: 2000 | BD88: 2000 | BE88: 500 | BF88: 1000 | BG88: 1000＆2000 | BH88: 1000 | BI88: 2000 | BJ88: 2000 | BK88: 1000 | BL88: 1000＆2000 | BM88: 1000＆2000 | BN88: 1000 | BO88: 2000 | BQ88: 2000 | BR88: ガチャコロ1 | BS88: 2
A89: 前年度 | B89: =SUM(C89:BQ89) -> 7327800 | C89: 130500 | D89: 100000 | E89: 104000 | F89: 93000 | G89: 108000 | H89: 128000 | I89: 224000 | K89: 130000 | N89: 107000 | O89: 262000 | Q89: 135000 | S89: 240000 | T89: 100000 | U89: 186000 | V89: 38500 | W89: 38500 | X89: 88000 | Y89: 425000 | Z89: 143000 | AB89: 98000 | AC89: 123000 | AH89: 96000 | AI89: 105000 | AJ89: 218000 | AL89: 101000 | AN89: 245000 | AP89: 184000 | AR89: 83000 | AS89: 162000 | AT89: 35500 | AU89: 253000 | AV89: 276000 | AW89: 74200 | AX89: 103000 | AY89: 136000 | BC89: 524000 | BD89: 279000 | BE89: 34600 | BG89: 310000 | BH89: 51000 | BI89: 275000 | BJ89: 178000 | BK89: 68000 | BL89: 138000 | BM89: 151000 | BN89: 103000 | BO89: 82000 | BQ89: 61000 | BR89: ガチャコロ2 | BS89: 10
A90: 目標 | B90: =SUM(C90:BQ90) -> 8508000 | C90: 130000 | D90: 120000 | E90: 110000 | F90: 100000 | G90: 100000 | H90: 100000 | I90: 250000 | L90: 100000 | M90: 100000 | N90: 150000 | O90: 230000 | P90: 100000 | Q90: 160000 | S90: 240000 | T90: 230000 | U90: =(U76+U89)/2 -> 217000 | V90: 35000 | W90: 35000 | X90: 180000 | Y90: 450000 | Z90: 190000 | AA90: =(AA76+AA89)/2 -> 0 | AB90: 128000 | AC90: =(AC76+AC89)/2 -> 121000 | AD90: 100000 | AE90: 120000 | AF90: =(AF76+AF89)/2 -> 0 | AG90: =(AG76+AG89)/2 -> 0 | AH90: 175000 | AI90: 100000 | AJ90: =(AJ76+AJ89)/2 -> 185000 | AL90: 100000 | AN90: 230000 | AO90: =(AO76+AO89)/2 -> 209000 | AP90: =(AP76+AP89)/2 -> 180500 | AQ90: =(AQ76+AQ89)/2 -> 0 | AR90: 100000 | AS90: =(AS76+AS89)/2 -> 140000 | AT90: =(AT76+AT89)/2 -> 55000 | AU90: =(AU76+AU89)/2 -> 243500 | AV90: =(AV76+AV89)/2 -> 251000 | AW90: 99000 | AX90: 100000 | AY90: 120000 | AZ90: 100000 | BA90: 100000 | BB90: 60000 | BC90: 430000 | BD90: =(BD76+BD89)/2 -> 204000 | BE90: 92000 | BF90: 100000 | BG90: 300000 | BH90: 100000 | BI90: 200000 | BJ90: =(BJ76+BJ89)/2 -> 141000 | BK90: 80000 | BL90: =(BL76+BL89)/2 -> 69000 | BM90: 170000 | BN90: 100000 | BO90: 100000 | BP90: =(BP76+BP89)/2 -> 0 | BQ90: 78000 | BR90: 1000GACHA | BS90: 15
BR91: デカプセル | BS91: 1
A92: 売上実績 | B92: =SUM(C92:BQ92) -> 6869800 | C92: =福重!F261-5800 -> 92000 | D92: =福重!Q261 -> 98000 | E92: =福重!AT261 -> 124000 | F92: =福重!AA261 -> 76000 | G92: =福重!AG261 -> 42000 | H92: =福重!AM261 -> 90000 | I92: =那珂川!F101+16000 -> 298000 | L92: =唐津!E95 -> 93000 | M92: =唐津!K95 -> 58000 | N92: =飯塚!S101 -> 111000 | O92: =飯塚!H101 -> 122000 | P92: =飯塚!AB101 -> 42000 | Q92: =小倉!F89 -> 150000 | S92: =+黒崎!F83 -> 178000 | T92: =+黒崎!Q83 -> 197000 | U92: 282000 | V92: 20000 | W92: 26000 | X92: 116000 | Y92: 130000 | Z92: 161000 | AB92: 160000 | AC92: 64000 | AD92: 106000 | AE92: 66000 | AH92: 245000 | AI92: 41000 | AJ92: 217000 | AL92: 48000 | AN92: 242000 | AO92: 337000 | AP92: 45000 | AR92: 48000 | AS92: 194000 | AT92: 74800 | AU92: 137000 | AV92: 116000 | AW92: 76700 | AX92: 123000 | AY92: 64000 | AZ92: 72000 | BA92: 58000 | BB92: 86300 | BC92: 308000 | BD92: 206000 | BE92: 107000 | BF92: 102000 | BG92: 314000 | BH92: 37000 | BI92: 137000 | BJ92: 62000 | BK92: 50000 | BL92: 86000 | BM92: 166000 | BN92: 24000 | BO92: 94000 | BQ92: 50000 | BR92: 500GACHA | BS92: 4
A93: 目標対比 | B93: =B92/B90 -> 0.80745181 | C93: =C92/C90 -> 0.70769231 | D93: =D92/D90 -> 0.81666667 | E93: =E92/E90 -> 1.1272727 | F93: =F92/F90 -> 0.76 | G93: =G92/G90 -> 0.42 | H93: =H92/H90 -> 0.9 | I93: =I92/I90 -> 1.192 | L93: =L92/L90 -> 0.93 | M93: =M92/M90 -> 0.58 | N93: =N92/N90 -> 0.74 | O93: =O92/O90 -> 0.53043478 | P93: =P92/P90 -> 0.42 | Q93: =Q92/Q90 -> 0.9375 | S93: =S92/S90 -> 0.74166667 | T93: =T92/T90 -> 0.85652174 | U93: =U92/U90 -> 1.2995392 | V93: =V92/V90 -> 0.57142857 | W93: =W92/W90 -> 0.74285714 | X93: =X92/X90 -> 0.64444444 | Y93: =Y92/Y90 -> 0.28888889 | Z93: =Z92/Z90 -> 0.84736842 | AB93: =AB92/AB90 -> 1.25 | AC93: =AC92/AC90 -> 0.52892562 | AD93: =AD92/AD90 -> 1.06 | AE93: =AE92/AE90 -> 0.55 | AH93: =IFERROR(AH92/AH90,"-") -> 1.4 | AI93: =IFERROR(AI92/AI90,"-") -> 0.41 | AJ93: =IFERROR(AJ92/AJ90,"-") -> 1.172973 | AL93: =IFERROR(AL92/AL90,"-") -> 0.48 | AN93: =IFERROR(AN92/AN90,"-") -> 1.0521739 | AO93: =IFERROR(AO92/AO90,"-") -> 1.6124402 | AP93: =IFERROR(AP92/AP90,"-") -> 0.24930748 | AR93: =IFERROR(AR92/AR90,"-") -> 0.48 | AS93: =IFERROR(AS92/AS90,"-") -> 1.3857143 | AT93: =IFERROR(AT92/AT90,"-") -> 1.36 | AU93: =IFERROR(AU92/AU90,"-") -> 0.56262834 | AV93: =IFERROR(AV92/AV90,"-") -> 0.46215139 | AW93: =IFERROR(AW92/AW90,"-") -> 0.77474747 | AX93: =IFERROR(AX92/AX90,"-") -> 1.23 | AY93: =IFERROR(AY92/AY90,"-") -> 0.53333333 | ... BO93: =IFERROR(BO92/BO90,"-") -> 0.94 | BQ93: =IFERROR(BQ92/BQ90,"-") -> 0.64102564 | BS93: =SUM(BS84:BS92) -> 58
A94: =B93 -> 0.80745181 | B94: =SUM(C94:BQ94) -> 6869800 | C94: =C92/$A$97 -> 92000 | D94: =D92/$A$97 -> 98000 | E94: =E92/$A$97 -> 124000 | F94: =F92/$A$97 -> 76000 | G94: =G92/$A$97 -> 42000 | H94: =H92/$A$97 -> 90000 | I94: =I92/$A$97 -> 298000 | L94: =L92/$A$97 -> 93000 | M94: =M92/$A$97 -> 58000 | N94: =N92/$A$97 -> 111000 | O94: =O92/$A$97 -> 122000 | P94: =P92/$A$97 -> 42000 | Q94: =Q92/$A$97 -> 150000 | S94: =S92/$A$97 -> 178000 | T94: =T92/$A$97 -> 197000 | U94: =U92/$A$97 -> 282000 | V94: =V92/$A$97 -> 20000 | W94: =W92/$A$97 -> 26000 | X94: =X92/$A$97 -> 116000 | Y94: =Y92/$A$97 -> 130000 | Z94: =Z92/$A$97 -> 161000 | AB94: =AB92/$A$97 -> 160000 | AC94: =AC92/$A$97 -> 64000 | AD94: =AD92/$A$97 -> 106000 | AE94: =AE92/$A$97 -> 66000 | AH94: =AH92/$A$97 -> 245000 | AI94: =AI92/$A$97 -> 41000 | AJ94: =AJ92/$A$97 -> 217000 | AL94: =AL92/$A$97 -> 48000 | AN94: =AN92/$A$97 -> 242000 | AO94: =AO92/$A$97 -> 337000 | AP94: =AP92/$A$97 -> 45000 | AR94: =AR92/$A$97 -> 48000 | AS94: =AS92/$A$97 -> 194000 | AT94: =AT92/$A$97 -> 74800 | AU94: =AU92/$A$97 -> 137000 | AV94: =AV92/$A$97 -> 116000 | AW94: =AW92/$A$97 -> 76700 | AX94: =AX92/$A$97 -> 123000 | AY94: =AY92/$A$97 -> 64000 | ... BO94: =BO92/$A$97 -> 94000 | BQ94: =BQ92/$A$97 -> 50000
A95: 予測達成率 | B95: =B94/B90 -> 0.80745181 | C95: 開始日 | D95: 全台AVE | E95: =B92/B84 -> 120522.81 | F95: ガチャ | G95: プライズ | K95: 売上目標 | L95: =SUM(C90:M90) -> 1110000 | Q95: 売上目標 | S95: =SUM(N90:T90) -> 1110000 | AC95: 売上目標 | AD95: =SUM(U90:AE90) -> 1576000 | AF95: 売上目標 | AG95: =SUM(AF90:AH90) -> 175000 | AL95: 売上目標 | AN95: =SUM(AI90:AO90) -> 824000 | AS95: 新 | AY95: 新 | BE95: 売上目標 | BF95: =SUM(AP90:BG90) -> 2675000 | BO95: 売上目標 | BP95: =SUM(BH90:BQ90) -> 1038000
A96: 進捗率 | B96: 経過日数 | C96: 46070 | D96: 総売上 | E96: 35643100 | F96: =B92 -> 6869800 | G96: =E96-B92 -> 28773300 | K96: 進捗 | L96: =SUM(C92:M92) -> 971000 | M96: =L96/L95 -> 0.87477477 | Q96: 進捗 | S96: =SUM(N92:T92) -> 800000 | T96: =S96/S95 -> 0.72072072 | AC96: 進捗 | AD96: =SUM(U92:AE92) -> 1131000 | AE96: =AD96/AD95 -> 0.71763959 | AF96: 進捗 | AG96: =SUM(AF92:AH92) -> 245000 | AH96: =AG96/AG95 -> 1.4 | AL96: 進捗 | AN96: =SUM(AI92:AO92) -> 885000 | AO96: =AN96/AN95 -> 1.0740291 | BE96: 進捗 | BF96: =SUM(AP92:BG92) -> 2131800 | BG96: =BF96/BF95 -> 0.79693458 | BO96: 進捗 | BP96: =SUM(BH92:BQ92) -> 706000 | BQ96: =BP96/BP95 -> 0.68015414
A97: 1 | K97: 売上予想 | L97: =SUM(C94:M94) -> 971000 | M97: =L97/L95 -> 0.87477477 | Q97: 売上予想 | S97: =SUM(N94:T94) -> 800000 | T97: =S97/S95 -> 0.72072072 | AC97: 売上予想 | AD97: =SUM(U94:AE94) -> 1131000 | AE97: =AD97/AD95 -> 0.71763959 | AF97: 売上予想 | AG97: =SUM(AH94) -> 245000 | AH97: =AG97/AG95 -> 1.4 | AL97: 売上予想 | AN97: =SUM(AI94:AO94) -> 885000 | AO97: =AN97/AN95 -> 1.0740291 | BE97: 売上予想 | BF97: =SUM(AP94:BG94) -> 2131800 | BG97: =BF97/BF95 -> 0.79693458 | BO97: 売上予想 | BP97: =SUM(BH94:BQ94) -> 706000 | BQ97: =BP97/BP95 -> 0.68015414
A99: 設置店舗数 | B99: =M99+AE99+BG99+BQ99+AH99+T99+AO99+BB99 -> 32 | C99: 1 | D99: 1 | E99: 1 | F99: 1 | G99: 1 | H99: 1 | I99: 2 | L99: 3 | M99: 3 | N99: 1 | O99: 1 | P99: 1 | Q99: 2 | R99: 2 | S99: 3 | T99: 3 | U99: 1 | V99: 1 | W99: 1 | X99: 2 | Y99: 2 | Z99: 3 | AB99: 4 | AD99: 5 | AE99: 5 | AH99: 1 | AI99: 1 | AJ99: 2 | AL99: 3 | AN99: 3 | AO99: 4 | AP99: 1 | AQ99: 1 | AR99: 2 | AS99: 2 | AT99: 2 | AU99: 3 | AV99: 3 | AW99: 3 | AX99: 4 | AY99: 4 | AZ99: 5 | BA99: 5 | BB99: 5 | BC99: 1 | BD99: 2 | BE99: 2 | BF99: 3 | BG99: 4 | BH99: 1 | BI99: 1 | BJ99: 2 | BK99: 3 | BL99: 4 | BM99: 5 | BN99: 6 | BO99: 6 | BQ99: 7 | BR99: =M99+AE99+AH99+AO99+BG99+BQ99+T99+BB99 -> 32 | BS99: 店舗
A100: 46113 | B100: 合計 | C100: 福重 | D100: 福重② | E100: 福重③ | F100: 福重④ | G100: 福重⑤ | H100: 福重⑥ | I100: 那珂川 | J100: 那珂川 | K100: 西新 | L100: 唐津 | M100: 唐津 | N100: 飯塚 | O100: 飯塚② | P100: 飯塚③ | Q100: 小倉 | R100: 小倉 | S100: 黒崎 | T100: 黒崎② | U100: 宗像 | V100: 宗像② | W100: 宗像③ | X100: 魚町 | Y100: 魚町② | Z100: 鞍手 | AB100: 長府② | AC100: 宇部① | AD100: 宇部② | AE100: 宇部③ | AH100: 八女 | AI100: 浜町 | AJ100: 時津 | AL100: 佐賀① | AN100: 佐賀② | AO100: 中州 | AP100: 宇宿① | AQ100: 宇宿② | AR100: 霧島① | AS100: 霧島② | AT100: 霧島500 | AU100: 川内① | AV100: 川内② | AW100: 川内500 | AX100: 都城① | AY100: 都城② | AZ100: 鹿屋① | BA100: 鹿屋② | BB100: 鹿屋500 | BC100: 菊陽② | BD100: 合志 | BE100: 合志 | BF100: 南熊本 | BG100: 下通 | BH100: 今宿 | BI100: 今宿➁ | BJ100: 八代 | BK100: 佐世保 | BL100: 大村 | BM100: 行橋 | BN100: 延岡① | BO100: 延岡② | BP100: Dプラ | BQ100: 光吉
A101: 設置台数 | B101: 57 | C101: 500GACHA | D101: 1000GACHA | E101: ティアラ | F101: ティアラ | G101: ティアラ | H101: ティアラ | I101: 1000GACHA | L101: 1000GACHA | M101: ティアラ | N101: 1000GACHA | O101: デカプセル | P101: ティアラ | Q101: ティアラ | R101: ティアラ | S101: ティアラ | T101: 1000GACHA | U101: ガチャコロ1 | V101: 500GATCHA | W101: 500GATCHA | X101: ティアラ | Y101: 1000GACHA | Z101: ガチャコロ2 | AB101: 1000GACHA | AC101: ティアラ | AD101: 1000GACHA | AE101: 1000GACHA | AH101: ガチャコロ２ | AI101: 1000GACHA | AJ101: ガチャコロ２ | AL101: 1000GACHA | AN101: ガチャコロ2 | AO101: 1000GACHA | AP101: 1000GACHA | AR101: 1000GACHA | AS101: ティアラ | AT101: 500GATCHA | AU101: 1000GACHA | AV101: ティアラ | AW101: 500GATCHA | AX101: ティアラ | AY101: 1000GACHA | AZ101: 1000GACHA | BA101: 1000GACHA | BB101: 500GATCHA | BC101: ガチャコロ２ | BD101: ガチャコロ２ | BE101: 500GACHA | BF101: ティアラ | BG101: ガチャコロ２ | BH101: 1000GACHA | BI101: ガチャコロ2 | BJ101: 1000GACHA | BK101: ティアラ | BL101: ガチャコロ２ | BM101: ガチャコロ2 | BN101: 1000GACHA | BO101: 1000GACHA | BQ101: ティアラ
A102: ロッカー台数 | B102: =SUM(C102:BQ102) -> 148 | C102: 2 | D102: 2 | E102: 3 | F102: 3 | G102: 3 | H102: 3 | I102: 2 | L102: 2 | M102: 2 | N102: 2 | O102: 4 | P102: 3 | Q102: 2 | R102: 2 | S102: 2 | T102: 2 | U102: 3 | V102: 2 | W102: 0 | X102: 6 | Y102: 2 | Z102: 4 | AB102: 2 | AC102: 2 | AD102: 2 | AE102: 2 | AH102: 4 | AI102: 2 | AJ102: 4 | AL102: 3 | AN102: 2 | AO102: 1 | AP102: 1 | AR102: 3 | AS102: 3 | AT102: 2 | AU102: 3 | AV102: 3 | AW102: 2 | AX102: 2 | AY102: 2 | AZ102: 3 | BA102: 3 | BB102: 2 | BC102: 4 | BD102: 4 | BE102: 3 | BF102: 2 | BG102: 3 | BH102: 2 | BI102: 4 | BJ102: 3 | BK102: 2 | BL102: 2 | BM102: 4 | BN102: 2 | BO102: 2 | BQ102: 2 | BR102: =SUM(C102:BQ102) -> 148 | BS102: ロッカー
A103: カプセル容量 | C103: 300 | D103: 300 | E103: 300 | F103: 300 | G103: 300 | H103: 300 | I103: 300 | L103: 300 | M103: 300 | N103: 300 | O103: 300 | P103: 300 | Q103: 300 | R103: 300 | S103: 300 | T103: 300 | U103: 400 | V103: 150 | W103: 150 | X103: 150 | Y103: 300 | Z103: 400 | AB103: 300 | AC103: 300 | AD103: 300 | AE103: 300 | AH103: 400 | AI103: 300 | AJ103: 400 | AL103: 300 | AN103: 400 | AO103: 300 | AP103: 300 | AR103: 300 | AS103: 300 | AT103: 300 | AU103: 300 | AV103: 300 | AW103: 300 | AX103: 300 | AY103: 300 | AZ103: 300 | BA103: 300 | BB103: 300 | BC103: 400 | BD103: 400 | BE103: 300 | BF103: 300 | BG103: 400 | BH103: 300 | BI103: 400 | BJ103: 300 | BK103: 300 | BL103: 400 | BM103: 400 | BN103: 300 | BO103: 300 | BQ103: 300
A104: ガチャの種類 | C104: バラエティー | D104: バラエティー | E104: スニーカー | F104: ゲームソフト | G104: ブランド | H104: ゲーム機 | I104: バラエティー | L104: バラエティー | M104: バラエティー | N104: バラエティー | O104: バラエティー | P104: スニーカー | Q104: バラエティー | R104: バラエティー | S104: バラエティー | T104: バラエティー | U104: バラエティー | V104: バラエティー | W104: バラエティー | X104: バラエティー | Y104: ポケモン | Z104: バラエティー | AB104: バラエティー | AC104: バラエティー | AD104: バラエティー | AE104: バラエティー(ポケモン） | AH104: バラエティー | AI104: バラエティー | AJ104: バラエティー | AL104: バラエティー | AN104: バラエティー | AO104: バラエティー | AP104: バラエティー | AR104: バラエティー | AS104: バラエティー | AT104: ポケモン | AU104: バラエティー | AV104: バラエティー | AW104: ポケモン | AX104: バラエティー | AY104: バラエティー | AZ104: バラエティー | BA104: バラエティー | BB104: バラエティー | BC104: バラエティー | BD104: バラエティー | BE104: バラエティー | BF104: バラエティー | BG104: バラエティー | BH104: バラエティー | BI104: バラエティー | BJ104: バラエティー | BK104: バラエティー | BL104: バラエティー | BM104: バラエティー | BN104: バラエティー | BO104: バラエティー | BQ104: バラエティー | BR104: ティアラ | BS104: 26
A105: プレイ料金 | C105: 500 | D105: 2000 | E105: 2000 | F105: 1000 | G105: 2000 | H105: 2000 | I105: 2000 | L105: 1000 | M105: 2000 | N105: 1000 | O105: 2000 | P105: 2000 | Q105: 1000 | R105: 2000 | S105: 2000 | T105: 1000 | U105: 2000 | V105: 500 | W105: 500 | X105: 2000 | Y105: 1000 | Z105: 2000 | AB105: 1000 | AC105: 1000 | AD105: 2000 | AE105: 2000 | AH105: 1000＆2000 | AI105: 1000 | AJ105: 1000＆2000 | AL105: 1000 | AN105: 2000 | AO105: 2000 | AP105: 2000 | AR105: 1000 | AS105: 2000 | AT105: 500 | AU105: 1000 | AV105: 2000 | AW105: 500 | AX105: 1000 | AY105: 2000 | AZ105: 1000 | BA105: 2000 | BB105: 500 | BC105: 2000 | BD105: 2000 | BE105: 500 | BF105: 1000 | BG105: 1000＆2000 | BH105: 1000 | BI105: 2000 | BJ105: 2000 | BK105: 1000 | BL105: 1000＆2000 | BM105: 1000＆2000 | BN105: 1000 | BO105: 2000 | BQ105: 2000 | BR105: ガチャコロ1 | BS105: 2
A106: 前年度 | B106: =SUM(C106:BQ106) -> 7500900 | C106: 160000 | D106: 278000 | E106: 92000 | F106: 124000 | G106: 108000 | H106: 134000 | I106: 302000 | K106: 153000 | N106: 127000 | O106: 156000 | Q106: 156000 | S106: 222000 | T106: 117000 | U106: 226000 | V106: 37600 | W106: 66000 | X106: 112000 | Y106: 135000 | Z106: 216000 | AB106: 76000 | AC106: 98000 | AH106: 275000 | AI106: 99000 | AJ106: 143000 | AL106: 63000 | AN106: 320000 | AP106: 160000 | AR106: 214000 | AS106: 100000 | AT106: 81600 | AU106: 145000 | AV106: 276000 | AW106: 101200 | AX106: 108000 | AY106: 82000 | BC106: 419000 | BD106: 267000 | BE106: 136500 | BG106: 435000 | BH106: 38000 | BI106: 130000 | BJ106: 234000 | BK106: 50000 | BL106: 137000 | BM106: 189000 | BN106: 84000 | BO106: 82000 | BQ106: 36000 | BR106: ガチャコロ2 | BS106: 10
A107: 目標 | B107: =SUM(C107:BQ107) -> 8125050 | C107: =(C92+C106)/2 -> 126000 | D107: =(D92+D106)/2 -> 188000 | E107: =(E92+E106)/2 -> 108000 | F107: =(F92+F106)/2 -> 100000 | G107: 100000 | H107: =(H92+H106)/2 -> 112000 | I107: =(I92+I106)/2 -> 300000 | L107: 100000 | M107: 100000 | N107: =(N92+N106)/2 -> 119000 | O107: =(O92+O106)/2 -> 139000 | P107: 100000 | Q107: =(Q92+Q106)/2 -> 153000 | R107: 100000 | S107: =(S92+S106)/2 -> 200000 | T107: 200000 | U107: =(U92+U106)/2 -> 254000 | V107: 50000 | W107: 50000 | X107: 100000 | Y107: 100000 | Z107: =(Z92+Z106)/2 -> 188500 | AA107: =(AA92+AA106)/2 -> 0 | AB107: =(AB92+AB106)/2 -> 118000 | AC107: 100000 | AD107: 100000 | AE107: 100000 | AF107: =(AF92+AF106)/2 -> 0 | AG107: =(AG92+AG106)/2 -> 0 | AH107: 280000 | AI107: 100000 | AJ107: 220000 | AK107: =(AK92+AK106)/2 -> 0 | AL107: 100000 | AN107: =(AN92+AN106)/2 -> 281000 | AO107: 400000 | AP107: 150000 | AQ107: =(AQ92+AQ106)/2 -> 0 | AR107: =(AR92+AR106)/2 -> 131000 | AS107: =(AS92+AS106)/2 -> 147000 | AT107: =(AT92+AT106)/2 -> 78200 | AU107: =(AU92+AU106)/2 -> 141000 | AV107: =(AV92+AV106)/2 -> 196000 | AW107: =(AW92+AW106)/2 -> 88950 | AX107: =(AX92+AX106)/2 -> 115500 | ... BG107: =(BG92+BG106)/2 -> 374500 | BH107: 100000 | BI107: =(BI92+BI106)/2 -> 133500 | BJ107: =(BJ92+BJ106)/2 -> 148000 | BK107: 100000 | BL107: =(BL92+BL106)/2 -> 111500 | BM107: =(BM92+BM106)/2 -> 177500 | BN107: =(BN92+BN106)/2 -> 54000 | BO107: =(BO92+BO106)/2 -> 88000 | BP107: =(BP92+BP106)/2 -> 0 | BQ107: 50000 | BR107: 1000GACHA | BS107: 15
...

Sheet 福重
B1: ５００円 | M1: ２０００円 | X1: 1000円ソフト | AD1: 2000円ブランド | AJ1: 2000円ゲーム | AP1: 2000円スニーカー
B2: 日付 | D2: 今回ﾒｰﾀｰ | E2: ﾒｰﾀｰ差 | F2: 売上 | K2: 備考 | M2: 日付 | O2: 今回ﾒｰﾀｰ | P2: ﾒｰﾀｰ差 | Q2: 売上 | V2: 備考 | X2: 日付 | Y2: 今回ﾒｰﾀｰ | Z2: ﾒｰﾀｰ差 | AA2: 売上 | AB2: 備考 | AD2: 日付 | AE2: 今回ﾒｰﾀｰ | AF2: ﾒｰﾀｰ差 | AG2: 売上 | AH2: 備考 | AJ2: 日付 | AK2: 今回ﾒｰﾀｰ | AL2: ﾒｰﾀｰ差 | AM2: 売上 | AN2: 備考 | AP2: 日付 | AR2: 今回ﾒｰﾀｰ | AS2: ﾒｰﾀｰ差 | AT2: 売上 | AY2: 備考
B3: 45919 | C3: 56000 | D3: 13942 | E3: 10 | F3: 1000 | K3: 上段リセット済み | M3: 45919 | O3: 2302 | P3: 8 | Q3: 8000 | X3: 45919 | Y3: 7137 | Z3: 8 | AA3: 8000 | AD3: 45919 | AE3: 4731 | AF3: 6 | AG3: 6000 | AJ3: 45919 | AK3: 6927 | AL3: 10 | AM3: 10000 | AP3: 45919 | AR3: 8311 | AS3: 14 | AT3: 14000
D4: 4602 | E4: 90 | F4: 9000
B5: 45922 | C5: =SUM(IF(F5="",0,F5), IF(F6="",0,F6), IF(Q5="",0,Q5), IF(AT5="",0,AT5), IF(AA5="",0,AA5), IF(AG5="",0,AG5), IF(AM5="",0,AM5)) -> 93500 | D5: 14107 | E5: =IF(D5="","",D5-D3) -> 165 | F5: =IF(D5="","",E5*100) -> 16500 | M5: =IF(B5="","",B5) -> 45922 | O5: 2320 | P5: =IF(O5="","",O5-O3) -> 18 | Q5: =IF(O5="","",P5*1000) -> 18000 | X5: =IF(AP5="","",AP5) -> 45922 | Y5: 7142 | Z5: =IF(Y5="","",Y5-Y3) -> 5 | AA5: =IF(Y5="","",Z5*1000) -> 5000 | AD5: =IF(AP5="","",AP5) -> 45922 | AE5: 4739 | AF5: =IF(AE5="","",AE5-AE3) -> 8 | AG5: =IF(AE5="","",AF5*1000) -> 8000 | AJ5: =IF(AD5="","",AD5) -> 45922 | AK5: 6959 | AL5: =IF(AK5="","",AK5-AK3) -> 32 | AM5: =IF(AK5="","",AL5*1000) -> 32000 | AP5: =IF(M5="","",M5) -> 45922 | AR5: 8319 | AS5: =IF(AR5="","",AR5-AR3) -> 8 | AT5: =IF(AR5="","",AS5*1000) -> 8000
D6: 4662 | E6: =IF(D6="","",D6-D4) -> 60 | F6: =IF(D6="","",E6*100) -> 6000 | P6: =IF(O6="","",O6-O4) | Z6: =IF(Y6="","",Y6-Y4) | AF6: =IF(AE6="","",AE6-AE4) | AL6: =IF(AK6="","",AK6-AK4) | AS6: =IF(AR6="","",AR6-AR4)
B7: 45926 | C7: =SUM(IF(F7="",0,F7), IF(F8="",0,F8), IF(Q7="",0,Q7), IF(AT7="",0,AT7), IF(AA7="",0,AA7), IF(AG7="",0,AG7), IF(AM7="",0,AM7)) -> 113500 | D7: 14387 | E7: =IF(D7="","",D7-D5) -> 280 | F7: =IF(D7="","",E7*100) -> 28000 | M7: =IF(B7="","",B7) -> 45926 | O7: 2336 | P7: =IF(O7="","",O7-O5) -> 16 | Q7: =IF(O7="","",P7*1000) -> 16000 | X7: =IF(AP7="","",AP7) -> 45926 | Y7: 7152 | Z7: =IF(Y7="","",Y7-Y5) -> 10 | AA7: =IF(Y7="","",Z7*1000) -> 10000 | AD7: =IF(X7="","",X7) -> 45926 | AE7: 4747 | AF7: =IF(AE7="","",AE7-AE5) -> 8 | AG7: =IF(AE7="","",AF7*1000) -> 8000 | AJ7: =IF(AD7="","",AD7) -> 45926 | AK7: 6981 | AL7: =IF(AK7="","",AK7-AK5) -> 22 | AM7: =IF(AK7="","",AL7*1000) -> 22000 | AP7: =IF(M7="","",M7) -> 45926 | AR7: 8327 | AS7: =IF(AR7="","",AR7-AR5) -> 8 | AT7: =IF(AR7="","",AS7*1000) -> 8000
D8: 4877 | E8: =IF(D8="","",D8-D6) -> 215 | F8: =IF(D8="","",E8*100) -> 21500 | K8: 下段電源落とした | M8: =IF(B8="","",B8) | P8: =IF(O8="","",O8-O7) | Q8: =IF(O8="","",P8*1000) | X8: =IF(AP8="","",AP8) | Z8: =IF(Y8="","",Y8-Y7) | AA8: =IF(Y8="","",Z8*1000) | AD8: =IF(X8="","",X8) | AF8: =IF(AE8="","",AE8-AE7) | AG8: =IF(AE8="","",AF8*1000) | AJ8: =IF(AD8="","",AD8) | AL8: =IF(AK8="","",AK8-AK7) | AM8: =IF(AK8="","",AL8*1000) | AP8: =IF(M8="","",M8) | AS8: =IF(AR8="","",AR8-AR7) | AT8: =IF(AR8="","",AS8*1000)
B9: 45930 | C9: =SUM(IF(F9="",0,F9), IF(F10="",0,F10), IF(Q9="",0,Q9), IF(AT9="",0,AT9), IF(AA9="",0,AA9), IF(AG9="",0,AG9), IF(AM9="",0,AM9)) -> 54000 | D9: 14427 | E9: =IF(D9="","",D9-D7) -> 40 | F9: =IF(D9="","",E9*100) -> 4000 | K9: 上段電源切られてた | M9: =IF(B9="","",B9) -> 45930 | O9: 2354 | P9: =IF(O9="","",O9-O7) -> 18 | Q9: =IF(O9="","",P9*1000) -> 18000 | X9: =IF(AP9="","",AP9) -> 45930 | Y9: 7158 | Z9: =IF(Y9="","",Y9-Y7) -> 6 | AA9: =IF(Y9="","",Z9*1000) -> 6000 | AD9: =IF(X9="","",X9) -> 45930 | AE9: 4757 | AF9: =IF(AE9="","",AE9-AE7) -> 10 | AG9: =IF(AE9="","",AF9*1000) -> 10000 | AJ9: =IF(AD9="","",AD9) -> 45930 | AK9: 6991 | AL9: =IF(AK9="","",AK9-AK7) -> 10 | AM9: =IF(AK9="","",AL9*1000) -> 10000 | AP9: =IF(M9="","",M9) -> 45930 | AR9: 8333 | AS9: =IF(AR9="","",AR9-AR7) -> 6 | AT9: =IF(AR9="","",AS9*1000) -> 6000
D10: 4877 | E10: =IF(D10="","",D10-D8) -> 0 | F10: =IF(D10="","",E10*100) -> 0 | K10: 下段リセット済み | M10: =IF(B10="","",B10) | P10: =IF(O10="","",O10-O9) | Q10: =IF(O10="","",P10*1000) | X10: =IF(AP10="","",AP10) | Z10: =IF(Y10="","",Y10-Y9) | AA10: =IF(Y10="","",Z10*1000) | AD10: =IF(X10="","",X10) | AF10: =IF(AE10="","",AE10-AE9) | AG10: =IF(AE10="","",AF10*1000) | AJ10: =IF(AD10="","",AD10) | AL10: =IF(AK10="","",AK10-AK9) | AM10: =IF(AK10="","",AL10*1000) | AP10: =IF(M10="","",M10) | AS10: =IF(AR10="","",AR10-AR9) | AT10: =IF(AR10="","",AS10*1000)
B11: 45933 | C11: =SUM(IF(F11="",0,F11), IF(F12="",0,F12), IF(Q11="",0,Q11), IF(AT11="",0,AT11), IF(AA11="",0,AA11), IF(AG11="",0,AG11), IF(AM11="",0,AM11)) -> 37000 | D11: 14507 | E11: =IF(D11="","",D11-D9) -> 80 | F11: =IF(D11="","",E11*100) -> 8000 | M11: =IF(B11="","",B11) -> 45933 | O11: 2364 | P11: =IF(O11="","",O11-O9) -> 10 | Q11: =IF(O11="","",P11*1000) -> 10000 | X11: =IF(AP11="","",AP11) -> 45933 | Y11: 7165 | Z11: =IF(Y11="","",Y11-Y9) -> 7 | AA11: =IF(Y11="","",Z11*1000) -> 7000 | AD11: =IF(X11="","",X11) -> 45933 | AE11: 4757 | AF11: =IF(AE11="","",AE11-AE9) -> 0 | AG11: =IF(AE11="","",AF11*1000) -> 0 | AJ11: =IF(AD11="","",AD11) -> 45933 | AK11: 7001 | AL11: =IF(AK11="","",AK11-AK9) -> 10 | AM11: =IF(AK11="","",AL11*1000) -> 10000 | AP11: =IF(M11="","",M11) -> 45933 | AR11: 8333 | AS11: =IF(AR11="","",AR11-AR9) -> 0 | AT11: =IF(AR11="","",AS11*1000) -> 0
D12: 4897 | E12: =IF(D12="","",D12-D10) -> 20 | F12: =IF(D12="","",E12*100) -> 2000 | M12: =IF(B12="","",B12) | P12: =IF(O12="","",O12-O11) | Q12: =IF(O12="","",P12*1000) | X12: =IF(AP12="","",AP12) | Z12: =IF(Y12="","",Y12-Y11) | AA12: =IF(Y12="","",Z12*1000) | AD12: =IF(X12="","",X12) | AF12: =IF(AE12="","",AE12-AE11) | AG12: =IF(AE12="","",AF12*1000) | AJ12: =IF(AD12="","",AD12) | AL12: =IF(AK12="","",AK12-AK11) | AM12: =IF(AK12="","",AL12*1000) | AP12: =IF(M12="","",M12) | AS12: =IF(AR12="","",AR12-AR11) | AT12: =IF(AR12="","",AS12*1000)
B13: 45935 | C13: =SUM(IF(F13="",0,F13), IF(F14="",0,F14), IF(Q13="",0,Q13), IF(AT13="",0,AT13), IF(AA13="",0,AA13), IF(AG13="",0,AG13), IF(AM13="",0,AM13)) -> 54500 | D13: 14617 | E13: =IF(D13="","",D13-D11) -> 110 | F13: =IF(D13="","",E13*100) -> 11000 | M13: =IF(B13="","",B13) -> 45935 | O13: 2368 | P13: =IF(O13="","",O13-O11) -> 4 | Q13: =IF(O13="","",P13*1000) -> 4000 | X13: =IF(AP13="","",AP13) -> 45935 | Y13: 7183 | Z13: =IF(Y13="","",Y13-Y11) -> 18 | AA13: =IF(Y13="","",Z13*1000) -> 18000 | AD13: =IF(X13="","",X13) -> 45935 | AE13: 4765 | AF13: =IF(AE13="","",AE13-AE11) -> 8 | AG13: =IF(AE13="","",AF13*1000) -> 8000 | AJ13: =IF(AD13="","",AD13) -> 45935 | AK13: 7007 | AL13: =IF(AK13="","",AK13-AK11) -> 6 | AM13: =IF(AK13="","",AL13*1000) -> 6000 | AP13: =IF(M13="","",M13) -> 45935 | AR13: 8337 | AS13: =IF(AR13="","",AR13-AR11) -> 4 | AT13: =IF(AR13="","",AS13*1000) -> 4000
D14: 4932 | E14: =IF(D14="","",D14-D12) -> 35 | F14: =IF(D14="","",E14*100) -> 3500 | M14: =IF(B14="","",B14) | P14: =IF(O14="","",O14-O13) | Q14: =IF(O14="","",P14*1000) | X14: =IF(AP14="","",AP14) | Z14: =IF(Y14="","",Y14-Y13) | AA14: =IF(Y14="","",Z14*1000) | AD14: =IF(X14="","",X14) | AF14: =IF(AE14="","",AE14-AE13) | AG14: =IF(AE14="","",AF14*1000) | AJ14: =IF(AD14="","",AD14) | AL14: =IF(AK14="","",AK14-AK13) | AM14: =IF(AK14="","",AL14*1000) | AP14: =IF(M14="","",M14) | AS14: =IF(AR14="","",AR14-AR13) | AT14: =IF(AR14="","",AS14*1000)
B15: 45940 | C15: =SUM(IF(F15="",0,F15), IF(F16="",0,F16), IF(Q15="",0,Q15), IF(AT15="",0,AT15), IF(AA15="",0,AA15), IF(AG15="",0,AG15), IF(AM15="",0,AM15)) -> 44100 | D15: 14733 | E15: =IF(D15="","",D15-D13) -> 116 | F15: =IF(D15="","",E15*100) -> 11600 | M15: =IF(B15="","",B15) -> 45940 | O15: 2382 | P15: =IF(O15="","",O15-O13) -> 14 | Q15: =IF(O15="","",P15*1000) -> 14000 | X15: =IF(AP15="","",AP15) -> 45940 | Y15: 7187 | Z15: =IF(Y15="","",Y15-Y13) -> 4 | AA15: =IF(Y15="","",Z15*1000) -> 4000 | AB15: 止まってた | AD15: =IF(X15="","",X15) -> 45940 | AE15: 4769 | AF15: =IF(AE15="","",AE15-AE13) -> 4 | AG15: =IF(AE15="","",AF15*1000) -> 4000 | AJ15: =IF(AD15="","",AD15) -> 45940 | AK15: 7013 | AL15: =IF(AK15="","",AK15-AK13) -> 6 | AM15: =IF(AK15="","",AL15*1000) -> 6000 | AP15: =IF(M15="","",M15) -> 45940 | AR15: 8339 | AS15: =IF(AR15="","",AR15-AR13) -> 2 | AT15: =IF(AR15="","",AS15*1000) -> 2000
D16: 4957 | E16: =IF(D16="","",D16-D14) -> 25 | F16: =IF(D16="","",E16*100) -> 2500 | M16: =IF(B16="","",B16) | P16: =IF(O16="","",O16-O14) | Q16: =IF(O16="","",P16*1000) | X16: =IF(AP16="","",AP16) | Z16: =IF(Y16="","",Y16-Y14) | AA16: =IF(Y16="","",Z16*1000) | AD16: =IF(X16="","",X16) | AF16: =IF(AE16="","",AE16-AE14) | AG16: =IF(AE16="","",AF16*1000) | AJ16: =IF(AD16="","",AD16) | AL16: =IF(AK16="","",AK16-AK14) | AM16: =IF(AK16="","",AL16*1000) | AP16: =IF(M16="","",M16) | AS16: =IF(AR16="","",AR16-AR14) | AT16: =IF(AR16="","",AS16*1000)
B17: 45946 | C17: =SUM(IF(F17="",0,F17), IF(F18="",0,F18), IF(Q17="",0,Q17), IF(AT17="",0,AT17), IF(AA17="",0,AA17), IF(AG17="",0,AG17), IF(AM17="",0,AM17)) -> 185500 | D17: 14958 | E17: =IF(D17="","",D17-D15) -> 225 | F17: =IF(D17="","",E17*100) -> 22500 | M17: =IF(B17="","",B17) -> 45946 | O17: 2414 | P17: =IF(O17="","",O17-O15) -> 32 | Q17: =IF(O17="","",P17*1000) -> 32000 | V17: 10/12リセット | X17: =IF(AP17="","",AP17) -> 45946 | Y17: 7237 | Z17: =IF(Y17="","",Y17-Y15) -> 50 | AA17: =IF(Y17="","",Z17*1000) -> 50000 | AB17: 10/12リセット | AD17: =IF(X17="","",X17) -> 45946 | AE17: 4819 | AF17: =IF(AE17="","",AE17-AE15) -> 50 | AG17: =IF(AE17="","",AF17*1000) -> 50000 | AH17: 10/12リセット | AJ17: =IF(AD17="","",AD17) -> 45946 | AK17: 7023 | AL17: =IF(AK17="","",AK17-AK15) -> 10 | AM17: =IF(AK17="","",AL17*1000) -> 10000 | AP17: =IF(M17="","",M17) -> 45946 | AR17: 8353 | AS17: =IF(AR17="","",AR17-AR15) -> 14 | AT17: =IF(AR17="","",AS17*1000) -> 14000
D18: 5027 | E18: =IF(D18="","",D18-D16) -> 70 | F18: =IF(D18="","",E18*100) -> 7000
C21: =SUM(IF(F21="",0,F21), IF(F22="",0,F22), IF(Q21="",0,Q21), IF(AT21="",0,AT21), IF(AA21="",0,AA21), IF(AG21="",0,AG21), IF(AM21="",0,AM21)) -> 0 | E21: =IF(D21="","",D21-D19) | F21: =IF(D21="","",E21*100) | M21: =IF(B21="","",B21) | P21: =IF(O21="","",O21-O19) | Q21: =IF(O21="","",P21*1000) | X21: =IF(AP21="","",AP21) | Z21: =IF(Y21="","",Y21-Y19) | AA21: =IF(Y21="","",Z21*1000) | AD21: =IF(X21="","",X21) | AF21: =IF(AE21="","",AE21-AE19) | AG21: =IF(AE21="","",AF21*1000) | AJ21: =IF(AD21="","",AD21) | AL21: =IF(AK21="","",AK21-AK19) | AM21: =IF(AK21="","",AL21*1000) | AP21: =IF(M21="","",M21) | AS21: =IF(AR21="","",AR21-AR19) | AT21: =IF(AR21="","",AS21*1000)
E22: =IF(D22="","",D22-D20) | F22: =IF(D22="","",E22*100) | P22: =IF(O22="","",O22-O20) | Z22: =IF(Y22="","",Y22-Y20) | AF22: =IF(AE22="","",AE22-AE20) | AL22: =IF(AK22="","",AK22-AK20) | AS22: =IF(AR22="","",AR22-AR20)
C23: =SUM(IF(F23="",0,F23), IF(F24="",0,F24), IF(Q23="",0,Q23), IF(AT23="",0,AT23), IF(AA23="",0,AA23), IF(AG23="",0,AG23), IF(AM23="",0,AM23)) -> 0 | E23: =IF(D23="","",D23-D21) | F23: =IF(D23="","",E23*100) | M23: =IF(B23="","",B23) | P23: =IF(O23="","",O23-O21) | Q23: =IF(O23="","",P23*1000) | X23: =IF(AP23="","",AP23) | Z23: =IF(Y23="","",Y23-Y21) | AA23: =IF(Y23="","",Z23*1000) | AD23: =IF(X23="","",X23) | AF23: =IF(AE23="","",AE23-AE21) | AG23: =IF(AE23="","",AF23*1000) | AJ23: =IF(AD23="","",AD23) | AL23: =IF(AK23="","",AK23-AK21) | AM23: =IF(AK23="","",AL23*1000) | AP23: =IF(M23="","",M23) | AS23: =IF(AR23="","",AR23-AR21) | AT23: =IF(AR23="","",AS23*1000)
E24: =IF(D24="","",D24-D22) | F24: =IF(D24="","",E24*100)
C25: =SUM(IF(F25="",0,F25), IF(F26="",0,F26), IF(Q25="",0,Q25), IF(AT25="",0,AT25), IF(AA25="",0,AA25), IF(AG25="",0,AG25), IF(AM25="",0,AM25)) -> 0 | E25: =IF(D25="","",D25-D23) | F25: =IF(D25="","",E25*100) | M25: =IF(B25="","",B25) | P25: =IF(O25="","",O25-O23) | Q25: =IF(O25="","",P25*1000) | X25: =IF(AP25="","",AP25) | Z25: =IF(Y25="","",Y25-Y23) | AA25: =IF(Y25="","",Z25*1000) | AD25: =IF(X25="","",X25) | AF25: =IF(AE25="","",AE25-AE23) | AG25: =IF(AE25="","",AF25*1000) | AJ25: =IF(AD25="","",AD25) | AL25: =IF(AK25="","",AK25-AK23) | AM25: =IF(AK25="","",AL25*1000) | AP25: =IF(M25="","",M25) | AS25: =IF(AR25="","",AR25-AR23) | AT25: =IF(AR25="","",AS25*1000)
E26: =IF(D26="","",D26-D24) | F26: =IF(D26="","",E26*100) | M26: =IF(B26="","",B26)
C27: =SUM(IF(F27="",0,F27), IF(F28="",0,F28), IF(Q27="",0,Q27), IF(AT27="",0,AT27), IF(AA27="",0,AA27), IF(AG27="",0,AG27), IF(AM27="",0,AM27)) -> 0 | E27: =IF(D27="","",D27-D25) | F27: =IF(D27="","",E27*100) | M27: =IF(B27="","",B27) | P27: =IF(O27="","",O27-O25) | Q27: =IF(O27="","",P27*1000) | Z27: =IF(Y27="","",Y27-Y25) | AA27: =IF(Y27="","",Z27*1000) | AD27: =IF(X27="","",X27) | AF27: =IF(AE27="","",AE27-AE25) | AG27: =IF(AE27="","",AF27*1000) | AJ27: =IF(AD27="","",AD27) | AL27: =IF(AK27="","",AK27-AK25) | AM27: =IF(AK27="","",AL27*1000) | AP27: =IF(M27="","",M27) | AS27: =IF(AR27="","",AR27-AR25) | AT27: =IF(AR27="","",AS27*1000)
E28: =IF(D28="","",D28-D26) | F28: =IF(D28="","",E28*100)
C29: =SUM(IF(F29="",0,F29), IF(F30="",0,F30), IF(Q29="",0,Q29), IF(AT29="",0,AT29), IF(AA29="",0,AA29), IF(AG29="",0,AG29), IF(AM29="",0,AM29)) -> 0 | E29: =IF(D29="","",D29-D27) | F29: =IF(D29="","",E29*100) | M29: =IF(B29="","",B29) | P29: =IF(O29="","",O29-O27) | Q29: =IF(O29="","",P29*1000) | X29: =IF(AP29="","",AP29) | Z29: =IF(Y29="","",Y29-Y27) | AA29: =IF(Y29="","",Z29*1000) | AD29: =IF(X29="","",X29) | AF29: =IF(AE29="","",AE29-AE27) | AG29: =IF(AE29="","",AF29*1000) | AJ29: =IF(AD29="","",AD29) | AL29: =IF(AK29="","",AK29-AK27) | AM29: =IF(AK29="","",AL29*1000) | AP29: =IF(M29="","",M29) | AS29: =IF(AR29="","",AR29-AR27) | AT29: =IF(AR29="","",AS29*1000)
E30: =IF(D30="","",D30-D28) | F30: =IF(D30="","",E30*100)
C31: =SUM(IF(F31="",0,F31), IF(F32="",0,F32), IF(Q31="",0,Q31), IF(AT31="",0,AT31), IF(AA31="",0,AA31), IF(AG31="",0,AG31), IF(AM31="",0,AM31)) -> 0 | E31: =IF(D31="","",D31-D29) | F31: =IF(D31="","",E31*100) | M31: =IF(B31="","",B31) | P31: =IF(O31="","",O31-O29) | Q31: =IF(O31="","",P31*1000) | X31: =IF(AP31="","",AP31) | Z31: =IF(Y31="","",Y31-Y29) | AA31: =IF(Y31="","",Z31*1000) | AD31: =IF(X31="","",X31) | AF31: =IF(AE31="","",AE31-AE29) | AG31: =IF(AE31="","",AF31*1000) | AJ31: =IF(AD31="","",AD31) | AL31: =IF(AK31="","",AK31-AK29) | AM31: =IF(AK31="","",AL31*1000) | AP31: =IF(M31="","",M31) | AS31: =IF(AR31="","",AR31-AR29) | AT31: =IF(AR31="","",AS31*1000)
E32: =IF(D32="","",D32-D30) | F32: =IF(D32="","",E32*100)
C33: =SUM(IF(F33="",0,F33), IF(F34="",0,F34), IF(Q33="",0,Q33), IF(AT33="",0,AT33), IF(AA33="",0,AA33), IF(AG33="",0,AG33), IF(AM33="",0,AM33)) -> 0 | E33: =IF(D33="","",D33-D31) | F33: =IF(D33="","",E33*100) | M33: =IF(B33="","",B33) | P33: =IF(O33="","",O33-O31) | Q33: =IF(O33="","",P33*1000) | X33: =IF(AP33="","",AP33) | Z33: =IF(Y33="","",Y33-Y31) | AA33: =IF(Y33="","",Z33*1000) | AD33: =IF(X33="","",X33) | AF33: =IF(AE33="","",AE33-AE31) | AG33: =IF(AE33="","",AF33*1000) | AJ33: =IF(AD33="","",AD33) | AL33: =IF(AK33="","",AK33-AK31) | AM33: =IF(AK33="","",AL33*1000) | AP33: =IF(M33="","",M33) | AS33: =IF(AR33="","",AR33-AR31) | AT33: =IF(AR33="","",AS33*1000)
E34: =IF(D34="","",D34-D32) | F34: =IF(D34="","",E34*100)
C35: =SUM(IF(F35="",0,F35), IF(F36="",0,F36), IF(Q35="",0,Q35), IF(AT35="",0,AT35), IF(AA35="",0,AA35), IF(AG35="",0,AG35), IF(AM35="",0,AM35)) -> 0 | E35: =IF(D35="","",D35-D33) | F35: =IF(D35="","",E35*100) | M35: =IF(B35="","",B35) | P35: =IF(O35="","",O35-O33) | Q35: =IF(O35="","",P35*1000) | X35: =IF(AP35="","",AP35) | Z35: =IF(Y35="","",Y35-Y33) | AA35: =IF(Y35="","",Z35*1000) | AD35: =IF(X35="","",X35) | AF35: =IF(AE35="","",AE35-AE33) | AG35: =IF(AE35="","",AF35*1000) | AJ35: =IF(AD35="","",AD35) | AL35: =IF(AK35="","",AK35-AK33) | AM35: =IF(AK35="","",AL35*1000) | AP35: =IF(M35="","",M35) | AS35: =IF(AR35="","",AR35-AR33) | AT35: =IF(AR35="","",AS35*1000)
E36: =IF(D36="","",D36-D34) | F36: =IF(D36="","",E36*100)
B37: =DATEDIF(#REF!,B$17,"d") -> #REF! | E37: =IF(D37="","",D37-D29) | F37: =IF(D37="","",E37*100) | M37: =IF(B37="","",B37) -> #REF! | P37: =IF(O37="","",O37-O29) | Q37: =IF(O37="","",P37*1000) | X37: =IF(AP37="","",AP37) -> #REF! | Z37: =IF(Y37="","",Y37-Y29) | AA37: =IF(Y37="","",Z37*1000) | AD37: =IF(X37="","",X37) -> #REF! | AF37: =IF(AE37="","",AE37-AE29) | AG37: =IF(AE37="","",AF37*1000) | AJ37: =IF(AD37="","",AD37) -> #REF! | AL37: =IF(AK37="","",AK37-AK29) | AM37: =IF(AK37="","",AL37*1000) | AP37: =IF(M37="","",M37) -> #REF! | AS37: =IF(AR37="","",AR37-AR29) | AT37: =IF(AR37="","",AS37*1000)
E38: =IF(D38="","",D38-D34) | F38: =IF(D38="","",E38*100)
B39: =SUM(E3, E5, E7, E9, E11, E13, E15, E17, E19, E21, E23, E25, E39,E27,E29,E31,E33,E35,E37) -> 1026 | E39: =IF(D39="","",D39-D37) | F39: =IF(D39="","",E39*100) | M39: =SUM(P3, P5, P7, P9, P11, P13, P15, P17, P19, P21, P29, P37, P39) -> 120 | P39: =IF(O39="","",O39-O37) | Q39: =IF(O39="","",P39*1000) | X39: =SUM(Z3, Z5, Z7, Z9, Z11, Z13, Z15, Z17, Z19, Z21, Z29, Z37, Z39) -> 108 | Z39: =IF(Y39="","",Y39-Y37) | AA39: =IF(Y39="","",Z39*1000) | AD39: =SUM(AF3, AF5, AF7, AF9, AF11, AF13, AF15, AF17, AF19, AF21, AF29, AF37, AF39) -> 94 | AF39: =IF(AE39="","",AE39-AE37) | AG39: =IF(AE39="","",AF39*1000) | AJ39: =SUM(AL3, AL5, AL7, AL9, AL11, AL13, AL15, AL17, AL19, AL21, AL29, AL37, AL39) -> 106 | AL39: =IF(AK39="","",AK39-AK37) | AM39: =IF(AK39="","",AL39*1000) | AP39: =SUM(AS3, AS5, AS7, AS9, AS11, AS13, AS15, AS17, AS19, AS21, AS29, AS37, AS39) -> 56 | AS39: =IF(AR39="","",AR39-AR37) | AT39: =IF(AR39="","",AS39*1000)
B40: =SUM(E4, E6, E8, E10, E12, E14, E16, E18, E20, E22, E24, E26, E40,E28,E30,E32,E34,E36,E38) -> 515 | E40: =IF(D40="","",D40-D38) | F40: =IF(D40="","",E40*100) | M40: =SUM(P4, P6, P8, P10, P12, P14, P16, P18, P20, P22, P34, P38, P40) -> 0 | X40: =SUM(Z4, Z6, Z8, Z10, Z12, Z14, Z16, Z18, Z20, Z22, Z34, Z38, Z40) -> 0 | AD40: =SUM(AF4, AF6, AF8, AF10, AF12, AF14, AF16, AF18, AF20, AF22, AF34, AF38, AF40) -> 0 | AJ40: =SUM(AL4, AL6, AL8, AL10, AL12, AL14, AL16, AL18, AL20, AL22, AL34, AL38, AL40) -> 0 | AP40: =SUM(AS4, AS6, AS8, AS10, AS12, AS14, AS16, AS18, AS20, AS22, AS34, AS38, AS40) -> 0
C41: =SUM(C3:C34) -> 638100 | E41: =SUM(E3:E40) -> 1541 | F41: =SUM(F3:F40) -> 154100 | G41: =SUM(G3:G14) -> 0 | H41: =SUM(H3:H14) -> 0 | I41: =SUM(I3:I14) -> 0 | J41: =SUM(J3:J14) -> 0 | P41: =SUM(P3:P39) -> 120 | Q41: =SUM(Q3:Q40) -> 120000 | R41: =SUM(R3:R14) -> 0 | S41: =SUM(S3:S14) -> 0 | T41: =SUM(T3:T14) -> 0 | U41: =SUM(U3:U14) -> 0 | Z41: =SUM(Z3:Z39) -> 108 | AA41: =SUM(AA3:AA40) -> 108000 | AF41: =SUM(AF3:AF39) -> 94 | AG41: =SUM(AG3:AG40) -> 94000 | AL41: =SUM(AL3:AL39) -> 106 | AM41: =SUM(AM3:AM40) -> 106000 | AS41: =SUM(AS3:AS39) -> 56 | AT41: =SUM(AT3:AT40) -> 56000 | AU41: =SUM(AU3:AU14) -> 0 | AV41: =SUM(AV3:AV14) -> 0 | AW41: =SUM(AW3:AW14) -> 0 | AX41: =SUM(AX3:AX14) -> 0
B42: 今月の日数 | C42: 全台日売AVE | D42: 売上予想合計 | E42: AVE | F42: 売上予想 | P42: AVE | Q42: 売上予想 | Z42: AVE | AA42: 売上予想 | AF42: AVE | AG42: 売上予想 | AL42: AVE | AM42: 売上予想 | AS42: AVE | AT42: 売上予想
B43: 30 | C43: =C41/B37 -> #REF! | D43: =C43*B43 -> #REF! | E43: =E41/B37*100 -> #REF! | F43: =E43*B43 -> #REF! | P43: =P41/M37*1000 -> #REF! | Q43: =P43*B43 -> #REF! | Z43: =Z41/X37*1000 -> #REF! | AA43: =Z43*B43 -> #REF! | AF43: =AF41/AD37*1000 -> #REF! | AG43: =AF43*B43 -> #REF! | AL43: =AL41/AJ37*1000 -> #REF! | AM43: =AL43*B43 -> #REF! | AS43: =AS41/AP37*1000 -> #REF! | AT43: =AS43*B43 -> #REF!
B45: ５００円 | M45: ２０００円 | X45: 1000円ソフト | AD45: 2000円ブランド | AJ45: 2000円ゲーム | AP45: 2000円スニーカー
B46: 日付 | D46: 今回ﾒｰﾀｰ | E46: ﾒｰﾀｰ差 | F46: 売上 | K46: 備考 | M46: 日付 | O46: 今回ﾒｰﾀｰ | P46: ﾒｰﾀｰ差 | Q46: 売上 | V46: 備考 | X46: 日付 | Y46: 今回ﾒｰﾀｰ | Z46: ﾒｰﾀｰ差 | AA46: 売上 | AB46: 備考 | AD46: 日付 | AE46: 今回ﾒｰﾀｰ | AF46: ﾒｰﾀｰ差 | AG46: 売上 | AH46: 備考 | AJ46: 日付 | AK46: 今回ﾒｰﾀｰ | AL46: ﾒｰﾀｰ差 | AM46: 売上 | AN46: 備考 | AP46: 日付 | AR46: 今回ﾒｰﾀｰ | AS46: ﾒｰﾀｰ差 | AT46: 売上 | AY46: 備考
B47: 45950 | C47: 138500 | D47: 15128 | E47: 170 | F47: 17000 | K47: リセット | M47: 45950 | O47: 2432 | P47: 18 | Q47: 18000 | X47: 45950 | Y47: 7256 | Z47: 19 | AA47: 19000 | AD47: 45950 | AE47: 4877 | AF47: 58 | AG47: 58000 | AJ47: 45950 | AK47: 7035 | AL47: 12 | AM47: 12000 | AP47: 45950 | AR47: 8363 | AS47: 10 | AT47: 10000 | AY47: リセット
D48: 5072 | E48: 45 | F48: 4500
B49: 45957 | C49: =SUM(IF(F49="",0,F49), IF(F50="",0,F50), IF(Q49="",0,Q49), IF(AT49="",0,AT49), IF(AA49="",0,AA49), IF(AG49="",0,AG49), IF(AM49="",0,AM49)) -> 216500 | D49: 15473 | E49: =IF(D49="","",D49-D47) -> 345 | F49: =IF(D49="","",E49*100) -> 34500 | M49: =IF(B49="","",B49) -> 45957 | O49: 2488 | P49: =IF(O49="","",O49-O47) -> 56 | Q49: =IF(O49="","",P49*1000) -> 56000 | X49: =IF(AP49="","",AP49) -> 45957 | Y49: 7289 | Z49: =IF(Y49="","",Y49-Y47) -> 33 | AA49: =IF(Y49="","",Z49*1000) -> 33000 | AD49: =IF(AP49="","",AP49) -> 45957 | AE49: 4907 | AF49: =IF(AE49="","",AE49-AE47) -> 30 | AG49: =IF(AE49="","",AF49*1000) -> 30000 | AJ49: =IF(AD49="","",AD49) -> 45957 | AK49: 7069 | AL49: =IF(AK49="","",AK49-AK47) -> 34 | AM49: =IF(AK49="","",AL49*1000) -> 34000 | AP49: =IF(M49="","",M49) -> 45957 | AR49: 8383 | AS49: =IF(AR49="","",AR49-AR47) -> 20 | AT49: =IF(AR49="","",AS49*1000) -> 20000
D50: 5162 | E50: =IF(D50="","",D50-D48) -> 90 | F50: =IF(D50="","",E50*100) -> 9000 | P50: =IF(O50="","",O50-O48) | Z50: =IF(Y50="","",Y50-Y48) | AF50: =IF(AE50="","",AE50-AE48) | AL50: =IF(AK50="","",AK50-AK48) | AS50: =IF(AR50="","",AR50-AR48)
B51: 45961 | C51: =SUM(IF(F51="",0,F51), IF(F52="",0,F52), IF(Q51="",0,Q51), IF(AT51="",0,AT51), IF(AA51="",0,AA51), IF(AG51="",0,AG51), IF(AM51="",0,AM51)) -> 120000 | D51: 15848 | E51: =IF(D51="","",D51-D49) -> 375 | F51: =IF(D51="","",E51*100) -> 37500 | M51: =IF(B51="","",B51) -> 45961 | O51: 2515 | P51: =IF(O51="","",O51-O49) -> 27 | Q51: =IF(O51="","",P51*1000) -> 27000 | X51: =IF(AP51="","",AP51) -> 45961 | Y51: 7297 | Z51: =IF(Y51="","",Y51-Y49) -> 8 | AA51: =IF(Y51="","",Z51*1000) -> 8000 | AD51: =IF(X51="","",X51) -> 45961 | AE51: 4911 | AF51: =IF(AE51="","",AE51-AE49) -> 4 | AG51: =IF(AE51="","",AF51*1000) -> 4000 | AJ51: =IF(AD51="","",AD51) -> 45961 | AK51: 7091 | AL51: =IF(AK51="","",AK51-AK49) -> 22 | AM51: =IF(AK51="","",AL51*1000) -> 22000 | AP51: =IF(M51="","",M51) -> 45961 | AR51: 8395 | AS51: =IF(AR51="","",AR51-AR49) -> 12 | AT51: =IF(AR51="","",AS51*1000) -> 12000
D52: 5257 | E52: =IF(D52="","",D52-D50) -> 95 | F52: =IF(D52="","",E52*100) -> 9500 | M52: =IF(B52="","",B52) | P52: =IF(O52="","",O52-O51) | Q52: =IF(O52="","",P52*1000) | X52: =IF(AP52="","",AP52) | Z52: =IF(Y52="","",Y52-Y51) | AA52: =IF(Y52="","",Z52*1000) | AD52: =IF(X52="","",X52) | AF52: =IF(AE52="","",AE52-AE51) | AG52: =IF(AE52="","",AF52*1000) | AJ52: =IF(AD52="","",AD52) | AL52: =IF(AK52="","",AK52-AK51) | AM52: =IF(AK52="","",AL52*1000) | AP52: =IF(M52="","",M52) | AS52: =IF(AR52="","",AR52-AR51) | AT52: =IF(AR52="","",AS52*1000)
B53: 45963 | C53: =SUM(IF(F53="",0,F53), IF(F54="",0,F54), IF(Q53="",0,Q53), IF(AT53="",0,AT53), IF(AA53="",0,AA53), IF(AG53="",0,AG53), IF(AM53="",0,AM53)) -> 76500 | D53: 15848 | E53: =IF(D53="","",D53-D51) -> 0 | F53: =IF(D53="","",E53*100) -> 0 | K53: リセット待ち | M53: =IF(B53="","",B53) -> 45963 | O53: 2529 | P53: =IF(O53="","",O53-O51) -> 14 | Q53: =IF(O53="","",P53*1000) -> 14000 | X53: =IF(AP53="","",AP53) -> 45963 | Y53: 7317 | Z53: =IF(Y53="","",Y53-Y51) -> 20 | AA53: =IF(Y53="","",Z53*1000) -> 20000 | AD53: =IF(X53="","",X53) -> 45963 | AE53: 4927 | AF53: =IF(AE53="","",AE53-AE51) -> 16 | AG53: =IF(AE53="","",AF53*1000) -> 16000 | AJ53: =IF(AD53="","",AD53) -> 45963 | AK53: 7095 | AL53: =IF(AK53="","",AK53-AK51) -> 4 | AM53: =IF(AK53="","",AL53*1000) -> 4000 | AN53: 軽くリセット | AP53: =IF(M53="","",M53) -> 45963 | AR53: 8403 | AS53: =IF(AR53="","",AR53-AR51) -> 8 | AT53: =IF(AR53="","",AS53*1000) -> 8000
D54: 5402 | E54: =IF(D54="","",D54-D52) -> 145 | F54: =IF(D54="","",E54*100) -> 14500 | M54: =IF(B54="","",B54) | P54: =IF(O54="","",O54-O53) | Q54: =IF(O54="","",P54*1000) | X54: =IF(AP54="","",AP54) | Z54: =IF(Y54="","",Y54-Y53) | AA54: =IF(Y54="","",Z54*1000) | AD54: =IF(X54="","",X54) | AF54: =IF(AE54="","",AE54-AE53) | AG54: =IF(AE54="","",AF54*1000) | AJ54: =IF(AD54="","",AD54) | AL54: =IF(AK54="","",AK54-AK53) | AM54: =IF(AK54="","",AL54*1000) | AP54: =IF(M54="","",M54) | AS54: =IF(AR54="","",AR54-AR53) | AT54: =IF(AR54="","",AS54*1000)
B55: 45967 | C55: =SUM(IF(F55="",0,F55), IF(F56="",0,F56), IF(Q55="",0,Q55), IF(AT55="",0,AT55), IF(AA55="",0,AA55), IF(AG55="",0,AG55), IF(AM55="",0,AM55)) -> 127500 | D55: 15853 | E55: =IF(D55="","",D55-D53) -> 5 | F55: =IF(D55="","",E55*100) -> 500 | K55: リセット済み | M55: =IF(B55="","",B55) -> 45967 | O55: 2535 | P55: =IF(O55="","",O55-O53) -> 6 | Q55: =IF(O55="","",P55*1000) -> 6000 | X55: =IF(AP55="","",AP55) -> 45967 | Y55: 7320 | Z55: =IF(Y55="","",Y55-Y53) -> 3 | AA55: =IF(Y55="","",Z55*1000) -> 3000 | AD55: =IF(X55="","",X55) -> 45967 | AE55: 4967 | AF55: =IF(AE55="","",AE55-AE53) -> 40 | AG55: =IF(AE55="","",AF55*1000) -> 40000 | AJ55: =IF(AD55="","",AD55) -> 45967 | AK55: 7107 | AL55: =IF(AK55="","",AK55-AK53) -> 12 | AM55: =IF(AK55="","",AL55*1000) -> 12000 | AP55: =IF(M55="","",M55) -> 45967 | AR55: 8457 | AS55: =IF(AR55="","",AR55-AR53) -> 54 | AT55: =IF(AR55="","",AS55*1000) -> 54000
D56: 5522 | E56: =IF(D56="","",D56-D54) -> 120 | F56: =IF(D56="","",E56*100) -> 12000 | K56: 玉補充済み | M56: =IF(B56="","",B56) | P56: =IF(O56="","",O56-O55) | Q56: =IF(O56="","",P56*1000) | X56: =IF(AP56="","",AP56) | Z56: =IF(Y56="","",Y56-Y55) | AA56: =IF(Y56="","",Z56*1000) | AD56: =IF(X56="","",X56) | AF56: =IF(AE56="","",AE56-AE55) | AG56: =IF(AE56="","",AF56*1000) | AJ56: =IF(AD56="","",AD56) | AL56: =IF(AK56="","",AK56-AK55) | AM56: =IF(AK56="","",AL56*1000) | AP56: =IF(M56="","",M56) | AS56: =IF(AR56="","",AR56-AR55) | AT56: =IF(AR56="","",AS56*1000)
B57: 45971 | C57: =SUM(IF(F57="",0,F57), IF(F58="",0,F58), IF(Q57="",0,Q57), IF(AT57="",0,AT57), IF(AA57="",0,AA57), IF(AG57="",0,AG57), IF(AM57="",0,AM57)) -> 102600 | D57: 16049 | E57: =IF(D57="","",D57-D55) -> 196 | F57: =IF(D57="","",E57*100) -> 19600 | M57: =IF(B57="","",B57) -> 45971 | O57: 2551 | P57: =IF(O57="","",O57-O55) -> 16 | Q57: =IF(O57="","",P57*1000) -> 16000 | X57: =IF(AP57="","",AP57) -> 45971 | Y57: 7332 | Z57: =IF(Y57="","",Y57-Y55) -> 12 | AA57: =IF(Y57="","",Z57*1000) -> 12000 | AD57: =IF(X57="","",X57) -> 45971 | AE57: 4991 | AF57: =IF(AE57="","",AE57-AE55) -> 24 | AG57: =IF(AE57="","",AF57*1000) -> 24000 | AJ57: =IF(AD57="","",AD57) -> 45971 | AK57: 7121 | AL57: =IF(AK57="","",AK57-AK55) -> 14 | AM57: =IF(AK57="","",AL57*1000) -> 14000 | AP57: =IF(M57="","",M57) -> 45971 | AR57: 8469 | AS57: =IF(AR57="","",AR57-AR55) -> 12 | AT57: =IF(AR57="","",AS57*1000) -> 12000
D58: 5572 | E58: =IF(D58="","",D58-D56) -> 50 | F58: =IF(D58="","",E58*100) -> 5000 | M58: =IF(B58="","",B58) | P58: =IF(O58="","",O58-O57) | Q58: =IF(O58="","",P58*1000) | X58: =IF(AP58="","",AP58) | Z58: =IF(Y58="","",Y58-Y57) | AA58: =IF(Y58="","",Z58*1000) | AD58: =IF(X58="","",X58) | AF58: =IF(AE58="","",AE58-AE57) | AG58: =IF(AE58="","",AF58*1000) | AJ58: =IF(AD58="","",AD58) | AL58: =IF(AK58="","",AK58-AK57) | AM58: =IF(AK58="","",AL58*1000) | AP58: =IF(M58="","",M58) | AS58: =IF(AR58="","",AR58-AR57) | AT58: =IF(AR58="","",AS58*1000)
B59: 45974 | C59: =SUM(IF(F59="",0,F59), IF(F60="",0,F60), IF(Q59="",0,Q59), IF(AT59="",0,AT59), IF(AA59="",0,AA59), IF(AG59="",0,AG59), IF(AM59="",0,AM59)) -> 66600 | D59: 16155 | E59: =IF(D59="","",D59-D57) -> 106 | F59: =IF(D59="","",E59*100) -> 10600 | M59: =IF(B59="","",B59) -> 45974 | O59: 2565 | P59: =IF(O59="","",O59-O57) -> 14 | Q59: =IF(O59="","",P59*1000) -> 14000 | X59: =IF(AP59="","",AP59) -> 45974 | Y59: 7335 | Z59: =IF(Y59="","",Y59-Y57) -> 3 | AA59: =IF(Y59="","",Z59*1000) -> 3000 | AD59: =IF(X59="","",X59) -> 45974 | AE59: 5009 | AF59: =IF(AE59="","",AE59-AE57) -> 18 | AG59: =IF(AE59="","",AF59*1000) -> 18000 | AJ59: =IF(AD59="","",AD59) -> 45974 | AK59: 7131 | AL59: =IF(AK59="","",AK59-AK57) -> 10 | AM59: =IF(AK59="","",AL59*1000) -> 10000 | AP59: =IF(M59="","",M59) -> 45974 | AR59: 8479 | AS59: =IF(AR59="","",AR59-AR57) -> 10 | AT59: =IF(AR59="","",AS59*1000) -> 10000
D60: 5582 | E60: =IF(D60="","",D60-D58) -> 10 | F60: =IF(D60="","",E60*100) -> 1000 | M60: =IF(B60="","",B60) | P60: =IF(O60="","",O60-O58) | Q60: =IF(O60="","",P60*1000) | X60: =IF(AP60="","",AP60) | Z60: =IF(Y60="","",Y60-Y58) | AA60: =IF(Y60="","",Z60*1000) | AD60: =IF(X60="","",X60) | AF60: =IF(AE60="","",AE60-AE58) | AG60: =IF(AE60="","",AF60*1000) | AJ60: =IF(AD60="","",AD60) | AL60: =IF(AK60="","",AK60-AK58) | AM60: =IF(AK60="","",AL60*1000) | AP60: =IF(M60="","",M60) | AS60: =IF(AR60="","",AR60-AR58) | AT60: =IF(AR60="","",AS60*1000)
C63: =SUM(IF(F63="",0,F63), IF(F64="",0,F64), IF(Q63="",0,Q63), IF(AT63="",0,AT63), IF(AA63="",0,AA63), IF(AG63="",0,AG63), IF(AM63="",0,AM63)) -> 0 | E63: =IF(D63="","",D63-D61) | F63: =IF(D63="","",E63*100) | M63: =IF(B63="","",B63) | P63: =IF(O63="","",O63-O61) | Q63: =IF(O63="","",P63*1000) | X63: =IF(AP63="","",AP63) | Z63: =IF(Y63="","",Y63-Y61) | AA63: =IF(Y63="","",Z63*1000) | AD63: =IF(X63="","",X63) | AF63: =IF(AE63="","",AE63-AE61) | AG63: =IF(AE63="","",AF63*1000) | AJ63: =IF(AD63="","",AD63) | AL63: =IF(AK63="","",AK63-AK61) | AM63: =IF(AK63="","",AL63*1000) | AP63: =IF(M63="","",M63) | AS63: =IF(AR63="","",AR63-AR61) | AT63: =IF(AR63="","",AS63*1000)
E64: =IF(D64="","",D64-D62) | F64: =IF(D64="","",E64*100) | P64: =IF(O64="","",O64-O62) | Z64: =IF(Y64="","",Y64-Y62) | AF64: =IF(AE64="","",AE64-AE62) | AL64: =IF(AK64="","",AK64-AK62) | AS64: =IF(AR64="","",AR64-AR62)
C65: =SUM(IF(F65="",0,F65), IF(F66="",0,F66), IF(Q65="",0,Q65), IF(AT65="",0,AT65), IF(AA65="",0,AA65), IF(AG65="",0,AG65), IF(AM65="",0,AM65)) -> 0 | E65: =IF(D65="","",D65-D63) | F65: =IF(D65="","",E65*100) | M65: =IF(B65="","",B65) | P65: =IF(O65="","",O65-O63) | Q65: =IF(O65="","",P65*1000) | X65: =IF(AP65="","",AP65) | Z65: =IF(Y65="","",Y65-Y63) | AA65: =IF(Y65="","",Z65*1000) | AD65: =IF(X65="","",X65) | AF65: =IF(AE65="","",AE65-AE63) | AG65: =IF(AE65="","",AF65*1000) | AJ65: =IF(AD65="","",AD65) | AL65: =IF(AK65="","",AK65-AK63) | AM65: =IF(AK65="","",AL65*1000) | AP65: =IF(M65="","",M65) | AS65: =IF(AR65="","",AR65-AR63) | AT65: =IF(AR65="","",AS65*1000)
E66: =IF(D66="","",D66-D64) | F66: =IF(D66="","",E66*100) | P66: =IF(O66="","",O66-O64) | Z66: =IF(Y66="","",Y66-Y64) | AF66: =IF(AE66="","",AE66-AE64) | AL66: =IF(AK66="","",AK66-AK64) | AS66: =IF(AR66="","",AR66-AR64)
C67: =SUM(IF(F67="",0,F67), IF(F68="",0,F68), IF(Q67="",0,Q67), IF(AT67="",0,AT67), IF(AA67="",0,AA67), IF(AG67="",0,AG67), IF(AM67="",0,AM67)) -> 0 | E67: =IF(D67="","",D67-D65) | F67: =IF(D67="","",E67*100) | M67: =IF(B67="","",B67) | P67: =IF(O67="","",O67-O65) | Q67: =IF(O67="","",P67*1000) | X67: =IF(AP67="","",AP67) | Z67: =IF(Y67="","",Y67-Y65) | AA67: =IF(Y67="","",Z67*1000) | AD67: =IF(X67="","",X67) | AF67: =IF(AE67="","",AE67-AE65) | AG67: =IF(AE67="","",AF67*1000) | AJ67: =IF(AD67="","",AD67) | AL67: =IF(AK67="","",AK67-AK65) | AM67: =IF(AK67="","",AL67*1000) | AP67: =IF(M67="","",M67) | AS67: =IF(AR67="","",AR67-AR65) | AT67: =IF(AR67="","",AS67*1000)
E68: =IF(D68="","",D68-D66) | F68: =IF(D68="","",E68*100)
C69: =SUM(IF(F69="",0,F69), IF(F70="",0,F70), IF(Q69="",0,Q69), IF(AT69="",0,AT69), IF(AA69="",0,AA69), IF(AG69="",0,AG69), IF(AM69="",0,AM69)) -> 0 | E69: =IF(D69="","",D69-D67) | F69: =IF(D69="","",E69*100) | M69: =IF(B69="","",B69) | P69: =IF(O69="","",O69-O67) | Q69: =IF(O69="","",P69*1000) | X69: =IF(AP69="","",AP69) | Z69: =IF(Y69="","",Y69-Y67) | AA69: =IF(Y69="","",Z69*1000) | AD69: =IF(X69="","",X69) | AF69: =IF(AE69="","",AE69-AE67) | AG69: =IF(AE69="","",AF69*1000) | AJ69: =IF(AD69="","",AD69) | AL69: =IF(AK69="","",AK69-AK67) | AM69: =IF(AK69="","",AL69*1000) | AP69: =IF(M69="","",M69) | AS69: =IF(AR69="","",AR69-AR67) | AT69: =IF(AR69="","",AS69*1000)
E70: =IF(D70="","",D70-D68) | F70: =IF(D70="","",E70*100) | M70: =IF(B70="","",B70)
C71: =SUM(IF(F71="",0,F71), IF(F72="",0,F72), IF(Q71="",0,Q71), IF(AT71="",0,AT71), IF(AA71="",0,AA71), IF(AG71="",0,AG71), IF(AM71="",0,AM71)) -> 0 | E71: =IF(D71="","",D71-D69) | F71: =IF(D71="","",E71*100) | M71: =IF(B71="","",B71) | P71: =IF(O71="","",O71-O69) | Q71: =IF(O71="","",P71*1000) | Z71: =IF(Y71="","",Y71-Y69) | AA71: =IF(Y71="","",Z71*1000) | AD71: =IF(X71="","",X71) | AF71: =IF(AE71="","",AE71-AE69) | AG71: =IF(AE71="","",AF71*1000) | AJ71: =IF(AD71="","",AD71) | AL71: =IF(AK71="","",AK71-AK69) | AM71: =IF(AK71="","",AL71*1000) | AP71: =IF(M71="","",M71) | AS71: =IF(AR71="","",AR71-AR69) | AT71: =IF(AR71="","",AS71*1000)
E72: =IF(D72="","",D72-D70) | F72: =IF(D72="","",E72*100)
C73: =SUM(IF(F73="",0,F73), IF(F74="",0,F74), IF(Q73="",0,Q73), IF(AT73="",0,AT73), IF(AA73="",0,AA73), IF(AG73="",0,AG73), IF(AM73="",0,AM73)) -> 0 | E73: =IF(D73="","",D73-D71) | F73: =IF(D73="","",E73*100) | M73: =IF(B73="","",B73) | P73: =IF(O73="","",O73-O71) | Q73: =IF(O73="","",P73*1000) | X73: =IF(AP73="","",AP73) | Z73: =IF(Y73="","",Y73-Y71) | AA73: =IF(Y73="","",Z73*1000) | AD73: =IF(X73="","",X73) | AF73: =IF(AE73="","",AE73-AE71) | AG73: =IF(AE73="","",AF73*1000) | AJ73: =IF(AD73="","",AD73) | AL73: =IF(AK73="","",AK73-AK71) | AM73: =IF(AK73="","",AL73*1000) | AP73: =IF(M73="","",M73) | AS73: =IF(AR73="","",AR73-AR71) | AT73: =IF(AR73="","",AS73*1000)
E74: =IF(D74="","",D74-D72) | F74: =IF(D74="","",E74*100)
C75: =SUM(IF(F75="",0,F75), IF(F76="",0,F76), IF(Q75="",0,Q75), IF(AT75="",0,AT75), IF(AA75="",0,AA75), IF(AG75="",0,AG75), IF(AM75="",0,AM75)) -> 0 | E75: =IF(D75="","",D75-D73) | F75: =IF(D75="","",E75*100) | M75: =IF(B75="","",B75) | P75: =IF(O75="","",O75-O73) | Q75: =IF(O75="","",P75*1000) | X75: =IF(AP75="","",AP75) | Z75: =IF(Y75="","",Y75-Y73) | AA75: =IF(Y75="","",Z75*1000) | AD75: =IF(X75="","",X75) | AF75: =IF(AE75="","",AE75-AE73) | AG75: =IF(AE75="","",AF75*1000) | AJ75: =IF(AD75="","",AD75) | AL75: =IF(AK75="","",AK75-AK73) | AM75: =IF(AK75="","",AL75*1000) | AP75: =IF(M75="","",M75) | AS75: =IF(AR75="","",AR75-AR73) | AT75: =IF(AR75="","",AS75*1000)
E76: =IF(D76="","",D76-D74) | F76: =IF(D76="","",E76*100)
C77: =SUM(IF(F77="",0,F77), IF(F78="",0,F78), IF(Q77="",0,Q77), IF(AT77="",0,AT77), IF(AA77="",0,AA77), IF(AG77="",0,AG77), IF(AM77="",0,AM77)) -> 0 | E77: =IF(D77="","",D77-D75) | F77: =IF(D77="","",E77*100) | M77: =IF(B77="","",B77) | P77: =IF(O77="","",O77-O75) | Q77: =IF(O77="","",P77*1000) | X77: =IF(AP77="","",AP77) | Z77: =IF(Y77="","",Y77-Y75) | AA77: =IF(Y77="","",Z77*1000) | AD77: =IF(X77="","",X77) | AF77: =IF(AE77="","",AE77-AE75) | AG77: =IF(AE77="","",AF77*1000) | AJ77: =IF(AD77="","",AD77) | AL77: =IF(AK77="","",AK77-AK75) | AM77: =IF(AK77="","",AL77*1000) | AP77: =IF(M77="","",M77) | AS77: =IF(AR77="","",AR77-AR75) | AT77: =IF(AR77="","",AS77*1000)
E78: =IF(D78="","",D78-D76) | F78: =IF(D78="","",E78*100)
C79: =SUM(IF(F79="",0,F79), IF(F80="",0,F80), IF(Q79="",0,Q79), IF(AT79="",0,AT79), IF(AA79="",0,AA79), IF(AG79="",0,AG79), IF(AM79="",0,AM79)) -> 0 | E79: =IF(D79="","",D79-D77) | F79: =IF(D79="","",E79*100) | M79: =IF(B79="","",B79) | P79: =IF(O79="","",O79-O77) | Q79: =IF(O79="","",P79*1000) | X79: =IF(AP79="","",AP79) | Z79: =IF(Y79="","",Y79-Y77) | AA79: =IF(Y79="","",Z79*1000) | AD79: =IF(X79="","",X79) | AF79: =IF(AE79="","",AE79-AE77) | AG79: =IF(AE79="","",AF79*1000) | AJ79: =IF(AD79="","",AD79) | AL79: =IF(AK79="","",AK79-AK77) | AM79: =IF(AK79="","",AL79*1000) | AP79: =IF(M79="","",M79) | AS79: =IF(AR79="","",AR79-AR77) | AT79: =IF(AR79="","",AS79*1000)
E80: =IF(D80="","",D80-D78) | F80: =IF(D80="","",E80*100)
B81: =DATEDIF(B$17,B$59,"d") -> 28 | E81: =IF(D81="","",D81-D73) | F81: =IF(D81="","",E81*100) | M81: =IF(B81="","",B81) -> 28 | P81: =IF(O81="","",O81-O73) | Q81: =IF(O81="","",P81*1000) | X81: =IF(AP81="","",AP81) -> 28 | Z81: =IF(Y81="","",Y81-Y73) | AA81: =IF(Y81="","",Z81*1000) | AD81: =IF(X81="","",X81) -> 28 | AF81: =IF(AE81="","",AE81-AE73) | AG81: =IF(AE81="","",AF81*1000) | AJ81: =IF(AD81="","",AD81) -> 28 | AL81: =IF(AK81="","",AK81-AK73) | AM81: =IF(AK81="","",AL81*1000) | AP81: =IF(M81="","",M81) -> 28 | AS81: =IF(AR81="","",AR81-AR73) | AT81: =IF(AR81="","",AS81*1000)
E82: =IF(D82="","",D82-D78) | F82: =IF(D82="","",E82*100)
B83: =SUM(E47, E49, E51, E53, E55, E57, E59, E61, E63, E65, E67, E69, E83,E71,E73,E75,E77,E79,E81) -> 1197 | E83: =IF(D83="","",D83-D81) | F83: =IF(D83="","",E83*100) | M83: =SUM(P47, P49, P51, P53, P55, P57, P59, P61, P63, P65, P73, P81, P83) -> 151 | P83: =IF(O83="","",O83-O81) | Q83: =IF(O83="","",P83*1000) | X83: =SUM(Z47, Z49, Z51, Z53, Z55, Z57, Z59, Z61, Z63, Z65, Z73, Z81, Z83) -> 98 | Z83: =IF(Y83="","",Y83-Y81) | AA83: =IF(Y83="","",Z83*1000) | AD83: =SUM(AF47, AF49, AF51, AF53, AF55, AF57, AF59, AF61, AF63, AF65, AF73, AF81, AF83) -> 190 | AF83: =IF(AE83="","",AE83-AE81) | AG83: =IF(AE83="","",AF83*1000) | AJ83: =SUM(AL47, AL49, AL51, AL53, AL55, AL57, AL59, AL61, AL63, AL65, AL73, AL81, AL83) -> 108 | AL83: =IF(AK83="","",AK83-AK81) | AM83: =IF(AK83="","",AL83*1000) | AP83: =SUM(AS47, AS49, AS51, AS53, AS55, AS57, AS59, AS61, AS63, AS65, AS73, AS81, AS83) -> 126 | AS83: =IF(AR83="","",AR83-AR81) | AT83: =IF(AR83="","",AS83*1000)
B84: =SUM(E48, E50, E52, E54, E56, E58, E60, E62, E64, E66, E68, E70, E84,E72,E74,E76,E78,E80,E82) -> 555 | E84: =IF(D84="","",D84-D82) | F84: =IF(D84="","",E84*100) | M84: =SUM(P48, P50, P52, P54, P56, P58, P60, P62, P64, P66, P78, P82, P84) -> 0 | X84: =SUM(Z48, Z50, Z52, Z54, Z56, Z58, Z60, Z62, Z64, Z66, Z78, Z82, Z84) -> 0 | AD84: =SUM(AF48, AF50, AF52, AF54, AF56, AF58, AF60, AF62, AF64, AF66, AF78, AF82, AF84) -> 0 | AJ84: =SUM(AL48, AL50, AL52, AL54, AL56, AL58, AL60, AL62, AL64, AL66, AL78, AL82, AL84) -> 0 | AP84: =SUM(AS48, AS50, AS52, AS54, AS56, AS58, AS60, AS62, AS64, AS66, AS78, AS82, AS84) -> 0
C85: =SUM(C47:C78) -> 848200 | E85: =SUM(E47:E84) -> 1752 | F85: =SUM(F47:F84) -> 175200 | G85: =SUM(G47:G58) -> 0 | H85: =SUM(H47:H58) -> 0 | I85: =SUM(I47:I58) -> 0 | J85: =SUM(J47:J58) -> 0 | P85: =SUM(P47:P83) -> 151 | Q85: =SUM(Q47:Q84) -> 151000 | R85: =SUM(R47:R58) -> 0 | S85: =SUM(S47:S58) -> 0 | T85: =SUM(T47:T58) -> 0 | U85: =SUM(U47:U58) -> 0 | Z85: =SUM(Z47:Z83) -> 98 | AA85: =SUM(AA47:AA84) -> 98000 | AF85: =SUM(AF47:AF83) -> 190 | AG85: =SUM(AG47:AG84) -> 190000 | AL85: =SUM(AL47:AL83) -> 108 | AM85: =SUM(AM47:AM84) -> 108000 | AS85: =SUM(AS47:AS83) -> 126 | AT85: =SUM(AT47:AT84) -> 126000 | AU85: =SUM(AU47:AU58) -> 0 | AV85: =SUM(AV47:AV58) -> 0 | AW85: =SUM(AW47:AW58) -> 0 | AX85: =SUM(AX47:AX58) -> 0
B86: 今月の日数 | C86: 全台日売AVE | D86: 売上予想合計 | E86: AVE | F86: 売上予想 | P86: AVE | Q86: 売上予想 | Z86: AVE | AA86: 売上予想 | AF86: AVE | AG86: 売上予想 | AL86: AVE | AM86: 売上予想 | AS86: AVE | AT86: 売上予想
B87: 28 | C87: =C85/B81 -> 30292.857 | D87: =C87*B87 -> 848200 | E87: =E85/B81*100 -> 6257.1429 | F87: =E87*B87 -> 175200 | P87: =P85/M81*1000 -> 5392.8571 | Q87: =P87*B87 -> 151000 | Z87: =Z85/X81*1000 -> 3500 | AA87: =Z87*B87 -> 98000 | AF87: =AF85/AD81*1000 -> 6785.7143 | AG87: =AF87*B87 -> 190000 | AL87: =AL85/AJ81*1000 -> 3857.1429 | AM87: =AL87*B87 -> 108000 | AS87: =AS85/AP81*1000 -> 4500 | AT87: =AS87*B87 -> 126000
B89: ５００円 | M89: ２０００円 | X89: 1000円ソフト | AD89: 2000円ブランド | AJ89: 2000円ゲーム | AP89: 2000円スニーカー
B90: 日付 | D90: 今回ﾒｰﾀｰ | E90: ﾒｰﾀｰ差 | F90: 売上 | K90: 備考 | M90: 日付 | O90: 今回ﾒｰﾀｰ | P90: ﾒｰﾀｰ差 | Q90: 売上 | V90: 備考 | X90: 日付 | Y90: 今回ﾒｰﾀｰ | Z90: ﾒｰﾀｰ差 | AA90: 売上 | AB90: 備考 | AD90: 日付 | AE90: 今回ﾒｰﾀｰ | AF90: ﾒｰﾀｰ差 | AG90: 売上 | AH90: 備考 | AJ90: 日付 | AK90: 今回ﾒｰﾀｰ | AL90: ﾒｰﾀｰ差 | AM90: 売上 | AN90: 備考 | AP90: 日付 | AR90: 今回ﾒｰﾀｰ | AS90: ﾒｰﾀｰ差 | AT90: 売上 | AY90: 備考
B91: 45977 | C91: 89500 | D91: 16330 | E91: 175 | F91: 17500 | M91: 45977 | O91: 2593 | P91: 28 | Q91: 28000 | X91: 45977 | Y91: 7346 | Z91: 11 | AA91: 11000 | AD91: 45977 | AE91: 5023 | AF91: 14 | AG91: 14000 | AJ91: 45977 | AK91: 7137 | AL91: 6 | AM91: 6000 | AP91: 45977 | AR91: 8489 | AS91: 10 | AT91: 10000
D92: 5612 | E92: 30 | F92: 3000
B93: 45982 | C93: =SUM(IF(F93="",0,F93), IF(F94="",0,F94), IF(Q93="",0,Q93), IF(AT93="",0,AT93), IF(AA93="",0,AA93), IF(AG93="",0,AG93), IF(AM93="",0,AM93)) -> 41500 | D93: 16370 | E93: =IF(D93="","",D93-D91) -> 40 | F93: =IF(D93="","",E93*100) -> 4000 | M93: =IF(B93="","",B93) -> 45982 | O93: 2605 | P93: =IF(O93="","",O93-O91) -> 12 | Q93: =IF(O93="","",P93*1000) -> 12000 | X93: =IF(AP93="","",AP93) -> 45982 | Y93: 7347 | Z93: =IF(Y93="","",Y93-Y91) -> 1 | AA93: =IF(Y93="","",Z93*1000) -> 1000 | AD93: =IF(AP93="","",AP93) -> 45982 | AE93: 5035 | AF93: =IF(AE93="","",AE93-AE91) -> 12 | AG93: =IF(AE93="","",AF93*1000) -> 12000 | AJ93: =IF(AD93="","",AD93) -> 45982 | AK93: 7143 | AL93: =IF(AK93="","",AK93-AK91) -> 6 | AM93: =IF(AK93="","",AL93*1000) -> 6000 | AP93: =IF(M93="","",M93) -> 45982 | AR93: 8495 | AS93: =IF(AR93="","",AR93-AR91) -> 6 | AT93: =IF(AR93="","",AS93*1000) -> 6000
D94: 5617 | E94: =IF(D94="","",D94-D92) -> 5 | F94: =IF(D94="","",E94*100) -> 500 | P94: =IF(O94="","",O94-O92) | Z94: =IF(Y94="","",Y94-Y92) | AF94: =IF(AE94="","",AE94-AE92) | AL94: =IF(AK94="","",AK94-AK92) | AS94: =IF(AR94="","",AR94-AR92)
B95: 45984 | C95: =SUM(IF(F95="",0,F95), IF(F96="",0,F96), IF(Q95="",0,Q95), IF(AT95="",0,AT95), IF(AA95="",0,AA95), IF(AG95="",0,AG95), IF(AM95="",0,AM95)) -> 57500 | D95: 16430 | E95: =IF(D95="","",D95-D93) -> 60 | F95: =IF(D95="","",E95*100) -> 6000 | M95: =IF(B95="","",B95) -> 45984 | O95: 2613 | P95: =IF(O95="","",O95-O93) -> 8 | Q95: =IF(O95="","",P95*1000) -> 8000 | X95: =IF(AP95="","",AP95) -> 45984 | Y95: 7363 | Z95: =IF(Y95="","",Y95-Y93) -> 16 | AA95: =IF(Y95="","",Z95*1000) -> 16000 | AD95: =IF(X95="","",X95) -> 45984 | AE95: 5039 | AF95: =IF(AE95="","",AE95-AE93) -> 4 | AG95: =IF(AE95="","",AF95*1000) -> 4000 | AJ95: =IF(AD95="","",AD95) -> 45984 | AK95: 7151 | AL95: =IF(AK95="","",AK95-AK93) -> 8 | AM95: =IF(AK95="","",AL95*1000) -> 8000 | AP95: =IF(M95="","",M95) -> 45984 | AR95: 8509 | AS95: =IF(AR95="","",AR95-AR93) -> 14 | AT95: =IF(AR95="","",AS95*1000) -> 14000 | AY95: ドラクエ1＆2 ちょい足し
D96: 5632 | E96: =IF(D96="","",D96-D94) -> 15 | F96: =IF(D96="","",E96*100) -> 1500 | M96: =IF(B96="","",B96) | P96: =IF(O96="","",O96-O95) | Q96: =IF(O96="","",P96*1000) | X96: =IF(AP96="","",AP96) | Z96: =IF(Y96="","",Y96-Y95) | AA96: =IF(Y96="","",Z96*1000) | AD96: =IF(X96="","",X96) | AF96: =IF(AE96="","",AE96-AE95) | AG96: =IF(AE96="","",AF96*1000) | AJ96: =IF(AD96="","",AD96) | AL96: =IF(AK96="","",AK96-AK95) | AM96: =IF(AK96="","",AL96*1000) | AP96: =IF(M96="","",M96) | AS96: =IF(AR96="","",AR96-AR95) | AT96: =IF(AR96="","",AS96*1000)
B97: 45987 | C97: =SUM(IF(F97="",0,F97), IF(F98="",0,F98), IF(Q97="",0,Q97), IF(AT97="",0,AT97), IF(AA97="",0,AA97), IF(AG97="",0,AG97), IF(AM97="",0,AM97)) -> 97000 | D97: 16555 | E97: =IF(D97="","",D97-D95) -> 125 | F97: =IF(D97="","",E97*100) -> 12500 | M97: =IF(B97="","",B97) -> 45987 | O97: 2631 | P97: =IF(O97="","",O97-O95) -> 18 | Q97: =IF(O97="","",P97*1000) -> 18000 | X97: =IF(AP97="","",AP97) -> 45987 | Y97: 7367 | Z97: =IF(Y97="","",Y97-Y95) -> 4 | AA97: =IF(Y97="","",Z97*1000) -> 4000 | AD97: =IF(X97="","",X97) -> 45987 | AE97: 5055 | AF97: =IF(AE97="","",AE97-AE95) -> 16 | AG97: =IF(AE97="","",AF97*1000) -> 16000 | AJ97: =IF(AD97="","",AD97) -> 45987 | AK97: 7185 | AL97: =IF(AK97="","",AK97-AK95) -> 34 | AM97: =IF(AK97="","",AL97*1000) -> 34000 | AP97: =IF(M97="","",M97) -> 45987 | AR97: 8519 | AS97: =IF(AR97="","",AR97-AR95) -> 10 | AT97: =IF(AR97="","",AS97*1000) -> 10000
D98: 5657 | E98: =IF(D98="","",D98-D96) -> 25 | F98: =IF(D98="","",E98*100) -> 2500 | M98: =IF(B98="","",B98) | P98: =IF(O98="","",O98-O97) | Q98: =IF(O98="","",P98*1000) | X98: =IF(AP98="","",AP98) | Z98: =IF(Y98="","",Y98-Y97) | AA98: =IF(Y98="","",Z98*1000) | AD98: =IF(X98="","",X98) | AF98: =IF(AE98="","",AE98-AE97) | AG98: =IF(AE98="","",AF98*1000) | AJ98: =IF(AD98="","",AD98) | AL98: =IF(AK98="","",AK98-AK97) | AM98: =IF(AK98="","",AL98*1000) | AP98: =IF(M98="","",M98) | AS98: =IF(AR98="","",AR98-AR97) | AT98: =IF(AR98="","",AS98*1000)
B99: 45989 | C99: =SUM(IF(F99="",0,F99), IF(F100="",0,F100), IF(Q99="",0,Q99), IF(AT99="",0,AT99), IF(AA99="",0,AA99), IF(AG99="",0,AG99), IF(AM99="",0,AM99)) -> 54500 | D99: 16575 | E99: =IF(D99="","",D99-D97) -> 20 | F99: =IF(D99="","",E99*100) -> 2000 | M99: =IF(B99="","",B99) -> 45989 | O99: 2657 | P99: =IF(O99="","",O99-O97) -> 26 | Q99: =IF(O99="","",P99*1000) -> 26000 | X99: =IF(AP99="","",AP99) -> 45989 | Y99: 7369 | Z99: =IF(Y99="","",Y99-Y97) -> 2 | AA99: =IF(Y99="","",Z99*1000) -> 2000 | AD99: =IF(X99="","",X99) -> 45989 | AE99: 5063 | AF99: =IF(AE99="","",AE99-AE97) -> 8 | AG99: =IF(AE99="","",AF99*1000) -> 8000 | AJ99: =IF(AD99="","",AD99) -> 45989 | AK99: 7187 | AL99: =IF(AK99="","",AK99-AK97) -> 2 | AM99: =IF(AK99="","",AL99*1000) -> 2000 | AP99: =IF(M99="","",M99) -> 45989 | AR99: 8533 | AS99: =IF(AR99="","",AR99-AR97) -> 14 | AT99: =IF(AR99="","",AS99*1000) -> 14000
D100: 5662 | E100: =IF(D100="","",D100-D98) -> 5 | F100: =IF(D100="","",E100*100) -> 500 | M100: =IF(B100="","",B100) | P100: =IF(O100="","",O100-O99) | Q100: =IF(O100="","",P100*1000) | X100: =IF(AP100="","",AP100) | Z100: =IF(Y100="","",Y100-Y99) | AA100: =IF(Y100="","",Z100*1000) | AD100: =IF(X100="","",X100) | AF100: =IF(AE100="","",AE100-AE99) | AG100: =IF(AE100="","",AF100*1000) | AJ100: =IF(AD100="","",AD100) | AL100: =IF(AK100="","",AK100-AK99) | AM100: =IF(AK100="","",AL100*1000) | AP100: =IF(M100="","",M100) | AS100: =IF(AR100="","",AR100-AR99) | AT100: =IF(AR100="","",AS100*1000)
B101: 45995 | C101: =SUM(IF(F101="",0,F101), IF(F102="",0,F102), IF(Q101="",0,Q101), IF(AT101="",0,AT101), IF(AA101="",0,AA101), IF(AG101="",0,AG101), IF(AM101="",0,AM101)) -> 165000 | D101: 16575 | E101: =IF(D101="","",D101-D99) -> 0 | F101: =IF(D101="","",E101*100) -> 0 | K101: リセット済み | M101: =IF(B101="","",B101) -> 45995 | O101: 2693 | P101: =IF(O101="","",O101-O99) -> 36 | Q101: =IF(O101="","",P101*1000) -> 36000 | X101: =IF(AP101="","",AP101) -> 45995 | Y101: 7402 | Z101: =IF(Y101="","",Y101-Y99) -> 33 | AA101: =IF(Y101="","",Z101*1000) -> 33000 | AB101: リセット済み | AD101: =IF(X101="","",X101) -> 45995 | AE101: 5089 | AF101: =IF(AE101="","",AE101-AE99) -> 26 | AG101: =IF(AE101="","",AF101*1000) -> 26000 | AJ101: =IF(AD101="","",AD101) -> 45995 | AK101: 7211 | AL101: =IF(AK101="","",AK101-AK99) -> 24 | AM101: =IF(AK101="","",AL101*1000) -> 24000 | AP101: =IF(M101="","",M101) -> 45995 | AR101: 8579 | AS101: =IF(AR101="","",AR101-AR99) -> 46 | AT101: =IF(AR101="","",AS101*1000) -> 46000
D102: 5662 | E102: =IF(D102="","",D102-D100) -> 0 | F102: =IF(D102="","",E102*100) -> 0 | K102: リセット済み | M102: =IF(B102="","",B102) | P102: =IF(O102="","",O102-O101) | Q102: =IF(O102="","",P102*1000) | X102: =IF(AP102="","",AP102) | Z102: =IF(Y102="","",Y102-Y101) | AA102: =IF(Y102="","",Z102*1000) | AD102: =IF(X102="","",X102) | AF102: =IF(AE102="","",AE102-AE101) | AG102: =IF(AE102="","",AF102*1000) | AJ102: =IF(AD102="","",AD102) | AL102: =IF(AK102="","",AK102-AK101) | AM102: =IF(AK102="","",AL102*1000) | AP102: =IF(M102="","",M102) | AS102: =IF(AR102="","",AR102-AR101) | AT102: =IF(AR102="","",AS102*1000)
B103: 45999 | C103: =SUM(IF(F103="",0,F103), IF(F104="",0,F104), IF(Q103="",0,Q103), IF(AT103="",0,AT103), IF(AA103="",0,AA103), IF(AG103="",0,AG103), IF(AM103="",0,AM103)) -> 129500 | D103: 17030 | E103: =IF(D103="","",D103-D101) -> 455 | F103: =IF(D103="","",E103*100) -> 45500 | M103: =IF(B103="","",B103) -> 45999 | O103: 2699 | P103: =IF(O103="","",O103-O101) -> 6 | Q103: =IF(O103="","",P103*1000) -> 6000 | X103: =IF(AP103="","",AP103) -> 45999 | Y103: 7429 | Z103: =IF(Y103="","",Y103-Y101) -> 27 | AA103: =IF(Y103="","",Z103*1000) -> 27000 | AB103: 60玉補充 | AD103: =IF(X103="","",X103) -> 45999 | AE103: 5113 | AF103: =IF(AE103="","",AE103-AE101) -> 24 | AG103: =IF(AE103="","",AF103*1000) -> 24000 | AJ103: =IF(AD103="","",AD103) -> 45999 | AK103: 7221 | AL103: =IF(AK103="","",AK103-AK101) -> 10 | AM103: =IF(AK103="","",AL103*1000) -> 10000 | AP103: =IF(M103="","",M103) -> 45999 | AR103: 8587 | AS103: =IF(AR103="","",AR103-AR101) -> 8 | AT103: =IF(AR103="","",AS103*1000) -> 8000
D104: 5752 | E104: =IF(D104="","",D104-D102) -> 90 | F104: =IF(D104="","",E104*100) -> 9000 | M104: =IF(B104="","",B104) | P104: =IF(O104="","",O104-O102) | Q104: =IF(O104="","",P104*1000) | X104: =IF(AP104="","",AP104) | Z104: =IF(Y104="","",Y104-Y102) | AA104: =IF(Y104="","",Z104*1000) | AD104: =IF(X104="","",X104) | AF104: =IF(AE104="","",AE104-AE102) | AG104: =IF(AE104="","",AF104*1000) | AJ104: =IF(AD104="","",AD104) | AL104: =IF(AK104="","",AK104-AK102) | AM104: =IF(AK104="","",AL104*1000) | AP104: =IF(M104="","",M104) | AS104: =IF(AR104="","",AR104-AR102) | AT104: =IF(AR104="","",AS104*1000)
B105: 46003 | C105: =SUM(IF(F105="",0,F105), IF(F106="",0,F106), IF(Q105="",0,Q105), IF(AT105="",0,AT105), IF(AA105="",0,AA105), IF(AG105="",0,AG105), IF(AM105="",0,AM105)) -> 89000 | D105: 17075 | E105: =IF(D105="","",D105-D103) -> 45 | F105: =IF(D105="","",E105*100) -> 4500 | M105: =IF(B105="","",B105) -> 46003 | O105: 2725 | P105: =IF(O105="","",O105-O103) -> 26 | Q105: =IF(O105="","",P105*1000) -> 26000 | X105: =IF(AP105="","",AP105) -> 46003 | Y105: 7445 | Z105: =IF(Y105="","",Y105-Y103) -> 16 | AA105: =IF(Y105="","",Z105*1000) -> 16000 | AD105: =IF(X105="","",X105) -> 46003 | AE105: 5121 | AF105: =IF(AE105="","",AE105-AE103) -> 8 | AG105: =IF(AE105="","",AF105*1000) -> 8000 | AJ105: =IF(AD105="","",AD105) -> 46003 | AK105: 7247 | AL105: =IF(AK105="","",AK105-AK103) -> 26 | AM105: =IF(AK105="","",AL105*1000) -> 26000 | AP105: =IF(M105="","",M105) -> 46003 | AR105: 8595 | AS105: =IF(AR105="","",AR105-AR103) -> 8 | AT105: =IF(AR105="","",AS105*1000) -> 8000
D106: 5757 | E106: =IF(D106="","",D106-D104) -> 5 | F106: =IF(D106="","",E106*100) -> 500
...

Sheet 唐津
B1: 1000円ガチャ | H1: 2000円ガチャ
B2: 日付 | C2: 今回ﾒｰﾀｰ | D2: ﾒｰﾀｰ差 | E2: 売上 | F2: 備考
B3: 45914 | C3: 622 | D3: 38 | E3: 38000
B4: 45916 | C4: 665 | D4: =IF(C4="","",C4-C3) -> 43 | E4: =IF(C4="","",D4*1000) -> 43000 | F4: 要、玉補充！！
B5: 45919 | C5: 675 | D5: =IF(C5="","",C5-C4) -> 10 | E5: =IF(C5="","",D5*1000) -> 10000 | F5: ロッカー残り6箇所
B6: 45922 | C6: 712 | D6: =IF(C6="","",C6-C5) -> 37 | E6: =IF(C6="","",D6*1000) -> 37000
B7: 45926 | C7: 725 | D7: =IF(C7="","",C7-C6) -> 13 | E7: =IF(C7="","",D7*1000) -> 13000 | F7: ロッカー残り6 60玉補充
B8: 45930 | C8: 758 | D8: =IF(C8="","",C8-C7) -> 33 | E8: =IF(C8="","",D8*1000) -> 33000 | F8: ロッカー残り6 更に60玉補充
B9: 45933 | C9: 763 | D9: =IF(C9="","",C9-C8) -> 5 | E9: =IF(C9="","",D9*1000) -> 5000
B10: 45936 | C10: 775 | D10: =IF(C10="","",C10-C9) -> 12 | E10: =IF(C10="","",D10*1000) -> 12000
B11: 45940 | C11: 798 | D11: =IF(C11="","",C11-C10) -> 23 | E11: =IF(C11="","",D11*1000) -> 23000 | F11: リセット済み
B12: 45943 | C12: 834 | D12: =IF(C12="","",C12-C11) -> 36 | E12: =IF(C12="","",D12*1000) -> 36000 | F12: ロッカー空き1箇所 残り9箇所
D13: =IF(C13="","",C13-C12) | E13: =IF(C13="","",D13*1000)
D14: =SUM(D3:D13) -> 250 | E14: =SUM(E3:E13) -> 250000
B16: 1000円ガチャ
B17: 日付 | C17: 今回ﾒｰﾀｰ | D17: ﾒｰﾀｰ差 | E17: 売上 | F17: 備考
B18: 45947 | C18: 863 | D18: =IF(C18="","",C18-C12) -> 29 | E18: =IF(C18="","",D18*1000) -> 29000
B19: 45957 | C19: 924 | D19: =IF(C19="","",C19-C18) -> 61 | E19: =IF(C19="","",D19*1000) -> 61000
B20: 45961 | C20: 930 | D20: =IF(C20="","",C20-C19) -> 6 | E20: =IF(C20="","",D20*1000) -> 6000
B21: 45964 | C21: 943 | D21: =IF(C21="","",C21-C20) -> 13 | E21: =IF(C21="","",D21*1000) -> 13000
B22: 45968 | C22: 961 | D22: =IF(C22="","",C22-C21) -> 18 | E22: =IF(C22="","",D22*1000) -> 18000
B23: 45971 | C23: 969 | D23: =IF(C23="","",C23-C22) -> 8 | E23: =IF(C23="","",D23*1000) -> 8000 | F23: リセット済み
B24: 45973 | C24: 982 | D24: =IF(C24="","",C24-C23) -> 13 | E24: =IF(C24="","",D24*1000) -> 13000
D25: =IF(C25="","",C25-C24) | E25: =IF(C25="","",D25*1000)
D26: =IF(C26="","",C26-C25) | E26: =IF(C26="","",D26*1000)
D27: =IF(C27="","",C27-C26) | E27: =IF(C27="","",D27*1000)
D28: =IF(C28="","",C28-C27) | E28: =IF(C28="","",D28*1000)
D29: =SUM(D18:D28) -> 148 | E29: =SUM(E18:E28) -> 148000
B31: 1000円ガチャ | H31: 2000円ガチャ
B32: 日付 | C32: 今回ﾒｰﾀｰ | D32: ﾒｰﾀｰ差 | E32: 売上 | F32: 備考 | H32: 日付 | I32: 今回ﾒｰﾀｰ | J32: ﾒｰﾀｰ差 | K32: 売上 | L32: 備考
B33: 45977 | C33: 1014 | D33: =IF(C33="","",C33-C24) -> 32 | E33: =IF(C33="","",D33*1000) -> 32000 | J33: =IF(I33="","",I33-I24) | K33: =IF(I33="","",J33*1000)
B34: 45982 | C34: 1022 | D34: =IF(C34="","",C34-C33) -> 8 | E34: =IF(C34="","",D34*1000) -> 8000 | J34: =IF(I34="","",I34-I33) | K34: =IF(I34="","",J34*1000)
B35: 45985 | C35: 1028 | D35: =IF(C35="","",C35-C34) -> 6 | E35: =IF(C35="","",D35*1000) -> 6000 | J35: =IF(I35="","",I35-I34) | K35: =IF(I35="","",J35*1000)
B36: 45989 | C36: 1057 | D36: =IF(C36="","",C36-C35) -> 29 | E36: =IF(C36="","",D36*1000) -> 29000 | J36: =IF(I36="","",I36-I35) | K36: =IF(I36="","",J36*1000)
B37: 45996 | C37: 1094 | D37: =IF(C37="","",C37-C36) -> 37 | E37: =IF(C37="","",D37*1000) -> 37000 | J37: =IF(I37="","",I37-I36) | K37: =IF(I37="","",J37*1000)
B38: 45999 | C38: 1118 | D38: =IF(C38="","",C38-C37) -> 24 | E38: =IF(C38="","",D38*1000) -> 24000 | J38: =IF(I38="","",I38-I37) | K38: =IF(I38="","",J38*1000)
B39: 46002 | C39: 1134 | D39: =IF(C39="","",C39-C38) -> 16 | E39: =IF(C39="","",D39*1000) -> 16000 | H39: 46002 | I39: 7699 | K39: =IF(I39="","",J39*1000) -> 0 | L39: 設置
B40: 46006 | C40: 1167 | D40: =IF(C40="","",C40-C39) -> 33 | E40: =IF(C40="","",D40*1000) -> 33000 | H40: 46008 | I40: 7741 | J40: =IF(I40="","",I40-I39) -> 42 | K40: =IF(I40="","",J40*1000) -> 42000
B41: 46008 | C41: 1188 | D41: =IF(C41="","",C41-C40) -> 21 | E41: =IF(C41="","",D41*1000) -> 21000
J42: =IF(I42="","",I42-I41) | K42: =IF(I42="","",J42*1000)
D43: =IF(C43="","",C43-C42) | E43: =IF(C43="","",D43*1000) | J43: =IF(I43="","",I43-I42) | K43: =IF(I43="","",J43*1000)
D44: =SUM(D33:D43) -> 206 | E44: =SUM(E33:E43) -> 206000 | J44: =SUM(J33:J43) -> 42 | K44: =SUM(K33:K43) -> 42000
B46: 1000円ガチャ | H46: 2000円ガチャ
B47: 日付 | C47: 今回ﾒｰﾀｰ | D47: ﾒｰﾀｰ差 | E47: 売上 | F47: 備考 | H47: 日付 | I47: 今回ﾒｰﾀｰ | J47: ﾒｰﾀｰ差 | K47: 売上 | L47: 備考
B48: 46010 | C48: 1191 | D48: =IF(C48="","",C48-C41) -> 3 | E48: =IF(C48="","",D48*1000) -> 3000 | F48: カプセル264補充した | H48: 46010 | I48: 7789 | J48: =IF(I48="","",I48-I40) -> 48 | K48: =IF(I48="","",J48*1000) -> 48000
B49: 46013 | C49: 1206 | D49: =IF(C49="","",C49-C48) -> 15 | E49: =IF(C49="","",D49*1000) -> 15000 | H49: 46013 | I49: 7803 | J49: =IF(I49="","",I49-I48) -> 14 | K49: =IF(I49="","",J49*1000) -> 14000
B50: 46017 | C50: 1223 | D50: =IF(C50="","",C50-C49) -> 17 | E50: =IF(C50="","",D50*1000) -> 17000 | F50: リセットしたい | H50: 46017 | I50: 7811 | J50: =IF(I50="","",I50-I49) -> 8 | K50: =IF(I50="","",J50*1000) -> 8000
B51: 46020 | C51: 1239 | D51: =IF(C51="","",C51-C50) -> 16 | E51: =IF(C51="","",D51*1000) -> 16000 | H51: 46020 | I51: 7829 | J51: =IF(I51="","",I51-I50) -> 18 | K51: =IF(I51="","",J51*1000) -> 18000
B52: 46022 | C52: 1277 | D52: =IF(C52="","",C52-C51) -> 38 | E52: =IF(C52="","",D52*1000) -> 38000 | F52: 4番でた | H52: 46022 | I52: 7835 | J52: =IF(I52="","",I52-I51) -> 6 | K52: =IF(I52="","",J52*1000) -> 6000 | L52: 4と9出た
B53: 46024 | C53: 1337 | D53: =IF(C53="","",C53-C52) -> 60 | E53: =IF(C53="","",D53*1000) -> 60000 | H53: 46024 | I53: 7857 | J53: =IF(I53="","",I53-I52) -> 22 | K53: =IF(I53="","",J53*1000) -> 22000
B54: 46025 | C54: 1368 | D54: =IF(C54="","",C54-C53) -> 31 | E54: =IF(C54="","",D54*1000) -> 31000 | H54: 46025 | I54: 7871 | J54: =IF(I54="","",I54-I53) -> 14 | K54: =IF(I54="","",J54*1000) -> 14000
B55: 46026 | C55: 1388 | D55: =IF(C55="","",C55-C54) -> 20 | E55: =IF(C55="","",D55*1000) -> 20000 | H55: 46026 | I55: 7881 | J55: =IF(I55="","",I55-I54) -> 10 | K55: =IF(I55="","",J55*1000) -> 10000
B56: 46027 | C56: 1401 | D56: =IF(C56="","",C56-C55) -> 13 | E56: =IF(C56="","",D56*1000) -> 13000 | H56: 46027 | I56: 7883 | J56: =IF(I56="","",I56-I55) -> 2 | K56: =IF(I56="","",J56*1000) -> 2000
B57: 46030 | C57: 1432 | D57: =IF(C57="","",C57-C56) -> 31 | E57: =IF(C57="","",D57*1000) -> 31000 | H57: 46030 | I57: 7897 | J57: =IF(I57="","",I57-I56) -> 14 | K57: =IF(I57="","",J57*1000) -> 14000
B58: 46032 | C58: 1445 | D58: =IF(C58="","",C58-C57) -> 13 | E58: =IF(C58="","",D58*1000) -> 13000 | H58: 46032 | I58: 7901 | J58: =IF(I58="","",I58-I57) -> 4 | K58: =IF(I58="","",J58*1000) -> 4000
B59: 46034 | C59: 1479 | D59: =IF(C59="","",C59-C58) -> 34 | E59: =IF(C59="","",D59*1000) -> 34000 | H59: 46034 | I59: 7909 | J59: =IF(I59="","",I59-I58) -> 8 | K59: =IF(I59="","",J59*1000) -> 8000
B60: 46036 | C60: 1491 | D60: =IF(C60="","",C60-C57) -> 59 | E60: =IF(C60="","",D60*1000) -> 59000 | H60: 46036 | I60: 7913 | J60: =IF(I60="","",I60-I57) -> 16 | K60: =IF(I60="","",J60*1000) -> 16000
D61: =SUM(D48:D60) -> 350 | E61: =SUM(E48:E60) -> 350000 | J61: =SUM(J48:J60) -> 184 | K61: =SUM(K48:K60) -> 184000
B63: 1000円ガチャ | H63: 2000円ガチャ
B64: 日付 | C64: 今回ﾒｰﾀｰ | D64: ﾒｰﾀｰ差 | E64: 売上 | F64: 備考 | H64: 日付 | I64: 今回ﾒｰﾀｰ | J64: ﾒｰﾀｰ差 | K64: 売上 | L64: 備考
B65: 46038 | C65: 1499 | D65: =IF(C65="","",C65-C60) -> 8 | E65: =IF(C65="","",D65*1000) -> 8000 | H65: 46038 | I65: 7923 | J65: =IF(I65="","",I65-I60) -> 10 | K65: =IF(I65="","",J65*1000) -> 10000
B66: 46044 | C66: 1521 | D66: =IF(C66="","",C66-C65) -> 22 | E66: =IF(C66="","",D66*1000) -> 22000 | H66: =IF(B66="","",B66) -> 46044 | I66: 7935 | J66: =IF(I66="","",I66-I65) -> 12 | K66: =IF(I66="","",J66*1000) -> 12000 | L66: リセット
B67: 46046 | C67: 1574 | D67: =IF(C67="","",C67-C66) -> 53 | E67: =IF(C67="","",D67*1000) -> 53000 | H67: =IF(B67="","",B67) -> 46046 | I67: 7937 | J67: =IF(I67="","",I67-I66) -> 2 | K67: =IF(I67="","",J67*1000) -> 2000
B68: 46048 | C68: 1591 | D68: =IF(C68="","",C68-C67) -> 17 | E68: =IF(C68="","",D68*1000) -> 17000 | H68: =IF(B68="","",B68) -> 46048 | I68: 7947 | J68: =IF(I68="","",I68-I67) -> 10 | K68: =IF(I68="","",J68*1000) -> 10000
B69: 46052 | C69: 1603 | D69: =IF(C69="","",C69-C68) -> 12 | E69: =IF(C69="","",D69*1000) -> 12000 | F69: 66玉補充した | H69: =IF(B69="","",B69) -> 46052 | I69: 7947 | J69: =IF(I69="","",I69-I68) -> 0 | K69: =IF(I69="","",J69*1000) -> 0
B70: 46055 | C70: 1628 | D70: =IF(C70="","",C70-C69) -> 25 | E70: =IF(C70="","",D70*1000) -> 25000 | H70: =IF(B70="","",B70) -> 46055 | I70: 7955 | J70: =IF(I70="","",I70-I69) -> 8 | K70: =IF(I70="","",J70*1000) -> 8000
B71: 46059 | C71: 1636 | D71: =IF(C71="","",C71-C70) -> 8 | E71: =IF(C71="","",D71*1000) -> 8000 | H71: =IF(B71="","",B71) -> 46059 | I71: 7961 | J71: =IF(I71="","",I71-I70) -> 6 | K71: =IF(I71="","",J71*1000) -> 6000
B72: 46062 | C72: 1647 | D72: =IF(C72="","",C72-C71) -> 11 | E72: =IF(C72="","",D72*1000) -> 11000 | H72: =IF(B72="","",B72) -> 46062 | I72: 7963 | J72: =IF(I72="","",I72-I71) -> 2 | K72: =IF(I72="","",J72*1000) -> 2000
D76: =IF(C76="","",C76-C75) | E76: =IF(C76="","",D76*1000) | H76: =IF(B76="","",B76) | J76: =IF(I76="","",I76-I75) | K76: =IF(I76="","",J76*1000)
D77: =IF(C77="","",C77-C74) | E77: =IF(C77="","",D77*1000) | H77: =IF(B77="","",B77) | J77: =IF(I77="","",I77-I74) | K77: =IF(I77="","",J77*1000)
D78: =SUM(D65:D77) -> 156 | E78: =SUM(E65:E77) -> 156000 | J78: =SUM(J65:J77) -> 50 | K78: =SUM(K65:K77) -> 50000
B80: 1000円ガチャ | H80: 2000円ガチャ
B81: 日付 | C81: 今回ﾒｰﾀｰ | D81: ﾒｰﾀｰ差 | E81: 売上 | F81: 備考 | H81: 日付 | I81: 今回ﾒｰﾀｰ | J81: ﾒｰﾀｰ差 | K81: 売上 | L81: 備考
B82: 46065 | C82: 1658 | D82: 11 | E82: 11000 | H82: 46065 | I82: 7967 | J82: 4 | K82: 4000
B83: 46069 | C83: 1671 | D83: =IF(C83="","",C83-C82) -> 13 | E83: =IF(C83="","",D83*1000) -> 13000 | H83: =IF(B83="","",B83) -> 46069 | I83: 7971 | J83: =IF(I83="","",I83-I82) -> 4 | K83: =IF(I83="","",J83*1000) -> 4000
B84: 46073 | C84: 1681 | D84: =IF(C84="","",C84-C83) -> 10 | E84: =IF(C84="","",D84*1000) -> 10000 | H84: =IF(B84="","",B84) -> 46073 | I84: 7985 | J84: =IF(I84="","",I84-I83) -> 14 | K84: =IF(I84="","",J84*1000) -> 14000
B85: 46083 | C85: 1711 | D85: =IF(C85="","",C85-C84) -> 30 | E85: =IF(C85="","",D85*1000) -> 30000 | H85: =IF(B85="","",B85) -> 46083 | I85: 8001 | J85: =IF(I85="","",I85-I84) -> 16 | K85: =IF(I85="","",J85*1000) -> 16000
B86: 46087 | C86: 1725 | D86: =IF(C86="","",C86-C85) -> 14 | E86: =IF(C86="","",D86*1000) -> 14000 | F86: 次玉補充！！！ | H86: =IF(B86="","",B86) -> 46087 | I86: 8003 | J86: =IF(I86="","",I86-I85) -> 2 | K86: =IF(I86="","",J86*1000) -> 2000
B87: 46090 | C87: 1740 | D87: =IF(C87="","",C87-C86) -> 15 | E87: =IF(C87="","",D87*1000) -> 15000 | F87: 次玉補充！！！ | H87: =IF(B87="","",B87) -> 46090 | I87: 8021 | J87: =IF(I87="","",I87-I86) -> 18 | K87: =IF(I87="","",J87*1000) -> 18000
H88: =IF(B88="","",B88) | J88: =IF(I88="","",I88-I87) | K88: =IF(I88="","",J88*1000)
H89: =IF(B89="","",B89) | J89: =IF(I89="","",I89-I88) | K89: =IF(I89="","",J89*1000)
D90: =IF(C90="","",C90-C89) | E90: =IF(C90="","",D90*1000) | H90: =IF(B90="","",B90) | J90: =IF(I90="","",I90-I89) | K90: =IF(I90="","",J90*1000)
D91: =IF(C91="","",C91-C90) | E91: =IF(C91="","",D91*1000) | H91: =IF(B91="","",B91) | J91: =IF(I91="","",I91-I90) | K91: =IF(I91="","",J91*1000)
D92: =IF(C92="","",C92-C91) | E92: =IF(C92="","",D92*1000) | H92: =IF(B92="","",B92) | J92: =IF(I92="","",I92-I91) | K92: =IF(I92="","",J92*1000)
D93: =IF(C93="","",C93-C92) | E93: =IF(C93="","",D93*1000) | H93: =IF(B93="","",B93) | J93: =IF(I93="","",I93-I92) | K93: =IF(I93="","",J93*1000)
D94: =IF(C94="","",C94-C91) | E94: =IF(C94="","",D94*1000) | H94: =IF(B94="","",B94) | J94: =IF(I94="","",I94-I91) | K94: =IF(I94="","",J94*1000)
D95: =SUM(D82:D94) -> 93 | E95: =SUM(E82:E94) -> 93000 | J95: =SUM(J82:J94) -> 58 | K95: =SUM(K82:K94) -> 58000
B97: 1000円ガチャ | H97: 2000円ガチャ
B98: 日付 | C98: 今回ﾒｰﾀｰ | D98: ﾒｰﾀｰ差 | E98: 売上 | F98: 備考 | H98: 日付 | I98: 今回ﾒｰﾀｰ | J98: ﾒｰﾀｰ差 | K98: 売上 | L98: 備考
B99: 46094 | C99: 1749 | D99: =IF(C99="","",C99-C87) -> 9 | E99: =IF(C99="","",D99*1000) -> 9000 | H99: 46065 | I99: 8031 | J99: 4 | K99: 4000
B100: 46097 | C100: 1762 | D100: =IF(C100="","",C100-C99) -> 13 | E100: =IF(C100="","",D100*1000) -> 13000 | H100: =IF(B100="","",B100) -> 46097 | I100: 8037 | J100: =IF(I100="","",I100-I99) -> 6 | K100: =IF(I100="","",J100*1000) -> 6000
B101: 46101 | C101: 1768 | D101: =IF(C101="","",C101-C100) -> 6 | E101: =IF(C101="","",D101*1000) -> 6000 | H101: =IF(B101="","",B101) -> 46101 | I101: 8041 | J101: =IF(I101="","",I101-I100) -> 4 | K101: =IF(I101="","",J101*1000) -> 4000
B102: 46104 | C102: 1776 | D102: =IF(C102="","",C102-C101) -> 8 | E102: =IF(C102="","",D102*1000) -> 8000 | F102: リセット済み | H102: =IF(B102="","",B102) -> 46104 | I102: 8045 | J102: =IF(I102="","",I102-I101) -> 4 | K102: =IF(I102="","",J102*1000) -> 4000
B103: 46108 | C103: 1782 | D103: =IF(C103="","",C103-C102) -> 6 | E103: =IF(C103="","",D103*1000) -> 6000 | H103: =IF(B103="","",B103) -> 46108 | I103: 8059 | J103: =IF(I103="","",I103-I102) -> 14 | K103: =IF(I103="","",J103*1000) -> 14000
B104: 46110 | C104: 1787 | D104: =IF(C104="","",C104-C103) -> 5 | E104: =IF(C104="","",D104*1000) -> 5000 | H104: =IF(B104="","",B104) -> 46110 | I104: 8067 | J104: =IF(I104="","",I104-I103) -> 8 | K104: =IF(I104="","",J104*1000) -> 8000
B105: 46115 | C105: 1789 | D105: =IF(C105="","",C105-C104) -> 2 | E105: =IF(C105="","",D105*1000) -> 2000 | H105: =IF(B105="","",B105) -> 46115 | I105: 8085 | J105: =IF(I105="","",I105-I104) -> 18 | K105: =IF(I105="","",J105*1000) -> 18000
B106: 46118 | C106: 1796 | D106: =IF(C106="","",C106-C105) -> 7 | E106: =IF(C106="","",D106*1000) -> 7000 | H106: =IF(B106="","",B106) -> 46118 | I106: 8093 | J106: =IF(I106="","",I106-I105) -> 8 | K106: =IF(I106="","",J106*1000) -> 8000
B107: 46121 | C107: 1805 | D107: =IF(C107="","",C107-C106) -> 9 | E107: =IF(C107="","",D107*1000) -> 9000 | H107: =IF(B107="","",B107) -> 46121 | I107: 8101 | J107: =IF(I107="","",I107-I106) -> 8 | K107: =IF(I107="","",J107*1000) -> 8000
D109: =IF(C109="","",C109-C108) | E109: =IF(C109="","",D109*1000) | H109: =IF(B109="","",B109) | J109: =IF(I109="","",I109-I108) | K109: =IF(I109="","",J109*1000)
D110: =IF(C110="","",C110-C109) | E110: =IF(C110="","",D110*1000) | H110: =IF(B110="","",B110) | J110: =IF(I110="","",I110-I109) | K110: =IF(I110="","",J110*1000)
...

Sheet 飯塚
B1: 2000円 | C1: 店番00309 | J1: 473.2 | M1: 1000円 | U1: 473.2 | X1: ティアラ2000円 | AF1: 473.2
B2: 日付 | C2: 前回ﾒｰﾀｰ | D2: 今回ﾒｰﾀｰ | E2: ﾒｰﾀｰ差 | F2: 売上 | G2: 立替金 | H2: 総売上 | I2: ＢＯＸ払出 | J2: ＣＰ払出 | K2: 備考 | M2: 日付 | N2: 前回ﾒｰﾀｰ | O2: 今回ﾒｰﾀｰ | P2: ﾒｰﾀｰ差 | Q2: 売上 | R2: 立替金 | S2: 総売上 | T2: ＢＯＸ払出 | U2: ＣＰ払出 | V2: 備考 | X2: 日付 | Y2: 前回ﾒｰﾀｰ | Z2: 今回ﾒｰﾀｰ | AA2: ﾒｰﾀｰ差 | AB2: 売上 | AC2: 立替金 | AD2: 総売上 | AE2: ＢＯＸ払出 | AF2: ＣＰ払出 | AG2: 備考
B3: 45922 | C3: 17177 | D3: 17185 | E3: =+D3-C3 -> 8 | F3: =+E3*1000 -> 8000 | G3: 0 | H3: =+F3-G3 -> 8000 | J3: =E3*#REF!/2 -> #REF! | M3: 45922 | N3: 2808 | O3: 2831 | P3: =+O3-N3 -> 23 | Q3: =+P3*1000 -> 23000 | R3: 0 | S3: =+Q3-R3 -> 23000 | U3: =P3*#REF!/2 -> #REF! | X3: 45922 | Y3: 7086 | Z3: 7104 | AA3: =+Z3-Y3 -> 18 | AB3: =+AA3*1000 -> 18000 | AC3: 0 | AD3: =+AB3-AC3 -> 18000 | AF3: =AA3*#REF!/2 -> #REF!
B4: 45926 | C4: 17185 | D4: 17209 | E4: =+D4-C4 -> 24 | F4: =+E4*1000 -> 24000 | G4: 0 | H4: =+F4-G4 -> 24000 | J4: =E4*#REF!/2 -> #REF! | M4: 45926 | N4: 2831 | O4: 2880 | P4: =+O4-N4 -> 49 | Q4: =+P4*1000 -> 49000 | R4: 0 | S4: =+Q4-R4 -> 49000 | U4: =P4*#REF!/2 -> #REF! | X4: 45926 | Y4: 7104 | Z4: 7134 | AA4: =+Z4-Y4 -> 30 | AB4: =+AA4*1000 -> 30000 | AC4: 0 | AD4: =+AB4-AC4 -> 30000 | AF4: =AA4*#REF!/2 -> #REF!
B5: 45929 | C5: 17209 | D5: 17237 | E5: =+D5-C5 -> 28 | F5: =+E5*1000 -> 28000 | G5: 0 | H5: =+F5-G5 -> 28000 | J5: =E5*#REF!/2 -> #REF! | M5: 45929 | N5: 2880 | O5: 2930 | P5: =+O5-N5 -> 50 | Q5: =+P5*1000 -> 50000 | R5: 0 | S5: =+Q5-R5 -> 50000 | U5: =P5*#REF!/2 -> #REF! | X5: 45929 | Y5: 7134 | Z5: 7148 | AA5: =+Z5-Y5 -> 14 | AB5: =+AA5*1000 -> 14000 | AC5: 0 | AD5: =+AB5-AC5 -> 14000 | AF5: =AA5*#REF!/2 -> #REF!
B6: 45933 | C6: 17237 | D6: 17259 | E6: =+D6-C6 -> 22 | F6: =+E6*1000 -> 22000 | G6: 0 | H6: =+F6-G6 -> 22000 | J6: =E6*#REF!/2 -> #REF! | M6: 45933 | N6: 2930 | O6: 3056 | P6: =+O6-N6 -> 126 | Q6: =+P6*1000 -> 126000 | R6: 0 | S6: =+Q6-R6 -> 126000 | U6: =P6*#REF!/2 -> #REF! | X6: 45933 | Y6: 7148 | Z6: 7156 | AA6: =+Z6-Y6 -> 8 | AB6: =+AA6*1000 -> 8000 | AC6: 0 | AD6: =+AB6-AC6 -> 8000 | AF6: =AA6*#REF!/2 -> #REF!
B7: 45936 | C7: 17259 | D7: 17275 | E7: =+D7-C7 -> 16 | F7: =+E7*1000 -> 16000 | G7: 0 | H7: =+F7-G7 -> 16000 | J7: =E7*#REF!/2 -> #REF! | M7: 45936 | N7: 3056 | O7: 3073 | P7: =+O7-N7 -> 17 | Q7: =+P7*1000 -> 17000 | R7: 0 | S7: =+Q7-R7 -> 17000 | U7: =P7*#REF!/2 -> #REF! | X7: 45936 | Y7: 7156 | Z7: 7170 | AA7: =+Z7-Y7 -> 14 | AB7: =+AA7*1000 -> 14000 | AC7: 0 | AD7: =+AB7-AC7 -> 14000 | AF7: =AA7*#REF!/2 -> #REF!
B8: 45940 | C8: 17275 | D8: 17341 | E8: =+D8-C8 -> 66 | F8: =+E8*1000 -> 66000 | G8: 0 | H8: =+F8-G8 -> 66000 | J8: =E8*#REF!/2 -> #REF! | M8: 45940 | N8: 3073 | O8: 3086 | P8: =+O8-N8 -> 13 | Q8: =+P8*1000 -> 13000 | R8: 0 | S8: =+Q8-R8 -> 13000 | U8: =P8*#REF!/2 -> #REF! | X8: 45940 | Y8: 7170 | Z8: 7190 | AA8: =+Z8-Y8 -> 20 | AB8: =+AA8*1000 -> 20000 | AC8: 0 | AD8: =+AB8-AC8 -> 20000 | AF8: =AA8*#REF!/2 -> #REF!
B9: 45943 | C9: 17341 | D9: 17383 | E9: =+D9-C9 -> 42 | F9: =+E9*1000 -> 42000 | G9: 0 | H9: =+F9-G9 -> 42000 | J9: =E9*#REF!/2 -> #REF! | M9: 45943 | N9: 3086 | O9: 3099 | P9: =+O9-N9 -> 13 | Q9: =+P9*1000 -> 13000 | R9: 0 | S9: =+Q9-R9 -> 13000 | U9: =P9*#REF!/2 -> #REF! | X9: 45943 | Y9: 7190 | Z9: 7204 | AA9: =+Z9-Y9 -> 14 | AB9: =+AA9*1000 -> 14000 | AC9: 0 | AD9: =+AB9-AC9 -> 14000 | AF9: =AA9*#REF!/2 -> #REF!
B10: 45947 | C10: 17383 | D10: 17463 | E10: =+D10-C10 -> 80 | F10: =+E10*1000 -> 80000 | G10: 0 | H10: =+F10-G10 -> 80000 | J10: =E10*#REF!/2 -> #REF! | M10: 45947 | N10: 3099 | O10: 3129 | P10: =+O10-N10 -> 30 | Q10: =+P10*1000 -> 30000 | R10: 0 | S10: =+Q10-R10 -> 30000 | U10: =P10*#REF!/2 -> #REF! | X10: 45947 | Y10: 7204 | Z10: 7220 | AA10: =+Z10-Y10 -> 16 | AB10: =+AA10*1000 -> 16000 | AC10: 0 | AD10: =+AB10-AC10 -> 16000 | AF10: =AA10*#REF!/2 -> #REF!
B11: 45950 | C11: 17463 | D11: 17652 | E11: =+D11-C11 -> 189 | F11: =+E11*1000 -> 189000 | G11: 0 | H11: =+F11-G11 -> 189000 | J11: =E11*#REF!/2 -> #REF! | L11: 景品原価 | M11: 45950 | N11: 3129 | O11: 3192 | P11: =+O11-N11 -> 63 | Q11: =+P11*1000 -> 63000 | R11: 0 | S11: =+Q11-R11 -> 63000 | U11: =P11*#REF!/2 -> #REF! | W11: 景品原価 | X11: 45950 | Y11: 7220 | Z11: 7238 | AA11: =+Z11-Y11 -> 18 | AB11: =+AA11*1000 -> 18000 | AC11: 0 | AD11: =+AB11-AC11 -> 18000 | AF11: =AA11*#REF!/2 -> #REF! | AH11: 景品原価
E12: =+D12-C12 -> 0 | F12: =+E12*1000 -> 0 | G12: 0 | H12: =+F12-G12 -> 0 | J12: =E12*#REF!/2 -> #REF! | P12: =+O12-N12 -> 0 | Q12: =+P12*1000 -> 0 | R12: 0 | S12: =+Q12-R12 -> 0 | U12: =P12*#REF!/2 -> #REF! | AA12: =+Z12-Y12 -> 0 | AB12: =+AA12*1000 -> 0 | AC12: 0 | AD12: =+AB12-AC12 -> 0 | AF12: =AA12*#REF!/2 -> #REF!
E13: =+D13-C13 -> 0 | F13: =+E13*1000 -> 0 | G13: 0 | H13: =+F13-G13 -> 0 | J13: =E13*#REF!/2 -> #REF! | P13: =+O13-N13 -> 0 | Q13: =+P13*1000 -> 0 | R13: 0 | S13: =+Q13-R13 -> 0 | U13: =P13*#REF!/2 -> #REF! | AA13: =+Z13-Y13 -> 0 | AB13: =+AA13*1000 -> 0 | AC13: 0 | AD13: =+AB13-AC13 -> 0 | AF13: =AA13*#REF!/2 -> #REF!
E14: =+D14-C14 -> 0 | F14: =+E14*1000 -> 0 | G14: 0 | H14: =+F14-G14 -> 0 | J14: =E14*#REF!/2 -> #REF! | P14: =+O14-N14 -> 0 | Q14: =+P14*1000 -> 0 | R14: 0 | S14: =+Q14-R14 -> 0 | U14: =P14*#REF!/2 -> #REF! | AA14: =+Z14-Y14 -> 0 | AB14: =+AA14*1000 -> 0 | AC14: 0 | AD14: =+AB14-AC14 -> 0 | AF14: =AA14*#REF!/2 -> #REF!
E15: =+D15-C15 -> 0 | F15: =+E15*1000 -> 0 | G15: 0 | H15: =+F15-G15 -> 0 | J15: =E15*#REF!/2 -> #REF! | L15: 利益率 | P15: =+O15-N15 -> 0 | Q15: =+P15*1000 -> 0 | R15: 0 | S15: =+Q15-R15 -> 0 | U15: =P15*#REF!/2 -> #REF! | W15: 利益率 | AA15: =+Z15-Y15 -> 0 | AB15: =+AA15*1000 -> 0 | AC15: 0 | AD15: =+AB15-AC15 -> 0 | AF15: =AA15*#REF!/2 -> #REF! | AH15: 利益率
E16: =SUM(E3:E15) -> 475 | F16: =SUM(F3:F15) -> 475000 | G16: =SUM(G3:G15) -> 0 | H16: =SUM(H3:H15) -> 475000 | I16: =SUM(I3:I15) -> 0 | J16: =SUM(J3:J15) -> #REF! | K16: =+H16*0.6-G16-J16 -> #REF! | L16: =+K16/H16 -> #REF! | P16: =SUM(P3:P15) -> 384 | Q16: =SUM(Q3:Q15) -> 384000 | R16: =SUM(R3:R15) -> 0 | S16: =SUM(S3:S15) -> 384000 | T16: =SUM(T3:T15) -> 0 | U16: =SUM(U3:U15) -> #REF! | V16: =+S16*0.6-R16-U16 -> #REF! | W16: =+V16/S16 -> #REF! | AA16: =SUM(AA3:AA15) -> 152 | AB16: =SUM(AB3:AB15) -> 152000 | AC16: =SUM(AC3:AC15) -> 0 | AD16: =SUM(AD3:AD15) -> 152000 | AE16: =SUM(AE3:AE15) -> 0 | AF16: =SUM(AF3:AF15) -> #REF! | AG16: =+AD16*0.6-AC16-AF16 -> #REF! | AH16: =+AG16/AD16 -> #REF!
B18: 2000円 | C18: 店番00309 | J18: 473.2 | M18: 1000円 | U18: 473.2 | X18: ティアラ2000円 | AF18: 473.2
B19: 日付 | C19: 前回ﾒｰﾀｰ | D19: 今回ﾒｰﾀｰ | E19: ﾒｰﾀｰ差 | F19: 売上 | G19: 立替金 | H19: 総売上 | I19: ＢＯＸ払出 | J19: ＣＰ払出 | K19: 備考 | M19: 日付 | N19: 前回ﾒｰﾀｰ | O19: 今回ﾒｰﾀｰ | P19: ﾒｰﾀｰ差 | Q19: 売上 | R19: 立替金 | S19: 総売上 | T19: ＢＯＸ払出 | U19: ＣＰ払出 | V19: 備考 | X19: 日付 | Y19: 前回ﾒｰﾀｰ | Z19: 今回ﾒｰﾀｰ | AA19: ﾒｰﾀｰ差 | AB19: 売上 | AC19: 立替金 | AD19: 総売上 | AE19: ＢＯＸ払出 | AF19: ＣＰ払出 | AG19: 備考
B20: 45954 | C20: 17652 | D20: 17672 | E20: =+D20-C20 -> 20 | F20: =+E20*1000 -> 20000 | G20: 0 | H20: =+F20-G20 -> 20000 | J20: =E20*#REF!/2 -> #REF! | M20: 45954 | N20: 3192 | O20: 3200 | P20: =+O20-N20 -> 8 | Q20: =+P20*1000 -> 8000 | R20: 0 | S20: =+Q20-R20 -> 8000 | U20: =P20*#REF!/2 -> #REF! | X20: 45954 | Y20: 7238 | Z20: 7240 | AA20: =+Z20-Y20 -> 2 | AB20: =+AA20*1000 -> 2000 | AC20: 0 | AD20: =+AB20-AC20 -> 2000 | AF20: =AA20*#REF!/2 -> #REF!
B21: 45957 | C21: 17672 | D21: 17704 | E21: =+D21-C21 -> 32 | F21: =+E21*1000 -> 32000 | G21: 0 | H21: =+F21-G21 -> 32000 | J21: =E21*#REF!/2 -> #REF! | M21: 45957 | N21: 3200 | O21: 3235 | P21: =+O21-N21 -> 35 | Q21: =+P21*1000 -> 35000 | R21: 0 | S21: =+Q21-R21 -> 35000 | U21: =P21*#REF!/2 -> #REF! | X21: 45957 | Y21: 7240 | Z21: 7260 | AA21: =+Z21-Y21 -> 20 | AB21: =+AA21*1000 -> 20000 | AC21: 0 | AD21: =+AB21-AC21 -> 20000 | AF21: =AA21*#REF!/2 -> #REF!
B22: 45961 | C22: 17704 | D22: 17722 | E22: =+D22-C22 -> 18 | F22: =+E22*1000 -> 18000 | G22: 0 | H22: =+F22-G22 -> 18000 | J22: =E22*#REF!/2 -> #REF! | M22: 45961 | N22: 3235 | O22: 3240 | P22: =+O22-N22 -> 5 | Q22: =+P22*1000 -> 5000 | R22: 0 | S22: =+Q22-R22 -> 5000 | U22: =P22*#REF!/2 -> #REF! | X22: 45961 | Y22: 7260 | Z22: 7260 | AA22: =+Z22-Y22 -> 0 | AB22: =+AA22*1000 -> 0 | AC22: 0 | AD22: =+AB22-AC22 -> 0 | AF22: =AA22*#REF!/2 -> #REF!
B23: 45964 | C23: 17722 | D23: 17764 | E23: =+D23-C23 -> 42 | F23: =+E23*1000 -> 42000 | G23: 0 | H23: =+F23-G23 -> 42000 | J23: =E23*#REF!/2 -> #REF! | M23: 45964 | N23: 3240 | O23: 3254 | P23: =+O23-N23 -> 14 | Q23: =+P23*1000 -> 14000 | R23: 0 | S23: =+Q23-R23 -> 14000 | U23: =P23*#REF!/2 -> #REF! | X23: 45964 | Y23: 7260 | Z23: 7268 | AA23: =+Z23-Y23 -> 8 | AB23: =+AA23*1000 -> 8000 | AC23: 0 | AD23: =+AB23-AC23 -> 8000 | AF23: =AA23*#REF!/2 -> #REF!
B24: 45968 | C24: 17764 | D24: 17786 | E24: =+D24-C24 -> 22 | F24: =+E24*1000 -> 22000 | G24: 0 | H24: =+F24-G24 -> 22000 | J24: =E24*#REF!/2 -> #REF! | M24: 45968 | N24: 3254 | O24: 3282 | P24: =+O24-N24 -> 28 | Q24: =+P24*1000 -> 28000 | R24: 0 | S24: =+Q24-R24 -> 28000 | U24: =P24*#REF!/2 -> #REF! | X24: 45968 | Y24: 7268 | Z24: 7276 | AA24: =+Z24-Y24 -> 8 | AB24: =+AA24*1000 -> 8000 | AC24: 0 | AD24: =+AB24-AC24 -> 8000 | AF24: =AA24*#REF!/2 -> #REF!
B25: 45971 | C25: 17786 | D25: 17814 | E25: =+D25-C25 -> 28 | F25: =+E25*1000 -> 28000 | G25: 0 | H25: =+F25-G25 -> 28000 | J25: =E25*#REF!/2 -> #REF! | M25: 45971 | N25: 3282 | O25: 3293 | P25: =+O25-N25 -> 11 | Q25: =+P25*1000 -> 11000 | R25: 0 | S25: =+Q25-R25 -> 11000 | U25: =P25*#REF!/2 -> #REF! | X25: 45971 | Y25: 7276 | Z25: 7292 | AA25: =+Z25-Y25 -> 16 | AB25: =+AA25*1000 -> 16000 | AC25: 0 | AD25: =+AB25-AC25 -> 16000 | AF25: =AA25*#REF!/2 -> #REF!
B26: 45975 | C26: 17814 | D26: 17826 | E26: =+D26-C26 -> 12 | F26: =+E26*1000 -> 12000 | G26: 0 | H26: =+F26-G26 -> 12000 | J26: =E26*#REF!/2 -> #REF! | M26: 45975 | N26: 3293 | O26: 3297 | P26: =+O26-N26 -> 4 | Q26: =+P26*1000 -> 4000 | R26: 0 | S26: =+Q26-R26 -> 4000 | U26: =P26*#REF!/2 -> #REF! | X26: 45975 | Y26: 7292 | Z26: 7292 | AA26: =+Z26-Y26 -> 0 | AB26: =+AA26*1000 -> 0 | AC26: 0 | AD26: =+AB26-AC26 -> 0 | AF26: =AA26*#REF!/2 -> #REF!
B27: 45978 | C27: 17826 | D27: 17854 | E27: =+D27-C27 -> 28 | F27: =+E27*1000 -> 28000 | G27: 0 | H27: =+F27-G27 -> 28000 | J27: =E27*#REF!/2 -> #REF! | M27: 45978 | N27: 3297 | O27: 3305 | P27: =+O27-N27 -> 8 | Q27: =+P27*1000 -> 8000 | R27: 0 | S27: =+Q27-R27 -> 8000 | U27: =P27*#REF!/2 -> #REF! | X27: 45978 | Y27: 7292 | Z27: 7304 | AA27: =+Z27-Y27 -> 12 | AB27: =+AA27*1000 -> 12000 | AC27: 0 | AD27: =+AB27-AC27 -> 12000 | AF27: =AA27*#REF!/2 -> #REF!
B28: 45981 | C28: 17854 | D28: 17870 | E28: =+D28-C28 -> 16 | F28: =+E28*1000 -> 16000 | G28: 0 | H28: =+F28-G28 -> 16000 | J28: =E28*#REF!/2 -> #REF! | L28: 景品原価 | M28: 45981 | N28: 3305 | O28: 3307 | P28: =+O28-N28 -> 2 | Q28: =+P28*1000 -> 2000 | R28: 0 | S28: =+Q28-R28 -> 2000 | U28: =P28*#REF!/2 -> #REF! | W28: 景品原価 | X28: 45981 | Y28: 7304 | Z28: 7308 | AA28: =+Z28-Y28 -> 4 | AB28: =+AA28*1000 -> 4000 | AC28: 0 | AD28: =+AB28-AC28 -> 4000 | AF28: =AA28*#REF!/2 -> #REF! | AH28: 景品原価
E29: =+D29-C29 -> 0 | F29: =+E29*1000 -> 0 | G29: 0 | H29: =+F29-G29 -> 0 | J29: =E29*#REF!/2 -> #REF! | P29: =+O29-N29 -> 0 | Q29: =+P29*1000 -> 0 | R29: 0 | S29: =+Q29-R29 -> 0 | U29: =P29*#REF!/2 -> #REF! | AA29: =+Z29-Y29 -> 0 | AB29: =+AA29*1000 -> 0 | AC29: 0 | AD29: =+AB29-AC29 -> 0 | AF29: =AA29*#REF!/2 -> #REF!
E30: =+D30-C30 -> 0 | F30: =+E30*1000 -> 0 | G30: 0 | H30: =+F30-G30 -> 0 | J30: =E30*#REF!/2 -> #REF! | P30: =+O30-N30 -> 0 | Q30: =+P30*1000 -> 0 | R30: 0 | S30: =+Q30-R30 -> 0 | U30: =P30*#REF!/2 -> #REF! | AA30: =+Z30-Y30 -> 0 | AB30: =+AA30*1000 -> 0 | AC30: 0 | AD30: =+AB30-AC30 -> 0 | AF30: =AA30*#REF!/2 -> #REF!
E31: =+D31-C31 -> 0 | F31: =+E31*1000 -> 0 | G31: 0 | H31: =+F31-G31 -> 0 | J31: =E31*#REF!/2 -> #REF! | P31: =+O31-N31 -> 0 | Q31: =+P31*1000 -> 0 | R31: 0 | S31: =+Q31-R31 -> 0 | U31: =P31*#REF!/2 -> #REF! | AA31: =+Z31-Y31 -> 0 | AB31: =+AA31*1000 -> 0 | AC31: 0 | AD31: =+AB31-AC31 -> 0 | AF31: =AA31*#REF!/2 -> #REF!
E32: =+D32-C32 -> 0 | F32: =+E32*1000 -> 0 | G32: 0 | H32: =+F32-G32 -> 0 | J32: =E32*#REF!/2 -> #REF! | L32: 利益率 | P32: =+O32-N32 -> 0 | Q32: =+P32*1000 -> 0 | R32: 0 | S32: =+Q32-R32 -> 0 | U32: =P32*#REF!/2 -> #REF! | W32: 利益率 | AA32: =+Z32-Y32 -> 0 | AB32: =+AA32*1000 -> 0 | AC32: 0 | AD32: =+AB32-AC32 -> 0 | AF32: =AA32*#REF!/2 -> #REF! | AH32: 利益率
E33: =SUM(E20:E32) -> 218 | F33: =SUM(F20:F32) -> 218000 | G33: =SUM(G20:G32) -> 0 | H33: =SUM(H20:H32) -> 218000 | I33: =SUM(I20:I32) -> 0 | J33: =SUM(J20:J32) -> #REF! | K33: =+H33*0.6-G33-J33 -> #REF! | L33: =+K33/H33 -> #REF! | P33: =SUM(P20:P32) -> 115 | Q33: =SUM(Q20:Q32) -> 115000 | R33: =SUM(R20:R32) -> 0 | S33: =SUM(S20:S32) -> 115000 | T33: =SUM(T20:T32) -> 0 | U33: =SUM(U20:U32) -> #REF! | V33: =+S33*0.6-R33-U33 -> #REF! | W33: =+V33/S33 -> #REF! | AA33: =SUM(AA20:AA32) -> 70 | AB33: =SUM(AB20:AB32) -> 70000 | AC33: =SUM(AC20:AC32) -> 0 | AD33: =SUM(AD20:AD32) -> 70000 | AE33: =SUM(AE20:AE32) -> 0 | AF33: =SUM(AF20:AF32) -> #REF! | AG33: =+AD33*0.6-AC33-AF33 -> #REF! | AH33: =+AG33/AD33 -> #REF!
B35: 2000円 | C35: 店番00309 | J35: 473.2 | M35: 1000円 | U35: 473.2 | X35: ティアラ2000円 | AF35: 473.2
B36: 日付 | C36: 前回ﾒｰﾀｰ | D36: 今回ﾒｰﾀｰ | E36: ﾒｰﾀｰ差 | F36: 売上 | G36: 立替金 | H36: 総売上 | I36: ＢＯＸ払出 | J36: ＣＰ払出 | K36: 備考 | M36: 日付 | N36: 前回ﾒｰﾀｰ | O36: 今回ﾒｰﾀｰ | P36: ﾒｰﾀｰ差 | Q36: 売上 | R36: 立替金 | S36: 総売上 | T36: ＢＯＸ払出 | U36: ＣＰ払出 | V36: 備考 | X36: 日付 | Y36: 前回ﾒｰﾀｰ | Z36: 今回ﾒｰﾀｰ | AA36: ﾒｰﾀｰ差 | AB36: 売上 | AC36: 立替金 | AD36: 総売上 | AE36: ＢＯＸ払出 | AF36: ＣＰ払出 | AG36: 備考
B37: 45985 | C37: 17870 | D37: 17908 | E37: =+D37-C37 -> 38 | F37: =+E37*1000 -> 38000 | G37: 0 | H37: =+F37-G37 -> 38000 | J37: =E37*#REF!/2 -> #REF! | M37: 45985 | N37: 3307 | O37: 3326 | P37: =+O37-N37 -> 19 | Q37: =+P37*1000 -> 19000 | R37: 0 | S37: =+Q37-R37 -> 19000 | U37: =P37*#REF!/2 -> #REF! | X37: 45985 | Y37: 7308 | Z37: 7318 | AA37: =+Z37-Y37 -> 10 | AB37: =+AA37*1000 -> 10000 | AC37: 0 | AD37: =+AB37-AC37 -> 10000 | AF37: =AA37*#REF!/2 -> #REF!
B38: 45989 | C38: 17908 | D38: 17962 | E38: =+D38-C38 -> 54 | F38: =+E38*1000 -> 54000 | G38: 0 | H38: =+F38-G38 -> 54000 | J38: =E38*#REF!/2 -> #REF! | M38: 45989 | N38: 3326 | O38: 3343 | P38: =+O38-N38 -> 17 | Q38: =+P38*1000 -> 17000 | R38: 0 | S38: =+Q38-R38 -> 17000 | U38: =P38*#REF!/2 -> #REF! | X38: 45989 | Y38: 7318 | Z38: 7342 | AA38: =+Z38-Y38 -> 24 | AB38: =+AA38*1000 -> 24000 | AC38: 0 | AD38: =+AB38-AC38 -> 24000 | AF38: =AA38*#REF!/2 -> #REF!
B39: 45993 | C39: 17962 | D39: 17992 | E39: =+D39-C39 -> 30 | F39: =+E39*1000 -> 30000 | G39: 0 | H39: =+F39-G39 -> 30000 | J39: =E39*#REF!/2 -> #REF! | M39: 45992 | N39: 3343 | O39: 3359 | P39: =+O39-N39 -> 16 | Q39: =+P39*1000 -> 16000 | R39: 0 | S39: =+Q39-R39 -> 16000 | U39: =P39*#REF!/2 -> #REF! | X39: 45992 | Y39: 7342 | Z39: 7350 | AA39: =+Z39-Y39 -> 8 | AB39: =+AA39*1000 -> 8000 | AC39: 0 | AD39: =+AB39-AC39 -> 8000 | AF39: =AA39*#REF!/2 -> #REF!
B40: 45996 | C40: 17992 | D40: 18004 | E40: =+D40-C40 -> 12 | F40: =+E40*1000 -> 12000 | G40: 0 | H40: =+F40-G40 -> 12000 | J40: =E40*#REF!/2 -> #REF! | M40: 45996 | N40: 3359 | O40: 3368 | P40: =+O40-N40 -> 9 | Q40: =+P40*1000 -> 9000 | R40: 0 | S40: =+Q40-R40 -> 9000 | U40: =P40*#REF!/2 -> #REF! | X40: 45996 | Y40: 7350 | Z40: 7356 | AA40: =+Z40-Y40 -> 6 | AB40: =+AA40*1000 -> 6000 | AC40: 0 | AD40: =+AB40-AC40 -> 6000 | AF40: =AA40*#REF!/2 -> #REF!
B41: 45999 | C41: 18004 | D41: 18024 | E41: =+D41-C41 -> 20 | F41: =+E41*1000 -> 20000 | G41: 0 | H41: =+F41-G41 -> 20000 | J41: =E41*#REF!/2 -> #REF! | M41: 45999 | N41: 3368 | O41: 3390 | P41: =+O41-N41 -> 22 | Q41: =+P41*1000 -> 22000 | R41: 0 | S41: =+Q41-R41 -> 22000 | U41: =P41*#REF!/2 -> #REF! | X41: 45999 | Y41: 7356 | Z41: 7362 | AA41: =+Z41-Y41 -> 6 | AB41: =+AA41*1000 -> 6000 | AC41: 0 | AD41: =+AB41-AC41 -> 6000 | AF41: =AA41*#REF!/2 -> #REF!
B42: 46003 | C42: 18024 | D42: 18046 | E42: =+D42-C42 -> 22 | F42: =+E42*1000 -> 22000 | G42: 0 | H42: =+F42-G42 -> 22000 | J42: =E42*#REF!/2 -> #REF! | M42: 46003 | N42: 3390 | O42: 3403 | P42: =+O42-N42 -> 13 | Q42: =+P42*1000 -> 13000 | R42: 0 | S42: =+Q42-R42 -> 13000 | U42: =P42*#REF!/2 -> #REF! | X42: 46003 | Y42: 7362 | Z42: 7364 | AA42: =+Z42-Y42 -> 2 | AB42: =+AA42*1000 -> 2000 | AC42: 0 | AD42: =+AB42-AC42 -> 2000 | AF42: =AA42*#REF!/2 -> #REF!
B43: 46006 | C43: 18046 | D43: 18084 | E43: =+D43-C43 -> 38 | F43: =+E43*1000 -> 38000 | G43: 0 | H43: =+F43-G43 -> 38000 | J43: =E43*#REF!/2 -> #REF! | M43: 46006 | N43: 3403 | O43: 3416 | P43: =+O43-N43 -> 13 | Q43: =+P43*1000 -> 13000 | R43: 0 | S43: =+Q43-R43 -> 13000 | U43: =P43*#REF!/2 -> #REF! | X43: 46006 | Y43: 7364 | Z43: 7372 | AA43: =+Z43-Y43 -> 8 | AB43: =+AA43*1000 -> 8000 | AC43: 0 | AD43: =+AB43-AC43 -> 8000 | AF43: =AA43*#REF!/2 -> #REF!
B44: 46010 | C44: 18084 | D44: 18102 | E44: =+D44-C44 -> 18 | F44: =+E44*1000 -> 18000 | G44: 0 | H44: =+F44-G44 -> 18000 | J44: =E44*#REF!/2 -> #REF! | M44: 46010 | N44: 3416 | O44: 3425 | P44: =+O44-N44 -> 9 | Q44: =+P44*1000 -> 9000 | R44: 0 | S44: =+Q44-R44 -> 9000 | U44: =P44*#REF!/2 -> #REF! | X44: 46010 | Y44: 7372 | Z44: 7414 | AA44: =+Z44-Y44 -> 42 | AB44: =+AA44*1000 -> 42000 | AC44: 0 | AD44: =+AB44-AC44 -> 42000 | AF44: =AA44*#REF!/2 -> #REF!
E45: =+D45-C45 -> 0 | F45: =+E45*1000 -> 0 | G45: 0 | H45: =+F45-G45 -> 0 | J45: =E45*#REF!/2 -> #REF! | L45: 景品原価 | P45: =+O45-N45 -> 0 | Q45: =+P45*1000 -> 0 | R45: 0 | S45: =+Q45-R45 -> 0 | U45: =P45*#REF!/2 -> #REF! | W45: 景品原価 | AA45: =+Z45-Y45 -> 0 | AB45: =+AA45*1000 -> 0 | AC45: 0 | AD45: =+AB45-AC45 -> 0 | AF45: =AA45*#REF!/2 -> #REF! | AH45: 景品原価
E46: =+D46-C46 -> 0 | F46: =+E46*1000 -> 0 | G46: 0 | H46: =+F46-G46 -> 0 | J46: =E46*#REF!/2 -> #REF! | P46: =+O46-N46 -> 0 | Q46: =+P46*1000 -> 0 | R46: 0 | S46: =+Q46-R46 -> 0 | U46: =P46*#REF!/2 -> #REF! | AA46: =+Z46-Y46 -> 0 | AB46: =+AA46*1000 -> 0 | AC46: 0 | AD46: =+AB46-AC46 -> 0 | AF46: =AA46*#REF!/2 -> #REF!
E47: =+D47-C47 -> 0 | F47: =+E47*1000 -> 0 | G47: 0 | H47: =+F47-G47 -> 0 | J47: =E47*#REF!/2 -> #REF! | P47: =+O47-N47 -> 0 | Q47: =+P47*1000 -> 0 | R47: 0 | S47: =+Q47-R47 -> 0 | U47: =P47*#REF!/2 -> #REF! | AA47: =+Z47-Y47 -> 0 | AB47: =+AA47*1000 -> 0 | AC47: 0 | AD47: =+AB47-AC47 -> 0 | AF47: =AA47*#REF!/2 -> #REF!
E48: =+D48-C48 -> 0 | F48: =+E48*1000 -> 0 | G48: 0 | H48: =+F48-G48 -> 0 | J48: =E48*#REF!/2 -> #REF! | P48: =+O48-N48 -> 0 | Q48: =+P48*1000 -> 0 | R48: 0 | S48: =+Q48-R48 -> 0 | U48: =P48*#REF!/2 -> #REF! | AA48: =+Z48-Y48 -> 0 | AB48: =+AA48*1000 -> 0 | AC48: 0 | AD48: =+AB48-AC48 -> 0 | AF48: =AA48*#REF!/2 -> #REF!
E49: =+D49-C49 -> 0 | F49: =+E49*1000 -> 0 | G49: 0 | H49: =+F49-G49 -> 0 | J49: =E49*#REF!/2 -> #REF! | L49: 利益率 | P49: =+O49-N49 -> 0 | Q49: =+P49*1000 -> 0 | R49: 0 | S49: =+Q49-R49 -> 0 | U49: =P49*#REF!/2 -> #REF! | W49: 利益率 | AA49: =+Z49-Y49 -> 0 | AB49: =+AA49*1000 -> 0 | AC49: 0 | AD49: =+AB49-AC49 -> 0 | AF49: =AA49*#REF!/2 -> #REF! | AH49: 利益率
E50: =SUM(E37:E49) -> 232 | F50: =SUM(F37:F49) -> 232000 | G50: =SUM(G37:G49) -> 0 | H50: =SUM(H37:H49) -> 232000 | I50: =SUM(I37:I49) -> 0 | J50: =SUM(J37:J49) -> #REF! | K50: =+H50*0.6-G50-J50 -> #REF! | L50: =+K50/H50 -> #REF! | P50: =SUM(P37:P49) -> 118 | Q50: =SUM(Q37:Q49) -> 118000 | R50: =SUM(R37:R49) -> 0 | S50: =SUM(S37:S49) -> 118000 | T50: =SUM(T37:T49) -> 0 | U50: =SUM(U37:U49) -> #REF! | V50: =+S50*0.6-R50-U50 -> #REF! | W50: =+V50/S50 -> #REF! | AA50: =SUM(AA37:AA49) -> 106 | AB50: =SUM(AB37:AB49) -> 106000 | AC50: =SUM(AC37:AC49) -> 0 | AD50: =SUM(AD37:AD49) -> 106000 | AE50: =SUM(AE37:AE49) -> 0 | AF50: =SUM(AF37:AF49) -> #REF! | AG50: =+AD50*0.6-AC50-AF50 -> #REF! | AH50: =+AG50/AD50 -> #REF!
B52: 2000円 | C52: 店番00309 | J52: 473.2 | M52: 1000円 | U52: 473.2 | X52: ティアラ2000円 | AF52: 473.2
B53: 日付 | C53: 前回ﾒｰﾀｰ | D53: 今回ﾒｰﾀｰ | E53: ﾒｰﾀｰ差 | F53: 売上 | G53: 立替金 | H53: 総売上 | I53: ＢＯＸ払出 | J53: ＣＰ払出 | K53: 備考 | M53: 日付 | N53: 前回ﾒｰﾀｰ | O53: 今回ﾒｰﾀｰ | P53: ﾒｰﾀｰ差 | Q53: 売上 | R53: 立替金 | S53: 総売上 | T53: ＢＯＸ払出 | U53: ＣＰ払出 | V53: 備考 | X53: 日付 | Y53: 前回ﾒｰﾀｰ | Z53: 今回ﾒｰﾀｰ | AA53: ﾒｰﾀｰ差 | AB53: 売上 | AC53: 立替金 | AD53: 総売上 | AE53: ＢＯＸ払出 | AF53: ＣＰ払出 | AG53: 備考
B54: 46013 | C54: 18102 | D54: 18122 | E54: =+D54-C54 -> 20 | F54: =+E54*1000 -> 20000 | G54: 0 | H54: =+F54-G54 -> 20000 | J54: =E54*#REF!/2 -> #REF! | M54: 46013 | N54: 3425 | O54: 3439 | P54: =+O54-N54 -> 14 | Q54: =+P54*1000 -> 14000 | R54: 0 | S54: =+Q54-R54 -> 14000 | U54: =P54*#REF!/2 -> #REF! | X54: 46013 | Y54: 7414 | Z54: 7448 | AA54: =+Z54-Y54 -> 34 | AB54: =+AA54*1000 -> 34000 | AC54: 0 | AD54: =+AB54-AC54 -> 34000 | AF54: =AA54*#REF!/2 -> #REF!
B55: 46017 | C55: 18122 | D55: 18178 | E55: =+D55-C55 -> 56 | F55: =+E55*1000 -> 56000 | G55: 0 | H55: =+F55-G55 -> 56000 | J55: =E55*#REF!/2 -> #REF! | M55: 46017 | N55: 3439 | O55: 3461 | P55: =+O55-N55 -> 22 | Q55: =+P55*1000 -> 22000 | R55: 0 | S55: =+Q55-R55 -> 22000 | U55: =P55*#REF!/2 -> #REF! | X55: 46017 | Y55: 7448 | Z55: 7454 | AA55: =+Z55-Y55 -> 6 | AB55: =+AA55*1000 -> 6000 | AC55: 0 | AD55: =+AB55-AC55 -> 6000 | AF55: =AA55*#REF!/2 -> #REF!
B56: 46020 | C56: 18178 | D56: 18212 | E56: =+D56-C56 -> 34 | F56: =+E56*1000 -> 34000 | G56: 0 | H56: =+F56-G56 -> 34000 | J56: =E56*#REF!/2 -> #REF! | M56: 46020 | N56: 3461 | O56: 3476 | P56: =+O56-N56 -> 15 | Q56: =+P56*1000 -> 15000 | R56: 0 | S56: =+Q56-R56 -> 15000 | U56: =P56*#REF!/2 -> #REF! | X56: 46020 | Y56: 7454 | Z56: 7464 | AA56: =+Z56-Y56 -> 10 | AB56: =+AA56*1000 -> 10000 | AC56: 0 | AD56: =+AB56-AC56 -> 10000 | AF56: =AA56*#REF!/2 -> #REF!
B57: 46024 | C57: 18212 | D57: 18348 | E57: =+D57-C57 -> 136 | F57: =+E57*1000 -> 136000 | G57: 0 | H57: =+F57-G57 -> 136000 | J57: =E57*#REF!/2 -> #REF! | M57: 46024 | N57: 3476 | O57: 3543 | P57: =+O57-N57 -> 67 | Q57: =+P57*1000 -> 67000 | R57: 0 | S57: =+Q57-R57 -> 67000 | U57: =P57*#REF!/2 -> #REF! | X57: 46024 | Y57: 7464 | Z57: 7504 | AA57: =+Z57-Y57 -> 40 | AB57: =+AA57*1000 -> 40000 | AC57: 0 | AD57: =+AB57-AC57 -> 40000 | AF57: =AA57*#REF!/2 -> #REF!
B58: 46027 | C58: 18348 | D58: 18420 | E58: =+D58-C58 -> 72 | F58: =+E58*1000 -> 72000 | G58: 0 | H58: =+F58-G58 -> 72000 | J58: =E58*#REF!/2 -> #REF! | M58: 46027 | N58: 3543 | O58: 3618 | P58: =+O58-N58 -> 75 | Q58: =+P58*1000 -> 75000 | R58: 0 | S58: =+Q58-R58 -> 75000 | U58: =P58*#REF!/2 -> #REF! | X58: 46027 | Y58: 7504 | Z58: 7530 | AA58: =+Z58-Y58 -> 26 | AB58: =+AA58*1000 -> 26000 | AC58: 0 | AD58: =+AB58-AC58 -> 26000 | AF58: =AA58*#REF!/2 -> #REF!
B59: 46031 | C59: 18420 | D59: 18438 | E59: =+D59-C59 -> 18 | F59: =+E59*1000 -> 18000 | G59: 0 | H59: =+F59-G59 -> 18000 | J59: =E59*#REF!/2 -> #REF! | M59: 46031 | N59: 3618 | O59: 3696 | P59: =+O59-N59 -> 78 | Q59: =+P59*1000 -> 78000 | R59: 0 | S59: =+Q59-R59 -> 78000 | U59: =P59*#REF!/2 -> #REF! | X59: 46031 | Y59: 7530 | Z59: 7540 | AA59: =+Z59-Y59 -> 10 | AB59: =+AA59*1000 -> 10000 | AC59: 0 | AD59: =+AB59-AC59 -> 10000 | AF59: =AA59*#REF!/2 -> #REF!
B60: 46034 | C60: 18438 | D60: 18474 | E60: =+D60-C60 -> 36 | F60: =+E60*1000 -> 36000 | G60: 0 | H60: =+F60-G60 -> 36000 | J60: =E60*#REF!/2 -> #REF! | M60: 46034 | N60: 3696 | O60: 3727 | P60: =+O60-N60 -> 31 | Q60: =+P60*1000 -> 31000 | R60: 0 | S60: =+Q60-R60 -> 31000 | U60: =P60*#REF!/2 -> #REF! | X60: 46034 | Y60: 7540 | Z60: 7548 | AA60: =+Z60-Y60 -> 8 | AB60: =+AA60*1000 -> 8000 | AC60: 0 | AD60: =+AB60-AC60 -> 8000 | AF60: =AA60*#REF!/2 -> #REF!
B61: 46038 | C61: 18474 | D61: 18502 | E61: =+D61-C61 -> 28 | F61: =+E61*1000 -> 28000 | G61: 0 | H61: =+F61-G61 -> 28000 | J61: =E61*#REF!/2 -> #REF! | M61: 46038 | N61: 3727 | O61: 3740 | P61: =+O61-N61 -> 13 | Q61: =+P61*1000 -> 13000 | R61: 0 | S61: =+Q61-R61 -> 13000 | U61: =P61*#REF!/2 -> #REF! | X61: 46038 | Y61: 7548 | Z61: 7554 | AA61: =+Z61-Y61 -> 6 | AB61: =+AA61*1000 -> 6000 | AC61: 0 | AD61: =+AB61-AC61 -> 6000 | AF61: =AA61*#REF!/2 -> #REF!
B62: 46042 | C62: 18502 | D62: 18552 | E62: =+D62-C62 -> 50 | F62: =+E62*1000 -> 50000 | G62: 0 | H62: =+F62-G62 -> 50000 | J62: =E62*#REF!/2 -> #REF! | L62: 景品原価 | M62: 46042 | N62: 3740 | O62: 3777 | P62: =+O62-N62 -> 37 | Q62: =+P62*1000 -> 37000 | R62: 0 | S62: =+Q62-R62 -> 37000 | U62: =P62*#REF!/2 -> #REF! | W62: 景品原価 | X62: 46042 | Y62: 7554 | Z62: 7566 | AA62: =+Z62-Y62 -> 12 | AB62: =+AA62*1000 -> 12000 | AC62: 0 | AD62: =+AB62-AC62 -> 12000 | AF62: =AA62*#REF!/2 -> #REF! | AH62: 景品原価
E63: =+D63-C63 -> 0 | F63: =+E63*1000 -> 0 | G63: 0 | H63: =+F63-G63 -> 0 | J63: =E63*#REF!/2 -> #REF! | P63: =+O63-N63 -> 0 | Q63: =+P63*1000 -> 0 | R63: 0 | S63: =+Q63-R63 -> 0 | U63: =P63*#REF!/2 -> #REF! | AA63: =+Z63-Y63 -> 0 | AB63: =+AA63*1000 -> 0 | AC63: 0 | AD63: =+AB63-AC63 -> 0 | AF63: =AA63*#REF!/2 -> #REF!
E64: =+D64-C64 -> 0 | F64: =+E64*1000 -> 0 | G64: 0 | H64: =+F64-G64 -> 0 | J64: =E64*#REF!/2 -> #REF! | P64: =+O64-N64 -> 0 | Q64: =+P64*1000 -> 0 | R64: 0 | S64: =+Q64-R64 -> 0 | U64: =P64*#REF!/2 -> #REF! | AA64: =+Z64-Y64 -> 0 | AB64: =+AA64*1000 -> 0 | AC64: 0 | AD64: =+AB64-AC64 -> 0 | AF64: =AA64*#REF!/2 -> #REF!
E65: =+D65-C65 -> 0 | F65: =+E65*1000 -> 0 | G65: 0 | H65: =+F65-G65 -> 0 | J65: =E65*#REF!/2 -> #REF! | P65: =+O65-N65 -> 0 | Q65: =+P65*1000 -> 0 | R65: 0 | S65: =+Q65-R65 -> 0 | U65: =P65*#REF!/2 -> #REF! | AA65: =+Z65-Y65 -> 0 | AB65: =+AA65*1000 -> 0 | AC65: 0 | AD65: =+AB65-AC65 -> 0 | AF65: =AA65*#REF!/2 -> #REF!
E66: =+D66-C66 -> 0 | F66: =+E66*1000 -> 0 | G66: 0 | H66: =+F66-G66 -> 0 | J66: =E66*#REF!/2 -> #REF! | L66: 利益率 | P66: =+O66-N66 -> 0 | Q66: =+P66*1000 -> 0 | R66: 0 | S66: =+Q66-R66 -> 0 | U66: =P66*#REF!/2 -> #REF! | W66: 利益率 | AA66: =+Z66-Y66 -> 0 | AB66: =+AA66*1000 -> 0 | AC66: 0 | AD66: =+AB66-AC66 -> 0 | AF66: =AA66*#REF!/2 -> #REF! | AH66: 利益率
E67: =SUM(E54:E66) -> 450 | F67: =SUM(F54:F66) -> 450000 | G67: =SUM(G54:G66) -> 0 | H67: =SUM(H54:H66) -> 450000 | I67: =SUM(I54:I66) -> 0 | J67: =SUM(J54:J66) -> #REF! | K67: =+H67*0.6-G67-J67 -> #REF! | L67: =+K67/H67 -> #REF! | P67: =SUM(P54:P66) -> 352 | Q67: =SUM(Q54:Q66) -> 352000 | R67: =SUM(R54:R66) -> 0 | S67: =SUM(S54:S66) -> 352000 | T67: =SUM(T54:T66) -> 0 | U67: =SUM(U54:U66) -> #REF! | V67: =+S67*0.6-R67-U67 -> #REF! | W67: =+V67/S67 -> #REF! | AA67: =SUM(AA54:AA66) -> 152 | AB67: =SUM(AB54:AB66) -> 152000 | AC67: =SUM(AC54:AC66) -> 0 | AD67: =SUM(AD54:AD66) -> 152000 | AE67: =SUM(AE54:AE66) -> 0 | AF67: =SUM(AF54:AF66) -> #REF! | AG67: =+AD67*0.6-AC67-AF67 -> #REF! | AH67: =+AG67/AD67 -> #REF!
B69: 2000円 | C69: 店番00309 | J69: 473.2 | M69: 1000円 | U69: 473.2 | X69: ティアラ2000円 | AF69: 473.2
B70: 日付 | C70: 前回ﾒｰﾀｰ | D70: 今回ﾒｰﾀｰ | E70: ﾒｰﾀｰ差 | F70: 売上 | G70: 立替金 | H70: 総売上 | I70: ＢＯＸ払出 | J70: ＣＰ払出 | K70: 備考 | M70: 日付 | N70: 前回ﾒｰﾀｰ | O70: 今回ﾒｰﾀｰ | P70: ﾒｰﾀｰ差 | Q70: 売上 | R70: 立替金 | S70: 総売上 | T70: ＢＯＸ払出 | U70: ＣＰ払出 | V70: 備考 | X70: 日付 | Y70: 前回ﾒｰﾀｰ | Z70: 今回ﾒｰﾀｰ | AA70: ﾒｰﾀｰ差 | AB70: 売上 | AC70: 立替金 | AD70: 総売上 | AE70: ＢＯＸ払出 | AF70: ＣＰ払出 | AG70: 備考
B71: 46045 | C71: 18552 | D71: 18580 | E71: =+D71-C71 -> 28 | F71: =+E71*1000 -> 28000 | G71: 0 | H71: =+F71-G71 -> 28000 | J71: =E71*#REF!/2 -> #REF! | M71: 46045 | N71: 3777 | O71: 3796 | P71: =+O71-N71 -> 19 | Q71: =+P71*1000 -> 19000 | R71: 0 | S71: =+Q71-R71 -> 19000 | U71: =P71*#REF!/2 -> #REF! | X71: 46045 | Y71: 7566 | Z71: 7570 | AA71: =+Z71-Y71 -> 4 | AB71: =+AA71*1000 -> 4000 | AC71: 0 | AD71: =+AB71-AC71 -> 4000 | AF71: =AA71*#REF!/2 -> #REF!
B72: 46048 | C72: 18580 | D72: 18624 | E72: =+D72-C72 -> 44 | F72: =+E72*1000 -> 44000 | G72: 0 | H72: =+F72-G72 -> 44000 | J72: =E72*#REF!/2 -> #REF! | M72: 46048 | N72: 3796 | O72: 3841 | P72: =+O72-N72 -> 45 | Q72: =+P72*1000 -> 45000 | R72: 0 | S72: =+Q72-R72 -> 45000 | U72: =P72*#REF!/2 -> #REF! | X72: 46048 | Y72: 7570 | Z72: 7572 | AA72: =+Z72-Y72 -> 2 | AB72: =+AA72*1000 -> 2000 | AC72: 0 | AD72: =+AB72-AC72 -> 2000 | AF72: =AA72*#REF!/2 -> #REF!
B73: 46052 | C73: 18624 | D73: 18662 | E73: =+D73-C73 -> 38 | F73: =+E73*1000 -> 38000 | G73: 0 | H73: =+F73-G73 -> 38000 | J73: =E73*#REF!/2 -> #REF! | M73: 46052 | N73: 3841 | O73: 3864 | P73: =+O73-N73 -> 23 | Q73: =+P73*1000 -> 23000 | R73: 0 | S73: =+Q73-R73 -> 23000 | U73: =P73*#REF!/2 -> #REF! | X73: 46052 | Y73: 7572 | Z73: 7578 | AA73: =+Z73-Y73 -> 6 | AB73: =+AA73*1000 -> 6000 | AC73: 0 | AD73: =+AB73-AC73 -> 6000 | AF73: =AA73*#REF!/2 -> #REF!
B74: 46062 | C74: 18662 | D74: 18700 | E74: =+D74-C74 -> 38 | F74: =+E74*1000 -> 38000 | G74: 0 | H74: =+F74-G74 -> 38000 | J74: =E74*#REF!/2 -> #REF! | M74: 46062 | N74: 3864 | O74: 3932 | P74: =+O74-N74 -> 68 | Q74: =+P74*1000 -> 68000 | R74: 0 | S74: =+Q74-R74 -> 68000 | U74: =P74*#REF!/2 -> #REF! | X74: 46062 | Y74: 7578 | Z74: 7594 | AA74: =+Z74-Y74 -> 16 | AB74: =+AA74*1000 -> 16000 | AC74: 0 | AD74: =+AB74-AC74 -> 16000 | AF74: =AA74*#REF!/2 -> #REF!
B75: 46066 | C75: 18700 | D75: 18738 | E75: =+D75-C75 -> 38 | F75: =+E75*1000 -> 38000 | G75: 0 | H75: =+F75-G75 -> 38000 | J75: =E75*#REF!/2 -> #REF! | M75: 46066 | N75: 3932 | O75: 3962 | P75: =+O75-N75 -> 30 | Q75: =+P75*1000 -> 30000 | R75: 0 | S75: =+Q75-R75 -> 30000 | U75: =P75*#REF!/2 -> #REF! | X75: 46066 | Y75: 7594 | Z75: 7602 | AA75: =+Z75-Y75 -> 8 | AB75: =+AA75*1000 -> 8000 | AC75: 0 | AD75: =+AB75-AC75 -> 8000 | AF75: =AA75*#REF!/2 -> #REF!
B76: 46069 | C76: 18738 | D76: 18750 | E76: =+D76-C76 -> 12 | F76: =+E76*1000 -> 12000 | G76: 0 | H76: =+F76-G76 -> 12000 | J76: =E76*#REF!/2 -> #REF! | M76: 46069 | N76: 3962 | O76: 3973 | P76: =+O76-N76 -> 11 | Q76: =+P76*1000 -> 11000 | R76: 0 | S76: =+Q76-R76 -> 11000 | U76: =P76*#REF!/2 -> #REF! | X76: 46069 | Y76: 7602 | Z76: 7610 | AA76: =+Z76-Y76 -> 8 | AB76: =+AA76*1000 -> 8000 | AC76: 0 | AD76: =+AB76-AC76 -> 8000 | AF76: =AA76*#REF!/2 -> #REF!
B77: 46073 | C77: 18750 | D77: 18764 | E77: =+D77-C77 -> 14 | F77: =+E77*1000 -> 14000 | G77: 0 | H77: =+F77-G77 -> 14000 | J77: =E77*#REF!/2 -> #REF! | M77: a2/20 | N77: 3973 | O77: 3992 | P77: =+O77-N77 -> 19 | Q77: =+P77*1000 -> 19000 | R77: 0 | S77: =+Q77-R77 -> 19000 | U77: =P77*#REF!/2 -> #REF! | X77: 46073 | Y77: 7610 | Z77: 7610 | AA77: =+Z77-Y77 -> 0 | AB77: =+AA77*1000 -> 0 | AC77: 0 | AD77: =+AB77-AC77 -> 0 | AF77: =AA77*#REF!/2 -> #REF!
E78: =+D78-C78 -> 0 | F78: =+E78*1000 -> 0 | G78: 0 | H78: =+F78-G78 -> 0 | J78: =E78*#REF!/2 -> #REF! | P78: =+O78-N78 -> 0 | Q78: =+P78*1000 -> 0 | R78: 0 | S78: =+Q78-R78 -> 0 | U78: =P78*#REF!/2 -> #REF! | AA78: =+Z78-Y78 -> 0 | AB78: =+AA78*1000 -> 0 | AC78: 0 | AD78: =+AB78-AC78 -> 0 | AF78: =AA78*#REF!/2 -> #REF!
E79: =+D79-C79 -> 0 | F79: =+E79*1000 -> 0 | G79: 0 | H79: =+F79-G79 -> 0 | J79: =E79*#REF!/2 -> #REF! | L79: 景品原価 | P79: =+O79-N79 -> 0 | Q79: =+P79*1000 -> 0 | R79: 0 | S79: =+Q79-R79 -> 0 | U79: =P79*#REF!/2 -> #REF! | W79: 景品原価 | AA79: =+Z79-Y79 -> 0 | AB79: =+AA79*1000 -> 0 | AC79: 0 | AD79: =+AB79-AC79 -> 0 | AF79: =AA79*#REF!/2 -> #REF! | AH79: 景品原価
E80: =+D80-C80 -> 0 | F80: =+E80*1000 -> 0 | G80: 0 | H80: =+F80-G80 -> 0 | J80: =E80*#REF!/2 -> #REF! | P80: =+O80-N80 -> 0 | Q80: =+P80*1000 -> 0 | R80: 0 | S80: =+Q80-R80 -> 0 | U80: =P80*#REF!/2 -> #REF! | AA80: =+Z80-Y80 -> 0 | AB80: =+AA80*1000 -> 0 | AC80: 0 | AD80: =+AB80-AC80 -> 0 | AF80: =AA80*#REF!/2 -> #REF!
E81: =+D81-C81 -> 0 | F81: =+E81*1000 -> 0 | G81: 0 | H81: =+F81-G81 -> 0 | J81: =E81*#REF!/2 -> #REF! | P81: =+O81-N81 -> 0 | Q81: =+P81*1000 -> 0 | R81: 0 | S81: =+Q81-R81 -> 0 | U81: =P81*#REF!/2 -> #REF! | AA81: =+Z81-Y81 -> 0 | AB81: =+AA81*1000 -> 0 | AC81: 0 | AD81: =+AB81-AC81 -> 0 | AF81: =AA81*#REF!/2 -> #REF!
E82: =+D82-C82 -> 0 | F82: =+E82*1000 -> 0 | G82: 0 | H82: =+F82-G82 -> 0 | J82: =E82*#REF!/2 -> #REF! | P82: =+O82-N82 -> 0 | Q82: =+P82*1000 -> 0 | R82: 0 | S82: =+Q82-R82 -> 0 | U82: =P82*#REF!/2 -> #REF! | AA82: =+Z82-Y82 -> 0 | AB82: =+AA82*1000 -> 0 | AC82: 0 | AD82: =+AB82-AC82 -> 0 | AF82: =AA82*#REF!/2 -> #REF!
E83: =+D83-C83 -> 0 | F83: =+E83*1000 -> 0 | G83: 0 | H83: =+F83-G83 -> 0 | J83: =E83*#REF!/2 -> #REF! | L83: 利益率 | P83: =+O83-N83 -> 0 | Q83: =+P83*1000 -> 0 | R83: 0 | S83: =+Q83-R83 -> 0 | U83: =P83*#REF!/2 -> #REF! | W83: 利益率 | AA83: =+Z83-Y83 -> 0 | AB83: =+AA83*1000 -> 0 | AC83: 0 | AD83: =+AB83-AC83 -> 0 | AF83: =AA83*#REF!/2 -> #REF! | AH83: 利益率
E84: =SUM(E71:E83) -> 212 | F84: =SUM(F71:F83) -> 212000 | G84: =SUM(G71:G83) -> 0 | H84: =SUM(H71:H83) -> 212000 | I84: =SUM(I71:I83) -> 0 | J84: =SUM(J71:J83) -> #REF! | K84: =+H84*0.6-G84-J84 -> #REF! | L84: =+K84/H84 -> #REF! | P84: =SUM(P71:P83) -> 215 | Q84: =SUM(Q71:Q83) -> 215000 | R84: =SUM(R71:R83) -> 0 | S84: =SUM(S71:S83) -> 215000 | T84: =SUM(T71:T83) -> 0 | U84: =SUM(U71:U83) -> #REF! | V84: =+S84*0.6-R84-U84 -> #REF! | W84: =+V84/S84 -> #REF! | AA84: =SUM(AA71:AA83) -> 44 | AB84: =SUM(AB71:AB83) -> 44000 | AC84: =SUM(AC71:AC83) -> 0 | AD84: =SUM(AD71:AD83) -> 44000 | AE84: =SUM(AE71:AE83) -> 0 | AF84: =SUM(AF71:AF83) -> #REF! | AG84: =+AD84*0.6-AC84-AF84 -> #REF! | AH84: =+AG84/AD84 -> #REF!
B86: 2000円 | C86: 店番00309 | J86: 473.2 | M86: 1000円 | U86: 473.2 | X86: ティアラ2000円 | AF86: 473.2
B87: 日付 | C87: 前回ﾒｰﾀｰ | D87: 今回ﾒｰﾀｰ | E87: ﾒｰﾀｰ差 | F87: 売上 | G87: 立替金 | H87: 総売上 | I87: ＢＯＸ払出 | J87: ＣＰ払出 | K87: 備考 | M87: 日付 | N87: 前回ﾒｰﾀｰ | O87: 今回ﾒｰﾀｰ | P87: ﾒｰﾀｰ差 | Q87: 売上 | R87: 立替金 | S87: 総売上 | T87: ＢＯＸ払出 | U87: ＣＰ払出 | V87: 備考 | X87: 日付 | Y87: 前回ﾒｰﾀｰ | Z87: 今回ﾒｰﾀｰ | AA87: ﾒｰﾀｰ差 | AB87: 売上 | AC87: 立替金 | AD87: 総売上 | AE87: ＢＯＸ払出 | AF87: ＣＰ払出 | AG87: 備考
B88: 46076 | C88: 18764 | D88: 18774 | E88: =+D88-C88 -> 10 | F88: =+E88*1000 -> 10000 | G88: 0 | H88: =+F88-G88 -> 10000 | J88: =E88*#REF!/2 -> #REF! | M88: 46076 | N88: 3992 | O88: 4011 | P88: =+O88-N88 -> 19 | Q88: =+P88*1000 -> 19000 | R88: 0 | S88: =+Q88-R88 -> 19000 | U88: =P88*#REF!/2 -> #REF! | X88: 46076 | Y88: 7610 | Z88: 7618 | AA88: =+Z88-Y88 -> 8 | AB88: =+AA88*1000 -> 8000 | AC88: 0 | AD88: =+AB88-AC88 -> 8000 | AF88: =AA88*#REF!/2 -> #REF!
B89: 46080 | C89: 18774 | D89: 18790 | E89: =+D89-C89 -> 16 | F89: =+E89*1000 -> 16000 | G89: 0 | H89: =+F89-G89 -> 16000 | J89: =E89*#REF!/2 -> #REF! | M89: 46080 | N89: 4011 | O89: 4028 | P89: =+O89-N89 -> 17 | Q89: =+P89*1000 -> 17000 | R89: 0 | S89: =+Q89-R89 -> 17000 | U89: =P89*#REF!/2 -> #REF! | X89: 46080 | Y89: 7618 | Z89: 7620 | AA89: =+Z89-Y89 -> 2 | AB89: =+AA89*1000 -> 2000 | AC89: 0 | AD89: =+AB89-AC89 -> 2000 | AF89: =AA89*#REF!/2 -> #REF!
B90: 46083 | C90: 18790 | D90: 18800 | E90: =+D90-C90 -> 10 | F90: =+E90*1000 -> 10000 | G90: 0 | H90: =+F90-G90 -> 10000 | J90: =E90*#REF!/2 -> #REF! | M90: 46083 | N90: 4028 | O90: 4048 | P90: =+O90-N90 -> 20 | Q90: =+P90*1000 -> 20000 | R90: 0 | S90: =+Q90-R90 -> 20000 | U90: =P90*#REF!/2 -> #REF! | X90: 46083 | Y90: 7620 | Z90: 7624 | AA90: =+Z90-Y90 -> 4 | AB90: =+AA90*1000 -> 4000 | AC90: 0 | AD90: =+AB90-AC90 -> 4000 | AF90: =AA90*#REF!/2 -> #REF!
B91: 46087 | C91: 18800 | D91: 18818 | E91: =+D91-C91 -> 18 | F91: =+E91*1000 -> 18000 | G91: 0 | H91: =+F91-G91 -> 18000 | J91: =E91*#REF!/2 -> #REF! | M91: 46087 | N91: 4048 | O91: 4057 | P91: =+O91-N91 -> 9 | Q91: =+P91*1000 -> 9000 | R91: 0 | S91: =+Q91-R91 -> 9000 | U91: =P91*#REF!/2 -> #REF! | X91: 46087 | Y91: 7624 | Z91: 7626 | AA91: =+Z91-Y91 -> 2 | AB91: =+AA91*1000 -> 2000 | AC91: 0 | AD91: =+AB91-AC91 -> 2000 | AF91: =AA91*#REF!/2 -> #REF!
B92: 46090 | C92: 18818 | D92: 18830 | E92: =+D92-C92 -> 12 | F92: =+E92*1000 -> 12000 | G92: 0 | H92: =+F92-G92 -> 12000 | J92: =E92*#REF!/2 -> #REF! | M92: 46090 | N92: 4057 | O92: 4070 | P92: =+O92-N92 -> 13 | Q92: =+P92*1000 -> 13000 | R92: 0 | S92: =+Q92-R92 -> 13000 | U92: =P92*#REF!/2 -> #REF! | X92: 46090 | Y92: 7626 | Z92: 7636 | AA92: =+Z92-Y92 -> 10 | AB92: =+AA92*1000 -> 10000 | AC92: 0 | AD92: =+AB92-AC92 -> 10000 | AF92: =AA92*#REF!/2 -> #REF!
B93: 46099 | C93: 18830 | D93: 18886 | E93: =+D93-C93 -> 56 | F93: =+E93*1000 -> 56000 | G93: 0 | H93: =+F93-G93 -> 56000 | J93: =E93*#REF!/2 -> #REF! | M93: 46099 | N93: 4070 | O93: 4103 | P93: =+O93-N93 -> 33 | Q93: =+P93*1000 -> 33000 | R93: 0 | S93: =+Q93-R93 -> 33000 | U93: =P93*#REF!/2 -> #REF! | X93: 46099 | Y93: 7636 | Z93: 7652 | AA93: =+Z93-Y93 -> 16 | AB93: =+AA93*1000 -> 16000 | AC93: 0 | AD93: =+AB93-AC93 -> 16000 | AF93: =AA93*#REF!/2 -> #REF!
E94: =+D94-C94 -> 0 | F94: =+E94*1000 -> 0 | G94: 0 | H94: =+F94-G94 -> 0 | J94: =E94*#REF!/2 -> #REF! | P94: =+O94-N94 -> 0 | Q94: =+P94*1000 -> 0 | R94: 0 | S94: =+Q94-R94 -> 0 | U94: =P94*#REF!/2 -> #REF! | AA94: =+Z94-Y94 -> 0 | AB94: =+AA94*1000 -> 0 | AC94: 0 | AD94: =+AB94-AC94 -> 0 | AF94: =AA94*#REF!/2 -> #REF!
E95: =+D95-C95 -> 0 | F95: =+E95*1000 -> 0 | G95: 0 | H95: =+F95-G95 -> 0 | J95: =E95*#REF!/2 -> #REF! | P95: =+O95-N95 -> 0 | Q95: =+P95*1000 -> 0 | R95: 0 | S95: =+Q95-R95 -> 0 | U95: =P95*#REF!/2 -> #REF! | AA95: =+Z95-Y95 -> 0 | AB95: =+AA95*1000 -> 0 | AC95: 0 | AD95: =+AB95-AC95 -> 0 | AF95: =AA95*#REF!/2 -> #REF!
E96: =+D96-C96 -> 0 | F96: =+E96*1000 -> 0 | G96: 0 | H96: =+F96-G96 -> 0 | J96: =E96*#REF!/2 -> #REF! | L96: 景品原価 | P96: =+O96-N96 -> 0 | Q96: =+P96*1000 -> 0 | R96: 0 | S96: =+Q96-R96 -> 0 | U96: =P96*#REF!/2 -> #REF! | W96: 景品原価 | AA96: =+Z96-Y96 -> 0 | AB96: =+AA96*1000 -> 0 | AC96: 0 | AD96: =+AB96-AC96 -> 0 | AF96: =AA96*#REF!/2 -> #REF! | AH96: 景品原価
E97: =+D97-C97 -> 0 | F97: =+E97*1000 -> 0 | G97: 0 | H97: =+F97-G97 -> 0 | J97: =E97*#REF!/2 -> #REF! | P97: =+O97-N97 -> 0 | Q97: =+P97*1000 -> 0 | R97: 0 | S97: =+Q97-R97 -> 0 | U97: =P97*#REF!/2 -> #REF! | AA97: =+Z97-Y97 -> 0 | AB97: =+AA97*1000 -> 0 | AC97: 0 | AD97: =+AB97-AC97 -> 0 | AF97: =AA97*#REF!/2 -> #REF!
E98: =+D98-C98 -> 0 | F98: =+E98*1000 -> 0 | G98: 0 | H98: =+F98-G98 -> 0 | J98: =E98*#REF!/2 -> #REF! | P98: =+O98-N98 -> 0 | Q98: =+P98*1000 -> 0 | R98: 0 | S98: =+Q98-R98 -> 0 | U98: =P98*#REF!/2 -> #REF! | AA98: =+Z98-Y98 -> 0 | AB98: =+AA98*1000 -> 0 | AC98: 0 | AD98: =+AB98-AC98 -> 0 | AF98: =AA98*#REF!/2 -> #REF!
E99: =+D99-C99 -> 0 | F99: =+E99*1000 -> 0 | G99: 0 | H99: =+F99-G99 -> 0 | J99: =E99*#REF!/2 -> #REF! | P99: =+O99-N99 -> 0 | Q99: =+P99*1000 -> 0 | R99: 0 | S99: =+Q99-R99 -> 0 | U99: =P99*#REF!/2 -> #REF! | AA99: =+Z99-Y99 -> 0 | AB99: =+AA99*1000 -> 0 | AC99: 0 | AD99: =+AB99-AC99 -> 0 | AF99: =AA99*#REF!/2 -> #REF!
E100: =+D100-C100 -> 0 | F100: =+E100*1000 -> 0 | G100: 0 | H100: =+F100-G100 -> 0 | J100: =E100*#REF!/2 -> #REF! | L100: 利益率 | P100: =+O100-N100 -> 0 | Q100: =+P100*1000 -> 0 | R100: 0 | S100: =+Q100-R100 -> 0 | U100: =P100*#REF!/2 -> #REF! | W100: 利益率 | AA100: =+Z100-Y100 -> 0 | AB100: =+AA100*1000 -> 0 | AC100: 0 | AD100: =+AB100-AC100 -> 0 | AF100: =AA100*#REF!/2 -> #REF! | AH100: 利益率
E101: =SUM(E88:E100) -> 122 | F101: =SUM(F88:F100) -> 122000 | G101: =SUM(G88:G100) -> 0 | H101: =SUM(H88:H100) -> 122000 | I101: =SUM(I88:I100) -> 0 | J101: =SUM(J88:J100) -> #REF! | K101: =+H101*0.6-G101-J101 -> #REF! | L101: =+K101/H101 -> #REF! | P101: =SUM(P88:P100) -> 111 | Q101: =SUM(Q88:Q100) -> 111000 | R101: =SUM(R88:R100) -> 0 | S101: =SUM(S88:S100) -> 111000 | T101: =SUM(T88:T100) -> 0 | U101: =SUM(U88:U100) -> #REF! | V101: =+S101*0.6-R101-U101 -> #REF! | W101: =+V101/S101 -> #REF! | AA101: =SUM(AA88:AA100) -> 42 | AB101: =SUM(AB88:AB100) -> 42000 | AC101: =SUM(AC88:AC100) -> 0 | AD101: =SUM(AD88:AD100) -> 42000 | AE101: =SUM(AE88:AE100) -> 0 | AF101: =SUM(AF88:AF100) -> #REF! | AG101: =+AD101*0.6-AC101-AF101 -> #REF! | AH101: =+AG101/AD101 -> #REF!
B103: 2000円 | C103: 店番00309 | J103: 473.2 | M103: 1000円 | U103: 473.2 | X103: ティアラ2000円 | AF103: 473.2
B104: 日付 | C104: 前回ﾒｰﾀｰ | D104: 今回ﾒｰﾀｰ | E104: ﾒｰﾀｰ差 | F104: 売上 | G104: 立替金 | H104: 総売上 | I104: ＢＯＸ払出 | J104: ＣＰ払出 | K104: 備考 | M104: 日付 | N104: 前回ﾒｰﾀｰ | O104: 今回ﾒｰﾀｰ | P104: ﾒｰﾀｰ差 | Q104: 売上 | R104: 立替金 | S104: 総売上 | T104: ＢＯＸ払出 | U104: ＣＰ払出 | V104: 備考 | X104: 日付 | Y104: 前回ﾒｰﾀｰ | Z104: 今回ﾒｰﾀｰ | AA104: ﾒｰﾀｰ差 | AB104: 売上 | AC104: 立替金 | AD104: 総売上 | AE104: ＢＯＸ払出 | AF104: ＣＰ払出 | AG104: 備考
B105: 46104 | C105: 18886 | D105: 18928 | E105: =+D105-C105 -> 42 | F105: =+E105*1000 -> 42000 | G105: 0 | H105: =+F105-G105 -> 42000 | J105: =E105*#REF!/2 -> #REF! | M105: 46104 | N105: 4103 | O105: 4120 | P105: =+O105-N105 -> 17 | Q105: =+P105*1000 -> 17000 | R105: 0 | S105: =+Q105-R105 -> 17000 | U105: =P105*#REF!/2 -> #REF! | X105: 46104 | Y105: 7652 | Z105: 7674 | AA105: =+Z105-Y105 -> 22 | AB105: =+AA105*1000 -> 22000 | AC105: 0 | AD105: =+AB105-AC105 -> 22000 | AF105: =AA105*#REF!/2 -> #REF!
B106: 46108 | C106: 18928 | D106: 18944 | E106: =+D106-C106 -> 16 | F106: =+E106*1000 -> 16000 | G106: 0 | H106: =+F106-G106 -> 16000 | J106: =E106*#REF!/2 -> #REF! | M106: 46108 | N106: 4120 | O106: 4132 | P106: =+O106-N106 -> 12 | Q106: =+P106*1000 -> 12000 | R106: 0 | S106: =+Q106-R106 -> 12000 | U106: =P106*#REF!/2 -> #REF! | X106: 46088 | Y106: 7674 | Z106: 7688 | AA106: =+Z106-Y106 -> 14 | AB106: =+AA106*1000 -> 14000 | AC106: 0 | AD106: =+AB106-AC106 -> 14000 | AF106: =AA106*#REF!/2 -> #REF!
...

Sheet 小倉
B1: 日付 | C1: 前回ﾒｰﾀｰ | D1: 今回ﾒｰﾀｰ | E1: ﾒｰﾀｰ差 | F1: 売上 | G1: 立替金 | H1: 総売上 | I1: ＢＯＸ払出 | J1: ＣＰ払出 | K1: 備考
B2: 45924 | D2: 10068 | E2: 50 | F2: 50000 | G2: 0 | H2: =+F2-G2 -> 50000 | J2: =+E2*#REF! -> #REF!
B3: 45931 | D3: 10122 | E3: =IF(D3="","",D3-D2) -> 54 | F3: =IF(D3="","",E3*1000) -> 54000 | G3: 0 | H3: =+F3-G3 -> 54000 | J3: =+E3*#REF! -> #REF!
B4: 45938 | D4: 10174 | E4: =IF(D4="","",D4-D3) -> 52 | F4: =IF(D4="","",E4*1000) -> 52000 | G4: 0 | H4: =+F4-G4 -> 52000 | J4: =+E4*#REF! -> #REF!
B5: 45946 | D5: 10272 | E5: =IF(D5="","",D5-D4) -> 98 | F5: =IF(D5="","",E5*1000) -> 98000 | G5: 0 | H5: =+F5-G5 -> 98000 | J5: =+E5*#REF! -> #REF!
E6: =IF(D6="","",D6-D5) | F6: =IF(D6="","",E6*1000)
E7: =IF(D7="","",D7-D6) | F7: =IF(D7="","",E7*1000)
E8: =IF(D8="","",D8-D7) | F8: =IF(D8="","",E8*1000)
E9: =IF(D9="","",D9-D8) | F9: =IF(D9="","",E9*1000)
E10: =IF(D10="","",D10-D9) | F10: =IF(D10="","",E10*1000)
E11: =IF(D11="","",D11-D10) | F11: =IF(D11="","",E11*1000)
E12: =IF(D12="","",D12-D11) | F12: =IF(D12="","",E12*1000) | G12: 0 | H12: =+F12-G12 -> #VALUE! | J12: =+E12*#REF! -> #VALUE!
E13: =IF(D13="","",D13-D12) | F13: =IF(D13="","",E13*1000) | G13: 0 | H13: =+F13-G13 -> #VALUE! | J13: =+E13*#REF! -> #VALUE!
E14: =SUM(E2:E13) -> 254 | F14: =SUM(F2:F13) -> 254000 | G14: =SUM(G2:G13) -> 0 | H14: =SUM(H2:H13) -> #VALUE! | I14: =SUM(I2:I13) -> 0 | J14: =SUM(J2:J13) -> #REF! | K14: =+H14*0.6-I14-J14-G14 -> #VALUE!
B16: 日付 | C16: 前回ﾒｰﾀｰ | D16: 今回ﾒｰﾀｰ | E16: ﾒｰﾀｰ差 | F16: 売上 | G16: 立替金 | H16: 総売上 | I16: ＢＯＸ払出 | J16: ＣＰ払出 | K16: 備考
B17: 45952 | D17: 10307 | E17: =+D17-D5 -> 35 | F17: =+E17*1000 -> 35000 | G17: 0 | H17: =+F17-G17 -> 35000 | J17: =+E17*#REF! -> #REF!
B18: 45959 | D18: 10345 | E18: =IF(D18="","",D18-D17) -> 38 | F18: =IF(D18="","",E18*1000) -> 38000 | G18: 0 | H18: =+F18-G18 -> 38000 | J18: =+E18*#REF! -> #REF!
B19: 45966 | D19: 10390 | E19: =IF(D19="","",D19-D18) -> 45 | F19: =IF(D19="","",E19*1000) -> 45000 | G19: 0 | H19: =+F19-G19 -> 45000 | J19: =+E19*#REF! -> #REF!
B20: 45973 | D20: 10435 | E20: =IF(D20="","",D20-D19) -> 45 | F20: =IF(D20="","",E20*1000) -> 45000 | G20: 0 | H20: =+F20-G20 -> 45000 | J20: =+E20*#REF! -> #REF!
B21: 45978 | D21: 10481 | E21: =IF(D21="","",D21-D20) -> 46 | F21: =IF(D21="","",E21*1000) -> 46000
E22: =IF(D22="","",D22-D21) | F22: =IF(D22="","",E22*1000)
E23: =IF(D23="","",D23-D22) | F23: =IF(D23="","",E23*1000)
E24: =IF(D24="","",D24-D23) | F24: =IF(D24="","",E24*1000)
E25: =IF(D25="","",D25-D24) | F25: =IF(D25="","",E25*1000)
E26: =IF(D26="","",D26-D25) | F26: =IF(D26="","",E26*1000)
E27: =IF(D27="","",D27-D26) | F27: =IF(D27="","",E27*1000) | G27: 0 | H27: =+F27-G27 -> #VALUE! | J27: =+E27*#REF! -> #VALUE!
E28: =IF(D28="","",D28-D27) | F28: =IF(D28="","",E28*1000) | G28: 0 | H28: =+F28-G28 -> #VALUE! | J28: =+E28*#REF! -> #VALUE!
E29: =SUM(E17:E28) -> 209 | F29: =SUM(F17:F28) -> 209000 | G29: =SUM(G17:G28) -> 0 | H29: =SUM(H17:H28) -> #VALUE! | I29: =SUM(I17:I28) -> 0 | J29: =SUM(J17:J28) -> #REF! | K29: =+H29*0.6-I29-J29-G29 -> #VALUE!
B31: 日付 | C31: 前回ﾒｰﾀｰ | D31: 今回ﾒｰﾀｰ | E31: ﾒｰﾀｰ差 | F31: 売上 | G31: 立替金 | H31: 総売上 | I31: ＢＯＸ払出 | J31: ＣＰ払出 | K31: 備考
B32: 45986 | D32: 10523 | E32: =+D32-D21 -> 42 | F32: =+E32*1000 -> 42000 | G32: 0 | H32: =+F32-G32 -> 42000 | J32: =+E32*#REF! -> #REF!
B33: 45994 | D33: 10570 | E33: =IF(D33="","",D33-D32) -> 47 | F33: =IF(D33="","",E33*1000) -> 47000 | G33: 0 | H33: =+F33-G33 -> 47000 | J33: =+E33*#REF! -> #REF!
B34: 46001 | D34: 10629 | E34: =IF(D34="","",D34-D33) -> 59 | F34: =IF(D34="","",E34*1000) -> 59000 | G34: 0 | H34: =+F34-G34 -> 59000 | J34: =+E34*#REF! -> #REF!
B35: 46008 | D35: 10667 | E35: =IF(D35="","",D35-D34) -> 38 | F35: =IF(D35="","",E35*1000) -> 38000 | G35: 0 | H35: =+F35-G35 -> 38000 | J35: =+E35*#REF! -> #REF!
E36: =IF(D36="","",D36-D35) | F36: =IF(D36="","",E36*1000)
E37: =IF(D37="","",D37-D36) | F37: =IF(D37="","",E37*1000)
E38: =IF(D38="","",D38-D37) | F38: =IF(D38="","",E38*1000)
E39: =IF(D39="","",D39-D38) | F39: =IF(D39="","",E39*1000)
E40: =IF(D40="","",D40-D39) | F40: =IF(D40="","",E40*1000)
E41: =IF(D41="","",D41-D40) | F41: =IF(D41="","",E41*1000)
E42: =IF(D42="","",D42-D41) | F42: =IF(D42="","",E42*1000) | G42: 0 | H42: =+F42-G42 -> #VALUE! | J42: =+E42*#REF! -> #VALUE!
E43: =IF(D43="","",D43-D42) | F43: =IF(D43="","",E43*1000) | G43: 0 | H43: =+F43-G43 -> #VALUE! | J43: =+E43*#REF! -> #VALUE!
E44: =SUM(E32:E43) -> 186 | F44: =SUM(F32:F43) -> 186000 | G44: =SUM(G32:G43) -> 0 | H44: =SUM(H32:H43) -> #VALUE! | I44: =SUM(I32:I43) -> 0 | J44: =SUM(J32:J43) -> #REF! | K44: =+H44*0.6-I44-J44-G44 -> #VALUE!
B46: 日付 | C46: 前回ﾒｰﾀｰ | D46: 今回ﾒｰﾀｰ | E46: ﾒｰﾀｰ差 | F46: 売上 | G46: 立替金 | H46: 総売上 | I46: ＢＯＸ払出 | J46: ＣＰ払出 | K46: 備考
B47: 46014 | D47: 10731 | E47: =+D47-D35 -> 64 | F47: =+E47*1000 -> 64000 | G47: 0 | H47: =+F47-G47 -> 64000 | J47: =+E47*#REF! -> #REF!
B48: 46020 | D48: 10758 | E48: =IF(D48="","",D48-D47) -> 27 | F48: =IF(D48="","",E48*1000) -> 27000 | G48: 0 | H48: =+F48-G48 -> 27000 | J48: =+E48*#REF! -> #REF!
B49: 46027 | D49: 10840 | E49: =IF(D49="","",D49-D48) -> 82 | F49: =IF(D49="","",E49*1000) -> 82000 | G49: 0 | H49: =+F49-G49 -> 82000 | J49: =+E49*#REF! -> #REF!
B50: 46034 | D50: 10907 | E50: =IF(D50="","",D50-D49) -> 67 | F50: =IF(D50="","",E50*1000) -> 67000 | G50: 0 | H50: =+F50-G50 -> 67000 | J50: =+E50*#REF! -> #REF!
B51: 46041 | D51: 10944 | E51: =IF(D51="","",D51-D50) -> 37 | F51: =IF(D51="","",E51*1000) -> 37000
E52: =IF(D52="","",D52-D51) | F52: =IF(D52="","",E52*1000)
E53: =IF(D53="","",D53-D52) | F53: =IF(D53="","",E53*1000)
E54: =IF(D54="","",D54-D53) | F54: =IF(D54="","",E54*1000)
E55: =IF(D55="","",D55-D54) | F55: =IF(D55="","",E55*1000)
E56: =IF(D56="","",D56-D55) | F56: =IF(D56="","",E56*1000)
E57: =IF(D57="","",D57-D56) | F57: =IF(D57="","",E57*1000) | G57: 0 | H57: =+F57-G57 -> #VALUE! | J57: =+E57*#REF! -> #VALUE!
E58: =IF(D58="","",D58-D57) | F58: =IF(D58="","",E58*1000) | G58: 0 | H58: =+F58-G58 -> #VALUE! | J58: =+E58*#REF! -> #VALUE!
E59: =SUM(E47:E58) -> 277 | F59: =SUM(F47:F58) -> 277000 | G59: =SUM(G47:G58) -> 0 | H59: =SUM(H47:H58) -> #VALUE! | I59: =SUM(I47:I58) -> 0 | J59: =SUM(J47:J58) -> #REF! | K59: =+H59*0.6-I59-J59-G59 -> #VALUE!
B61: 日付 | C61: 前回ﾒｰﾀｰ | D61: 今回ﾒｰﾀｰ | E61: ﾒｰﾀｰ差 | F61: 売上 | G61: 立替金 | H61: 総売上 | I61: ＢＯＸ払出 | J61: ＣＰ払出 | K61: 備考
B62: 46050 | D62: 11003 | E62: =+D62-D51 -> 59 | F62: =+E62*1000 -> 59000 | G62: 0 | H62: =+F62-G62 -> 59000 | J62: =+E62*#REF! -> #REF!
B63: 46057 | D63: 11048 | E63: =IF(D63="","",D63-D62) -> 45 | F63: =IF(D63="","",E63*1000) -> 45000 | G63: 0 | H63: =+F63-G63 -> 45000 | J63: =+E63*#REF! -> #REF!
B64: 46063 | D64: 11098 | E64: =IF(D64="","",D64-D63) -> 50 | F64: =IF(D64="","",E64*1000) -> 50000 | G64: 0 | H64: =+F64-G64 -> 50000 | J64: =+E64*#REF! -> #REF!
B65: 46071 | D65: 11139 | E65: =IF(D65="","",D65-D64) -> 41 | F65: =IF(D65="","",E65*1000) -> 41000 | G65: 0 | H65: =+F65-G65 -> 41000 | J65: =+E65*#REF! -> #REF!
E66: =IF(D66="","",D66-D65) | F66: =IF(D66="","",E66*1000)
E67: =IF(D67="","",D67-D66) | F67: =IF(D67="","",E67*1000)
E68: =IF(D68="","",D68-D67) | F68: =IF(D68="","",E68*1000)
E69: =IF(D69="","",D69-D68) | F69: =IF(D69="","",E69*1000)
E70: =IF(D70="","",D70-D69) | F70: =IF(D70="","",E70*1000)
E71: =IF(D71="","",D71-D70) | F71: =IF(D71="","",E71*1000)
E72: =IF(D72="","",D72-D71) | F72: =IF(D72="","",E72*1000) | G72: 0 | H72: =+F72-G72 -> #VALUE! | J72: =+E72*#REF! -> #VALUE!
E73: =IF(D73="","",D73-D72) | F73: =IF(D73="","",E73*1000) | G73: 0 | H73: =+F73-G73 -> #VALUE! | J73: =+E73*#REF! -> #VALUE!
E74: =SUM(E62:E73) -> 195 | F74: =SUM(F62:F73) -> 195000 | G74: =SUM(G62:G73) -> 0 | H74: =SUM(H62:H73) -> #VALUE! | I74: =SUM(I62:I73) -> 0 | J74: =SUM(J62:J73) -> #REF! | K74: =+H74*0.6-I74-J74-G74 -> #VALUE!
B76: 日付 | C76: 前回ﾒｰﾀｰ | D76: 今回ﾒｰﾀｰ | E76: ﾒｰﾀｰ差 | F76: 売上 | G76: 立替金 | H76: 総売上 | I76: ＢＯＸ払出 | J76: ＣＰ払出 | K76: 備考
B77: 46077 | D77: 11170 | E77: =+D77-D65 -> 31 | F77: =+E77*1000 -> 31000 | G77: 0 | H77: =+F77-G77 -> 31000 | J77: =+E77*#REF! -> #REF!
B78: 46085 | D78: 11231 | E78: =IF(D78="","",D78-D77) -> 61 | F78: =IF(D78="","",E78*1000) -> 61000 | G78: 0 | H78: =+F78-G78 -> 61000 | J78: =+E78*#REF! -> #REF!
B79: 46092 | D79: 11271 | E79: =IF(D79="","",D79-D78) -> 40 | F79: =IF(D79="","",E79*1000) -> 40000 | G79: 0 | H79: =+F79-G79 -> 40000 | J79: =+E79*#REF! -> #REF!
B80: 46097 | D80: 11289 | E80: =IF(D80="","",D80-D79) -> 18 | F80: =IF(D80="","",E80*1000) -> 18000 | G80: 0 | H80: =+F80-G80 -> 18000 | J80: =+E80*#REF! -> #REF!
E81: =IF(D81="","",D81-D80) | F81: =IF(D81="","",E81*1000)
E82: =IF(D82="","",D82-D81) | F82: =IF(D82="","",E82*1000)
E83: =IF(D83="","",D83-D82) | F83: =IF(D83="","",E83*1000)
E84: =IF(D84="","",D84-D83) | F84: =IF(D84="","",E84*1000)
E85: =IF(D85="","",D85-D84) | F85: =IF(D85="","",E85*1000)
E86: =IF(D86="","",D86-D85) | F86: =IF(D86="","",E86*1000)
E87: =IF(D87="","",D87-D86) | F87: =IF(D87="","",E87*1000) | G87: 0 | H87: =+F87-G87 -> #VALUE! | J87: =+E87*#REF! -> #VALUE!
E88: =IF(D88="","",D88-D87) | F88: =IF(D88="","",E88*1000) | G88: 0 | H88: =+F88-G88 -> #VALUE! | J88: =+E88*#REF! -> #VALUE!
E89: =SUM(E77:E88) -> 150 | F89: =SUM(F77:F88) -> 150000 | G89: =SUM(G77:G88) -> 0 | H89: =SUM(H77:H88) -> #VALUE! | I89: =SUM(I77:I88) -> 0 | J89: =SUM(J77:J88) -> #REF! | K89: =+H89*0.6-I89-J89-G89 -> #VALUE!
B91: 1000円 | M91: 2000円
B92: 日付 | C92: 前回ﾒｰﾀｰ | D92: 今回ﾒｰﾀｰ | E92: ﾒｰﾀｰ差 | F92: 売上 | G92: 立替金 | H92: 総売上 | I92: ＢＯＸ払出 | J92: ＣＰ払出 | K92: 備考 | M92: 日付 | N92: 前回ﾒｰﾀｰ | O92: 今回ﾒｰﾀｰ | P92: ﾒｰﾀｰ差 | Q92: 売上 | R92: 立替金 | S92: 総売上 | T92: ＢＯＸ払出 | U92: ＣＰ払出 | V92: 備考
B93: 46100 | D93: 11295 | E93: =+D93-D80 -> 6 | F93: =+E93*1000 -> 6000 | G93: 0 | H93: =+F93-G93 -> 6000 | J93: =+E93*#REF! -> #REF! | M93: 46100 | N93: 6535 | O93: 6535 | P93: =+O93-N93 -> 0 | Q93: =+P93*1000 -> 0 | R93: 0 | S93: =+Q93-R93 -> 0 | U93: =+P93*#REF! -> #REF!
B94: 46107 | D94: 11331 | E94: =IF(D94="","",D94-D93) -> 36 | F94: =IF(D94="","",E94*1000) -> 36000 | G94: 0 | H94: =+F94-G94 -> 36000 | J94: =+E94*#REF! -> #REF! | M94: 46107 | N94: 6535 | O94: 6541 | P94: =IF(O94="","",O94-O93) -> 6 | Q94: =IF(O94="","",P94*1000) -> 6000 | R94: 0 | S94: =+Q94-R94 -> 6000 | U94: =+P94*#REF! -> #REF!
B95: 46113 | D95: 11354 | E95: =IF(D95="","",D95-D94) -> 23 | F95: =IF(D95="","",E95*1000) -> 23000 | G95: 0 | H95: =+F95-G95 -> 23000 | J95: =+E95*#REF! -> #REF! | M95: 46113 | O95: 6551 | P95: =IF(O95="","",O95-O94) -> 10 | Q95: =IF(O95="","",P95*1000) -> 10000 | S95: =IF(Q95="","",R95*1000) -> 0 | U95: =+P95*#REF! -> #REF!
B96: 46120 | D96: 11378 | E96: =IF(D96="","",D96-D95) -> 24 | F96: =IF(D96="","",E96*1000) -> 24000 | G96: 0 | H96: =+F96-G96 -> 24000 | J96: =+E96*#REF! -> #REF! | M96: 46120 | O96: 6563 | P96: =IF(O96="","",O96-O95) -> 12 | Q96: =IF(O96="","",P96*1000) -> 12000 | S96: =IF(Q96="","",R96*1000) -> 0 | U96: =+P96*#REF! -> #REF!
B97: 46128 | D97: 11407 | E97: =IF(D97="","",D97-D96) -> 29 | F97: =IF(D97="","",E97*1000) -> 29000 | M97: 46128 | O97: 6577 | P97: =IF(O97="","",O97-O96) -> 14 | Q97: =IF(O97="","",P97*1000) -> 14000 | S97: =IF(Q97="","",R97*1000) -> 0
E98: =IF(D98="","",D98-D97) | F98: =IF(D98="","",E98*1000) | P98: =IF(O98="","",O98-O97) | Q98: =IF(O98="","",P98*1000) | S98: =IF(Q98="","",R98*1000)
E99: =IF(D99="","",D99-D98) | F99: =IF(D99="","",E99*1000) | P99: =IF(O99="","",O99-O98) | Q99: =IF(O99="","",P99*1000) | S99: =IF(Q99="","",R99*1000)
E100: =IF(D100="","",D100-D99) | F100: =IF(D100="","",E100*1000) | P100: =IF(O100="","",O100-O99) | Q100: =IF(O100="","",P100*1000) | S100: =IF(Q100="","",R100*1000)
E101: =IF(D101="","",D101-D100) | F101: =IF(D101="","",E101*1000) | P101: =IF(O101="","",O101-O100) | Q101: =IF(O101="","",P101*1000) | S101: =IF(Q101="","",R101*1000)
E102: =IF(D102="","",D102-D101) | F102: =IF(D102="","",E102*1000) | P102: =IF(O102="","",O102-O101) | Q102: =IF(O102="","",P102*1000) | S102: =IF(Q102="","",R102*1000)
E103: =IF(D103="","",D103-D102) | F103: =IF(D103="","",E103*1000) | G103: 0 | H103: =+F103-G103 -> #VALUE! | J103: =+E103*#REF! -> #VALUE! | P103: =IF(O103="","",O103-O102) | Q103: =IF(O103="","",P103*1000) | S103: =IF(Q103="","",R103*1000) | U103: =+P103*#REF! -> #VALUE!
E104: =IF(D104="","",D104-D103) | F104: =IF(D104="","",E104*1000) | G104: 0 | H104: =+F104-G104 -> #VALUE! | J104: =+E104*#REF! -> #VALUE! | P104: =IF(O104="","",O104-O103) | Q104: =IF(O104="","",P104*1000) | S104: =IF(Q104="","",R104*1000) | U104: =+P104*#REF! -> #VALUE!
E105: =SUM(E93:E104) -> 118 | F105: =SUM(F93:F104) -> 118000 | G105: =SUM(G93:G104) -> 0 | H105: =SUM(H93:H104) -> #VALUE! | I105: =SUM(I93:I104) -> 0 | J105: =SUM(J93:J104) -> #REF! | K105: =+H105*0.6-I105-J105-G105 -> #VALUE! | P105: =SUM(P93:P104) -> 42 | Q105: =SUM(Q93:Q104) -> 42000 | R105: =SUM(R93:R104) -> 0 | S105: =SUM(S93:S104) -> 6000 | T105: =SUM(T93:T104) -> 0 | U105: =SUM(U93:U104) -> #REF! | V105: =+S105*0.6-T105-U105-R105 -> #REF!
B107: 1000円 | M107: 2000円
...

Sheet 黒崎
B1: 2000円 | M1: 1000円
B2: 日付 | D2: 今回ﾒｰﾀｰ | E2: ﾒｰﾀｰ差 | F2: 売上 | K2: 備考 | M2: 日付 | O2: 今回ﾒｰﾀｰ | P2: ﾒｰﾀｰ差 | Q2: 売上 | V2: 備考
B3: 45924 | D3: 12224 | E3: 64 | F3: 64000 | M3: 45924 | O3: 3527 | P3: 113 | Q3: 113000
B4: 45931 | D4: 12370 | E4: =IF(D4="","",D4-D3) -> 146 | F4: =IF(D4="","",E4*1000) -> 146000 | M4: =IF(B4="","",B4) -> 45931 | O4: 3588 | P4: =IF(O4="","",O4-O3) -> 61 | Q4: =IF(O4="","",P4*1000) -> 61000
B5: 45934 | D5: 12416 | E5: =IF(D5="","",D5-D4) -> 46 | F5: =IF(D5="","",E5*1000) -> 46000 | M5: =IF(B5="","",B5) -> 45934 | O5: 3619 | P5: =IF(O5="","",O5-O4) -> 31 | Q5: =IF(O5="","",P5*1000) -> 31000
B6: 45938 | D6: 12492 | E6: =IF(D6="","",D6-D5) -> 76 | F6: =IF(D6="","",E6*1000) -> 76000 | M6: =IF(B6="","",B6) -> 45938 | O6: 3652 | P6: =IF(O6="","",O6-O5) -> 33 | Q6: =IF(O6="","",P6*1000) -> 33000
B7: 45946 | D7: 12626 | E7: =IF(D7="","",D7-D6) -> 134 | F7: =IF(D7="","",E7*1000) -> 134000 | M7: =IF(B7="","",B7) -> 45946 | O7: 3757 | P7: =IF(O7="","",O7-O6) -> 105 | Q7: =IF(O7="","",P7*1000) -> 105000
E8: =IF(D8="","",D8-D7) | F8: =IF(D8="","",E8*1000) | M8: =IF(B8="","",B8) | P8: =IF(O8="","",O8-O7) | Q8: =IF(O8="","",P8*1000)
E9: =IF(D9="","",D9-D8) | F9: =IF(D9="","",E9*1000) | M9: =IF(B9="","",B9) | P9: =IF(O9="","",O9-O8) | Q9: =IF(O9="","",P9*1000)
E10: =IF(D10="","",D10-D9) | F10: =IF(D10="","",E10*1000) | M10: =IF(B10="","",B10) | P10: =IF(O10="","",O10-O9) | Q10: =IF(O10="","",P10*1000)
E11: =IF(D11="","",D11-D10) | F11: =IF(D11="","",E11*1000) | M11: =IF(B11="","",B11) | N11: =IF(C11="","",C11) | P11: =IF(O11="","",O11-O10) | Q11: =IF(O11="","",P11*1000)
E12: =IF(D12="","",D12-D11) | F12: =IF(D12="","",E12*1000) | M12: =IF(B12="","",B12) | N12: =IF(C12="","",C12) | P12: =IF(O12="","",O12-O11) | Q12: =IF(O12="","",P12*1000)
E13: =SUM(E3:E12) -> 466 | F13: =SUM(F3:F12) -> 466000 | P13: =SUM(P3:P12) -> 343 | Q13: =SUM(Q3:Q12) -> 343000
B15: 2000円 | M15: 1000円
B16: 日付 | D16: 今回ﾒｰﾀｰ | E16: ﾒｰﾀｰ差 | F16: 売上 | K16: 備考 | M16: 日付 | O16: 今回ﾒｰﾀｰ | P16: ﾒｰﾀｰ差 | Q16: 売上 | V16: 備考
B17: 45952 | D17: 12696 | E17: =IF(D17="","",D17-D7) -> 70 | F17: =IF(D17="","",E17*1000) -> 70000 | M17: =IF(B17="","",B17) -> 45952 | O17: 3797 | P17: =IF(O17="","",O17-O7) -> 40 | Q17: =IF(O17="","",P17*1000) -> 40000
B18: 45959 | D18: 12738 | E18: =IF(D18="","",D18-D17) -> 42 | F18: =IF(D18="","",E18*1000) -> 42000 | M18: =IF(B18="","",B18) -> 45959 | O18: 3864 | P18: =IF(O18="","",O18-O17) -> 67 | Q18: =IF(O18="","",P18*1000) -> 67000
B19: 45966 | D19: 12790 | E19: =IF(D19="","",D19-D18) -> 52 | F19: =IF(D19="","",E19*1000) -> 52000 | M19: =IF(B19="","",B19) -> 45966 | O19: 3927 | P19: =IF(O19="","",O19-O18) -> 63 | Q19: =IF(O19="","",P19*1000) -> 63000
B20: 45973 | D20: 12886 | E20: =IF(D20="","",D20-D19) -> 96 | F20: =IF(D20="","",E20*1000) -> 96000 | M20: =IF(B20="","",B20) -> 45973 | O20: 3996 | P20: =IF(O20="","",O20-O19) -> 69 | Q20: =IF(O20="","",P20*1000) -> 69000
B21: 45978 | D21: 12908 | E21: =IF(D21="","",D21-D20) -> 22 | F21: =IF(D21="","",E21*1000) -> 22000 | M21: =IF(B21="","",B21) -> 45978 | O21: 4031 | P21: =IF(O21="","",O21-O20) -> 35 | Q21: =IF(O21="","",P21*1000) -> 35000
E22: =IF(D22="","",D22-D21) | F22: =IF(D22="","",E22*1000) | M22: =IF(B22="","",B22) | P22: =IF(O22="","",O22-O21) | Q22: =IF(O22="","",P22*1000)
E23: =IF(D23="","",D23-D22) | F23: =IF(D23="","",E23*1000) | M23: =IF(B23="","",B23) | P23: =IF(O23="","",O23-O22) | Q23: =IF(O23="","",P23*1000)
E24: =IF(D24="","",D24-D23) | F24: =IF(D24="","",E24*1000) | M24: =IF(B24="","",B24) | P24: =IF(O24="","",O24-O23) | Q24: =IF(O24="","",P24*1000)
E25: =IF(D25="","",D25-D24) | F25: =IF(D25="","",E25*1000) | M25: =IF(B25="","",B25) | N25: =IF(C25="","",C25) | P25: =IF(O25="","",O25-O24) | Q25: =IF(O25="","",P25*1000)
E26: =IF(D26="","",D26-D25) | F26: =IF(D26="","",E26*1000) | M26: =IF(B26="","",B26) | N26: =IF(C26="","",C26) | P26: =IF(O26="","",O26-O25) | Q26: =IF(O26="","",P26*1000)
E27: =SUM(E17:E26) -> 282 | F27: =SUM(F17:F26) -> 282000 | P27: =SUM(P17:P26) -> 274 | Q27: =SUM(Q17:Q26) -> 274000
B29: 2000円 | M29: 1000円
B30: 日付 | D30: 今回ﾒｰﾀｰ | E30: ﾒｰﾀｰ差 | F30: 売上 | K30: 備考 | M30: 日付 | O30: 今回ﾒｰﾀｰ | P30: ﾒｰﾀｰ差 | Q30: 売上 | V30: 備考
B31: 45986 | D31: 12998 | E31: =IF(D31="","",D31-D21) -> 90 | F31: =IF(D31="","",E31*1000) -> 90000 | M31: =IF(B31="","",B31) -> 45986 | O31: 4171 | P31: =IF(O31="","",O31-O21) -> 140 | Q31: =IF(O31="","",P31*1000) -> 140000
B32: 45994 | D32: 13060 | E32: =IF(D32="","",D32-D31) -> 62 | F32: =IF(D32="","",E32*1000) -> 62000 | M32: =IF(B32="","",B32) -> 45994 | O32: 4276 | P32: =IF(O32="","",O32-O31) -> 105 | Q32: =IF(O32="","",P32*1000) -> 105000
B33: 46001 | D33: 13092 | E33: =IF(D33="","",D33-D32) -> 32 | F33: =IF(D33="","",E33*1000) -> 32000 | M33: =IF(B33="","",B33) -> 46001 | O33: 4309 | P33: =IF(O33="","",O33-O32) -> 33 | Q33: =IF(O33="","",P33*1000) -> 33000
B34: 46008 | D34: 13168 | E34: =IF(D34="","",D34-D33) -> 76 | F34: =IF(D34="","",E34*1000) -> 76000 | M34: =IF(B34="","",B34) -> 46008 | O34: 4365 | P34: =IF(O34="","",O34-O33) -> 56 | Q34: =IF(O34="","",P34*1000) -> 56000
E35: =IF(D35="","",D35-D34) | F35: =IF(D35="","",E35*1000) | M35: =IF(B35="","",B35) | P35: =IF(O35="","",O35-O34) | Q35: =IF(O35="","",P35*1000)
E36: =IF(D36="","",D36-D35) | F36: =IF(D36="","",E36*1000) | M36: =IF(B36="","",B36) | P36: =IF(O36="","",O36-O35) | Q36: =IF(O36="","",P36*1000)
E37: =IF(D37="","",D37-D36) | F37: =IF(D37="","",E37*1000) | M37: =IF(B37="","",B37) | P37: =IF(O37="","",O37-O36) | Q37: =IF(O37="","",P37*1000)
E38: =IF(D38="","",D38-D37) | F38: =IF(D38="","",E38*1000) | M38: =IF(B38="","",B38) | P38: =IF(O38="","",O38-O37) | Q38: =IF(O38="","",P38*1000)
E39: =IF(D39="","",D39-D38) | F39: =IF(D39="","",E39*1000) | M39: =IF(B39="","",B39) | N39: =IF(C39="","",C39) | P39: =IF(O39="","",O39-O38) | Q39: =IF(O39="","",P39*1000)
E40: =IF(D40="","",D40-D39) | F40: =IF(D40="","",E40*1000) | M40: =IF(B40="","",B40) | N40: =IF(C40="","",C40) | P40: =IF(O40="","",O40-O39) | Q40: =IF(O40="","",P40*1000)
E41: =SUM(E31:E40) -> 260 | F41: =SUM(F31:F40) -> 260000 | P41: =SUM(P31:P40) -> 334 | Q41: =SUM(Q31:Q40) -> 334000
B43: 2000円 | M43: 1000円
B44: 日付 | D44: 今回ﾒｰﾀｰ | E44: ﾒｰﾀｰ差 | F44: 売上 | K44: 備考 | M44: 日付 | O44: 今回ﾒｰﾀｰ | P44: ﾒｰﾀｰ差 | Q44: 売上 | V44: 備考
B45: 46014 | D45: 13242 | E45: =IF(D45="","",D45-D34) -> 74 | F45: =IF(D45="","",E45*1000) -> 74000 | M45: =IF(B45="","",B45) -> 46014 | O45: 4461 | P45: =IF(O45="","",O45-O34) -> 96 | Q45: =IF(O45="","",P45*1000) -> 96000
B46: 46020 | D46: 13306 | E46: =IF(D46="","",D46-D45) -> 64 | F46: =IF(D46="","",E46*1000) -> 64000 | M46: =IF(B46="","",B46) -> 46020 | O46: 4501 | P46: =IF(O46="","",O46-O45) -> 40 | Q46: =IF(O46="","",P46*1000) -> 40000
B47: 46027 | D47: 13474 | E47: =IF(D47="","",D47-D46) -> 168 | F47: =IF(D47="","",E47*1000) -> 168000 | M47: =IF(B47="","",B47) -> 46027 | O47: 4599 | P47: =IF(O47="","",O47-O46) -> 98 | Q47: =IF(O47="","",P47*1000) -> 98000
B48: 46035 | D48: 13556 | E48: =IF(D48="","",D48-D47) -> 82 | F48: =IF(D48="","",E48*1000) -> 82000 | M48: =IF(B48="","",B48) -> 46035 | O48: 4704 | P48: =IF(O48="","",O48-O47) -> 105 | Q48: =IF(O48="","",P48*1000) -> 105000
B49: 46041 | D49: 13594 | E49: =IF(D49="","",D49-D48) -> 38 | F49: =IF(D49="","",E49*1000) -> 38000 | M49: =IF(B49="","",B49) -> 46041 | O49: 4751 | P49: =IF(O49="","",O49-O48) -> 47 | Q49: =IF(O49="","",P49*1000) -> 47000
E50: =IF(D50="","",D50-D49) | F50: =IF(D50="","",E50*1000) | M50: =IF(B50="","",B50) | P50: =IF(O50="","",O50-O49) | Q50: =IF(O50="","",P50*1000)
E51: =IF(D51="","",D51-D50) | F51: =IF(D51="","",E51*1000) | M51: =IF(B51="","",B51) | P51: =IF(O51="","",O51-O50) | Q51: =IF(O51="","",P51*1000)
E52: =IF(D52="","",D52-D51) | F52: =IF(D52="","",E52*1000) | M52: =IF(B52="","",B52) | P52: =IF(O52="","",O52-O51) | Q52: =IF(O52="","",P52*1000)
E53: =IF(D53="","",D53-D52) | F53: =IF(D53="","",E53*1000) | M53: =IF(B53="","",B53) | N53: =IF(C53="","",C53) | P53: =IF(O53="","",O53-O52) | Q53: =IF(O53="","",P53*1000)
E54: =IF(D54="","",D54-D53) | F54: =IF(D54="","",E54*1000) | M54: =IF(B54="","",B54) | N54: =IF(C54="","",C54) | P54: =IF(O54="","",O54-O53) | Q54: =IF(O54="","",P54*1000)
E55: =SUM(E45:E54) -> 426 | F55: =SUM(F45:F54) -> 426000 | P55: =SUM(P45:P54) -> 386 | Q55: =SUM(Q45:Q54) -> 386000
B57: 2000円 | M57: 1000円
